Workbook

Sheet Dashboard
A1: TILLMAN PROJECT DASHBOARD
A2: ="Last Updated: "&TEXT(NOW(),"MM/DD/YYYY h:mm AM/PM") -> Last Updated: 10/10/2026 1:51 PM
A4: FILTERS
A5: Area Filter: | B5: All | C5: Status Filter: | D5: All | E5: Vendor Filter: | F5: All | G5: Supervisor Filter: | H5: All
A7: KEY PERFORMANCE INDICATORS — ACTIVE PROJECTS
A9: Total Active Projects | D9: Total Planned Footage (ft) | H9: Footage Completed (ft) | L9: Footage Remaining (ft)
A10: {=SUMPRODUCT(((('Tillman UG Footage'!P2:P209="In Process")+('Tillman UG Footage'!P2:P209="Not Started")+('Tillman UG Footage'!P2:P209="Locates Called"))>0)*1*--(IF($B$5="All",TRUE,'Tillman UG Footage'!B2:B209=$B$5))*--(IF($D$5="All",TRUE,'Tillman UG Footage'!P2:P209=$D$5))*--(IF($F$5="All",TRUE,ISNUMBER(FIND($F$5,'Tillman UG Footage'!D2:D209&" "))))*--(IF($H$5="All",TRUE,ISNUMBER(FIND($H$5,'Tillman UG Footage'!F2:F209&" ")))))} -> 173 | D10: {=SUMPRODUCT(((('Tillman UG Footage'!P2:P209="In Process")+('Tillman UG Footage'!P2:P209="Not Started")+('Tillman UG Footage'!P2:P209="Locates Called"))>0)*1*--(IF($B$5="All",TRUE,'Tillman UG Footage'!B2:B209=$B$5))*--(IF($D$5="All",TRUE,'Tillman UG Footage'!P2:P209=$D$5))*--(IF($F$5="All",TRUE,ISNUMBER(FIND($F$5,'Tillman UG Footage'!D2:D209&" "))))*--(IF($H$5="All",TRUE,ISNUMBER(FIND($H$5,'Tillman UG Footage'!F2:F209&" "))))*(IF(ISNUMBER('Tillman UG Footage'!V2:V209),'Tillman UG Footage'!V2:V209,0)))} -> 1055483 | H10: {=SUMPRODUCT(((('Tillman UG Footage'!P2:P209="In Process")+('Tillman UG Footage'!P2:P209="Not Started")+('Tillman UG Footage'!P2:P209="Locates Called"))>0)*1*--(IF($B$5="All",TRUE,'Tillman UG Footage'!B2:B209=$B$5))*--(IF($D$5="All",TRUE,'Tillman UG Footage'!P2:P209=$D$5))*--(IF($F$5="All",TRUE,ISNUMBER(FIND($F$5,'Tillman UG Footage'!D2:D209&" "))))*--(IF($H$5="All",TRUE,ISNUMBER(FIND($H$5,'Tillman UG Footage'!F2:F209&" "))))*(IF(ISNUMBER('Tillman UG Footage'!W2:W209),'Tillman UG Footage'!W2:W209,0)))} -> 193973 | L10: {=SUMPRODUCT(((('Tillman UG Footage'!P2:P209="In Process")+('Tillman UG Footage'!P2:P209="Not Started")+('Tillman UG Footage'!P2:P209="Locates Called"))>0)*1*--(IF($B$5="All",TRUE,'Tillman UG Footage'!B2:B209=$B$5))*--(IF($D$5="All",TRUE,'Tillman UG Footage'!P2:P209=$D$5))*--(IF($F$5="All",TRUE,ISNUMBER(FIND($F$5,'Tillman UG Footage'!D2:D209&" "))))*--(IF($H$5="All",TRUE,ISNUMBER(FIND($H$5,'Tillman UG Footage'!F2:F209&" "))))*(IF(ISNUMBER('Tillman UG Footage'!X2:X209),'Tillman UG Footage'!X2:X209,0)))} -> 870533
A12: Overall % Complete | D12: Total SOW Est. Cost | H12: Total HHP | L12: Projects Pending PW
A13: =IFERROR(H10/D10,0) -> 0.18377653 | D13: {=SUMPRODUCT(((('Tillman UG Footage'!P2:P209="In Process")+('Tillman UG Footage'!P2:P209="Not Started")+('Tillman UG Footage'!P2:P209="Locates Called"))>0)*1*--(IF($B$5="All",TRUE,'Tillman UG Footage'!B2:B209=$B$5))*--(IF($D$5="All",TRUE,'Tillman UG Footage'!P2:P209=$D$5))*--(IF($F$5="All",TRUE,ISNUMBER(FIND($F$5,'Tillman UG Footage'!D2:D209&" "))))*--(IF($H$5="All",TRUE,ISNUMBER(FIND($H$5,'Tillman UG Footage'!F2:F209&" "))))*(IF(ISNUMBER('Tillman UG Footage'!N2:N209),'Tillman UG Footage'!N2:N209,0)))} -> 9986420.6 | H13: {=SUMPRODUCT(((('Tillman UG Footage'!P2:P209="In Process")+('Tillman UG Footage'!P2:P209="Not Started")+('Tillman UG Footage'!P2:P209="Locates Called"))>0)*1*--(IF($B$5="All",TRUE,'Tillman UG Footage'!B2:B209=$B$5))*--(IF($D$5="All",TRUE,'Tillman UG Footage'!P2:P209=$D$5))*--(IF($F$5="All",TRUE,ISNUMBER(FIND($F$5,'Tillman UG Footage'!D2:D209&" "))))*--(IF($H$5="All",TRUE,ISNUMBER(FIND($H$5,'Tillman UG Footage'!F2:F209&" "))))*(IF(ISNUMBER('Tillman UG Footage'!H2:H209),'Tillman UG Footage'!H2:H209,0)))} -> 10586 | L13: =COUNTA('Pending Resto-COP Packages'!A10:A113) -> 103
A15: PROJECTS BY AREA | F15: CONSTRUCTION STATUS | K15: PERMIT STATUS
A16: Area | B16: Projects | C16: Footage | D16: % Complete | F16: Status | G16: Count | H16: Footage | I16: Est. Cost | K16: Permit Status | L16: Count | M16: % of Total
A17: St Petersburg | B17: {=SUMPRODUCT(((('Tillman UG Footage'!P2:P209="In Process")+('Tillman UG Footage'!P2:P209="Not Started")+('Tillman UG Footage'!P2:P209="Locates Called"))>0)*1*--('Tillman UG Footage'!B2:B209="St Petersburg")*--(IF($D$5="All",TRUE,'Tillman UG Footage'!P2:P209=$D$5))*--(IF($F$5="All",TRUE,ISNUMBER(FIND($F$5,'Tillman UG Footage'!D2:D209&" "))))*--(IF($H$5="All",TRUE,ISNUMBER(FIND($H$5,'Tillman UG Footage'!F2:F209&" ")))))} -> 1 | C17: {=SUMPRODUCT(((('Tillman UG Footage'!P2:P209="In Process")+('Tillman UG Footage'!P2:P209="Not Started")+('Tillman UG Footage'!P2:P209="Locates Called"))>0)*1*--('Tillman UG Footage'!B2:B209="St Petersburg")*--(IF($D$5="All",TRUE,'Tillman UG Footage'!P2:P209=$D$5))*--(IF($F$5="All",TRUE,ISNUMBER(FIND($F$5,'Tillman UG Footage'!D2:D209&" "))))*--(IF($H$5="All",TRUE,ISNUMBER(FIND($H$5,'Tillman UG Footage'!F2:F209&" "))))*(IF(ISNUMBER('Tillman UG Footage'!V2:V209),'Tillman UG Footage'!V2:V209,0)))} -> 6182 | D17: {=IFERROR(SUMPRODUCT(((('Tillman UG Footage'!P2:P209="In Process")+('Tillman UG Footage'!P2:P209="Not Started")+('Tillman UG Footage'!P2:P209="Locates Called"))>0)*1*--('Tillman UG Footage'!B2:B209="St Petersburg")*--(IF($D$5="All",TRUE,'Tillman UG Footage'!P2:P209=$D$5))*--(IF($F$5="All",TRUE,ISNUMBER(FIND($F$5,'Tillman UG Footage'!D2:D209&" "))))*--(IF($H$5="All",TRUE,ISNUMBER(FIND($H$5,'Tillman UG Footage'!F2:F209&" "))))*(IF(ISNUMBER('Tillman UG Footage'!W2:W209),'Tillman UG Footage'!W2:W209,0)))/C17,0)} -> 0.95422193 | F17: In Process | G17: {=SUMPRODUCT(--(IF($B$5="All",TRUE,'Tillman UG Footage'!B2:B209=$B$5))*--('Tillman UG Footage'!P2:P209="In Process")*--(IF($F$5="All",TRUE,ISNUMBER(FIND($F$5,'Tillman UG Footage'!D2:D209&" "))))*--(IF($H$5="All",TRUE,ISNUMBER(FIND($H$5,'Tillman UG Footage'!F2:F209&" ")))))} -> 30 | H17: {=SUMPRODUCT(--(IF($B$5="All",TRUE,'Tillman UG Footage'!B2:B209=$B$5))*--('Tillman UG Footage'!P2:P209="In Process")*--(IF($F$5="All",TRUE,ISNUMBER(FIND($F$5,'Tillman UG Footage'!D2:D209&" "))))*--(IF($H$5="All",TRUE,ISNUMBER(FIND($H$5,'Tillman UG Footage'!F2:F209&" "))))*(IF(ISNUMBER('Tillman UG Footage'!V2:V209),'Tillman UG Footage'!V2:V209,0)))} -> 201366 | I17: {=SUMPRODUCT(--(IF($B$5="All",TRUE,'Tillman UG Footage'!B2:B209=$B$5))*--('Tillman UG Footage'!P2:P209="In Process")*--(IF($F$5="All",TRUE,ISNUMBER(FIND($F$5,'Tillman UG Footage'!D2:D209&" "))))*--(IF($H$5="All",TRUE,ISNUMBER(FIND($H$5,'Tillman UG Footage'!F2:F209&" "))))*(IF(ISNUMBER('Tillman UG Footage'!N2:N209),'Tillman UG Footage'!N2:N209,0)))} -> 1781324.4 | K17: Received | L17: {=SUMPRODUCT(((('Tillman UG Footage'!P2:P209="In Process")+('Tillman UG Footage'!P2:P209="Not Started")+('Tillman UG Footage'!P2:P209="Locates Called"))>0)*1*--(IF($B$5="All",TRUE,'Tillman UG Footage'!B2:B209=$B$5))*--(IF($D$5="All",TRUE,'Tillman UG Footage'!P2:P209=$D$5))*--(IF($F$5="All",TRUE,ISNUMBER(FIND($F$5,'Tillman UG Footage'!D2:D209&" "))))*--(IF($H$5="All",TRUE,ISNUMBER(FIND($H$5,'Tillman UG Footage'!F2:F209&" "))))*--('Tillman UG Footage'!J2:J209="Received"))} -> 98 | M17: =IFERROR(L17/SUM(L17:L19),0) -> 0.56647399
A18: Lakeland | B18: {=SUMPRODUCT(((('Tillman UG Footage'!P2:P209="In Process")+('Tillman UG Footage'!P2:P209="Not Started")+('Tillman UG Footage'!P2:P209="Locates Called"))>0)*1*--('Tillman UG Footage'!B2:B209="Lakeland")*--(IF($D$5="All",TRUE,'Tillman UG Footage'!P2:P209=$D$5))*--(IF($F$5="All",TRUE,ISNUMBER(FIND($F$5,'Tillman UG Footage'!D2:D209&" "))))*--(IF($H$5="All",TRUE,ISNUMBER(FIND($H$5,'Tillman UG Footage'!F2:F209&" ")))))} -> 2 | C18: {=SUMPRODUCT(((('Tillman UG Footage'!P2:P209="In Process")+('Tillman UG Footage'!P2:P209="Not Started")+('Tillman UG Footage'!P2:P209="Locates Called"))>0)*1*--('Tillman UG Footage'!B2:B209="Lakeland")*--(IF($D$5="All",TRUE,'Tillman UG Footage'!P2:P209=$D$5))*--(IF($F$5="All",TRUE,ISNUMBER(FIND($F$5,'Tillman UG Footage'!D2:D209&" "))))*--(IF($H$5="All",TRUE,ISNUMBER(FIND($H$5,'Tillman UG Footage'!F2:F209&" "))))*(IF(ISNUMBER('Tillman UG Footage'!V2:V209),'Tillman UG Footage'!V2:V209,0)))} -> 4107 | D18: {=IFERROR(SUMPRODUCT(((('Tillman UG Footage'!P2:P209="In Process")+('Tillman UG Footage'!P2:P209="Not Started")+('Tillman UG Footage'!P2:P209="Locates Called"))>0)*1*--('Tillman UG Footage'!B2:B209="Lakeland")*--(IF($D$5="All",TRUE,'Tillman UG Footage'!P2:P209=$D$5))*--(IF($F$5="All",TRUE,ISNUMBER(FIND($F$5,'Tillman UG Footage'!D2:D209&" "))))*--(IF($H$5="All",TRUE,ISNUMBER(FIND($H$5,'Tillman UG Footage'!F2:F209&" "))))*(IF(ISNUMBER('Tillman UG Footage'!W2:W209),'Tillman UG Footage'!W2:W209,0)))/C18,0)} -> 0.95641588 | F18: Not Started | G18: {=SUMPRODUCT(--(IF($B$5="All",TRUE,'Tillman UG Footage'!B2:B209=$B$5))*--('Tillman UG Footage'!P2:P209="Not Started")*--(IF($F$5="All",TRUE,ISNUMBER(FIND($F$5,'Tillman UG Footage'!D2:D209&" "))))*--(IF($H$5="All",TRUE,ISNUMBER(FIND($H$5,'Tillman UG Footage'!F2:F209&" ")))))} -> 92 | H18: {=SUMPRODUCT(--(IF($B$5="All",TRUE,'Tillman UG Footage'!B2:B209=$B$5))*--('Tillman UG Footage'!P2:P209="Not Started")*--(IF($F$5="All",TRUE,ISNUMBER(FIND($F$5,'Tillman UG Footage'!D2:D209&" "))))*--(IF($H$5="All",TRUE,ISNUMBER(FIND($H$5,'Tillman UG Footage'!F2:F209&" "))))*(IF(ISNUMBER('Tillman UG Footage'!V2:V209),'Tillman UG Footage'!V2:V209,0)))} -> 534834 | I18: {=SUMPRODUCT(--(IF($B$5="All",TRUE,'Tillman UG Footage'!B2:B209=$B$5))*--('Tillman UG Footage'!P2:P209="Not Started")*--(IF($F$5="All",TRUE,ISNUMBER(FIND($F$5,'Tillman UG Footage'!D2:D209&" "))))*--(IF($H$5="All",TRUE,ISNUMBER(FIND($H$5,'Tillman UG Footage'!F2:F209&" "))))*(IF(ISNUMBER('Tillman UG Footage'!N2:N209),'Tillman UG Footage'!N2:N209,0)))} -> 4613883.2 | K18: Pending | L18: {=SUMPRODUCT(((('Tillman UG Footage'!P2:P209="In Process")+('Tillman UG Footage'!P2:P209="Not Started")+('Tillman UG Footage'!P2:P209="Locates Called"))>0)*1*--(IF($B$5="All",TRUE,'Tillman UG Footage'!B2:B209=$B$5))*--(IF($D$5="All",TRUE,'Tillman UG Footage'!P2:P209=$D$5))*--(IF($F$5="All",TRUE,ISNUMBER(FIND($F$5,'Tillman UG Footage'!D2:D209&" "))))*--(IF($H$5="All",TRUE,ISNUMBER(FIND($H$5,'Tillman UG Footage'!F2:F209&" "))))*--('Tillman UG Footage'!J2:J209="Pending"))} -> 73 | M18: =IFERROR(L18/SUM(L17:L19),0) -> 0.42196532
A19: Bradenton | B19: {=SUMPRODUCT(((('Tillman UG Footage'!P2:P209="In Process")+('Tillman UG Footage'!P2:P209="Not Started")+('Tillman UG Footage'!P2:P209="Locates Called"))>0)*1*--('Tillman UG Footage'!B2:B209="Bradenton")*--(IF($D$5="All",TRUE,'Tillman UG Footage'!P2:P209=$D$5))*--(IF($F$5="All",TRUE,ISNUMBER(FIND($F$5,'Tillman UG Footage'!D2:D209&" "))))*--(IF($H$5="All",TRUE,ISNUMBER(FIND($H$5,'Tillman UG Footage'!F2:F209&" ")))))} -> 11 | C19: {=SUMPRODUCT(((('Tillman UG Footage'!P2:P209="In Process")+('Tillman UG Footage'!P2:P209="Not Started")+('Tillman UG Footage'!P2:P209="Locates Called"))>0)*1*--('Tillman UG Footage'!B2:B209="Bradenton")*--(IF($D$5="All",TRUE,'Tillman UG Footage'!P2:P209=$D$5))*--(IF($F$5="All",TRUE,ISNUMBER(FIND($F$5,'Tillman UG Footage'!D2:D209&" "))))*--(IF($H$5="All",TRUE,ISNUMBER(FIND($H$5,'Tillman UG Footage'!F2:F209&" "))))*(IF(ISNUMBER('Tillman UG Footage'!V2:V209),'Tillman UG Footage'!V2:V209,0)))} -> 52836 | D19: {=IFERROR(SUMPRODUCT(((('Tillman UG Footage'!P2:P209="In Process")+('Tillman UG Footage'!P2:P209="Not Started")+('Tillman UG Footage'!P2:P209="Locates Called"))>0)*1*--('Tillman UG Footage'!B2:B209="Bradenton")*--(IF($D$5="All",TRUE,'Tillman UG Footage'!P2:P209=$D$5))*--(IF($F$5="All",TRUE,ISNUMBER(FIND($F$5,'Tillman UG Footage'!D2:D209&" "))))*--(IF($H$5="All",TRUE,ISNUMBER(FIND($H$5,'Tillman UG Footage'!F2:F209&" "))))*(IF(ISNUMBER('Tillman UG Footage'!W2:W209),'Tillman UG Footage'!W2:W209,0)))/C19,0)} -> 0.20232417 | F19: Locates Called | G19: {=SUMPRODUCT(--(IF($B$5="All",TRUE,'Tillman UG Footage'!B2:B209=$B$5))*--('Tillman UG Footage'!P2:P209="Locates Called")*--(IF($F$5="All",TRUE,ISNUMBER(FIND($F$5,'Tillman UG Footage'!D2:D209&" "))))*--(IF($H$5="All",TRUE,ISNUMBER(FIND($H$5,'Tillman UG Footage'!F2:F209&" ")))))} -> 51 | H19: {=SUMPRODUCT(--(IF($B$5="All",TRUE,'Tillman UG Footage'!B2:B209=$B$5))*--('Tillman UG Footage'!P2:P209="Locates Called")*--(IF($F$5="All",TRUE,ISNUMBER(FIND($F$5,'Tillman UG Footage'!D2:D209&" "))))*--(IF($H$5="All",TRUE,ISNUMBER(FIND($H$5,'Tillman UG Footage'!F2:F209&" "))))*(IF(ISNUMBER('Tillman UG Footage'!V2:V209),'Tillman UG Footage'!V2:V209,0)))} -> 319283 | I19: {=SUMPRODUCT(--(IF($B$5="All",TRUE,'Tillman UG Footage'!B2:B209=$B$5))*--('Tillman UG Footage'!P2:P209="Locates Called")*--(IF($F$5="All",TRUE,ISNUMBER(FIND($F$5,'Tillman UG Footage'!D2:D209&" "))))*--(IF($H$5="All",TRUE,ISNUMBER(FIND($H$5,'Tillman UG Footage'!F2:F209&" "))))*(IF(ISNUMBER('Tillman UG Footage'!N2:N209),'Tillman UG Footage'!N2:N209,0)))} -> 3591212.8 | K19: Not Required | L19: {=SUMPRODUCT(((('Tillman UG Footage'!P2:P209="In Process")+('Tillman UG Footage'!P2:P209="Not Started")+('Tillman UG Footage'!P2:P209="Locates Called"))>0)*1*--(IF($B$5="All",TRUE,'Tillman UG Footage'!B2:B209=$B$5))*--(IF($D$5="All",TRUE,'Tillman UG Footage'!P2:P209=$D$5))*--(IF($F$5="All",TRUE,ISNUMBER(FIND($F$5,'Tillman UG Footage'!D2:D209&" "))))*--(IF($H$5="All",TRUE,ISNUMBER(FIND($H$5,'Tillman UG Footage'!F2:F209&" "))))*--('Tillman UG Footage'!J2:J209="Not Required"))} -> 2 | M19: =IFERROR(L19/SUM(L17:L19),0) -> 0.011560694
A20: Fort Myers | B20: {=SUMPRODUCT(((('Tillman UG Footage'!P2:P209="In Process")+('Tillman UG Footage'!P2:P209="Not Started")+('Tillman UG Footage'!P2:P209="Locates Called"))>0)*1*--('Tillman UG Footage'!B2:B209="Fort Myers")*--(IF($D$5="All",TRUE,'Tillman UG Footage'!P2:P209=$D$5))*--(IF($F$5="All",TRUE,ISNUMBER(FIND($F$5,'Tillman UG Footage'!D2:D209&" "))))*--(IF($H$5="All",TRUE,ISNUMBER(FIND($H$5,'Tillman UG Footage'!F2:F209&" ")))))} -> 26 | C20: {=SUMPRODUCT(((('Tillman UG Footage'!P2:P209="In Process")+('Tillman UG Footage'!P2:P209="Not Started")+('Tillman UG Footage'!P2:P209="Locates Called"))>0)*1*--('Tillman UG Footage'!B2:B209="Fort Myers")*--(IF($D$5="All",TRUE,'Tillman UG Footage'!P2:P209=$D$5))*--(IF($F$5="All",TRUE,ISNUMBER(FIND($F$5,'Tillman UG Footage'!D2:D209&" "))))*--(IF($H$5="All",TRUE,ISNUMBER(FIND($H$5,'Tillman UG Footage'!F2:F209&" "))))*(IF(ISNUMBER('Tillman UG Footage'!V2:V209),'Tillman UG Footage'!V2:V209,0)))} -> 169836 | D20: {=IFERROR(SUMPRODUCT(((('Tillman UG Footage'!P2:P209="In Process")+('Tillman UG Footage'!P2:P209="Not Started")+('Tillman UG Footage'!P2:P209="Locates Called"))>0)*1*--('Tillman UG Footage'!B2:B209="Fort Myers")*--(IF($D$5="All",TRUE,'Tillman UG Footage'!P2:P209=$D$5))*--(IF($F$5="All",TRUE,ISNUMBER(FIND($F$5,'Tillman UG Footage'!D2:D209&" "))))*--(IF($H$5="All",TRUE,ISNUMBER(FIND($H$5,'Tillman UG Footage'!F2:F209&" "))))*(IF(ISNUMBER('Tillman UG Footage'!W2:W209),'Tillman UG Footage'!W2:W209,0)))/C20,0)} -> 0.36343296 | F20: Completed | G20: {=SUMPRODUCT(--(IF($B$5="All",TRUE,'Tillman UG Footage'!B2:B209=$B$5))*--('Tillman UG Footage'!P2:P209="Completed")*--(IF($F$5="All",TRUE,ISNUMBER(FIND($F$5,'Tillman UG Footage'!D2:D209&" "))))*--(IF($H$5="All",TRUE,ISNUMBER(FIND($H$5,'Tillman UG Footage'!F2:F209&" ")))))} -> 6 | H20: {=SUMPRODUCT(--(IF($B$5="All",TRUE,'Tillman UG Footage'!B2:B209=$B$5))*--('Tillman UG Footage'!P2:P209="Completed")*--(IF($F$5="All",TRUE,ISNUMBER(FIND($F$5,'Tillman UG Footage'!D2:D209&" "))))*--(IF($H$5="All",TRUE,ISNUMBER(FIND($H$5,'Tillman UG Footage'!F2:F209&" "))))*IF(ISNUMBER('Tillman UG Footage'!V2:V209),'Tillman UG Footage'!V2:V209,0))} -> 47138 | I20: {=SUMPRODUCT(--(IF($B$5="All",TRUE,'Tillman UG Footage'!B2:B209=$B$5))*--('Tillman UG Footage'!P2:P209="Completed")*--(IF($F$5="All",TRUE,ISNUMBER(FIND($F$5,'Tillman UG Footage'!D2:D209&" "))))*--(IF($H$5="All",TRUE,ISNUMBER(FIND($H$5,'Tillman UG Footage'!F2:F209&" "))))*IF(ISNUMBER('Tillman UG Footage'!N2:N209),'Tillman UG Footage'!N2:N209,0))} -> 572325 | K20: TOTAL | L20: =SUM(L17:L19) -> 173 | M20: 1
A21: Port Charlotte | B21: {=SUMPRODUCT(((('Tillman UG Footage'!P2:P209="In Process")+('Tillman UG Footage'!P2:P209="Not Started")+('Tillman UG Footage'!P2:P209="Locates Called"))>0)*1*--('Tillman UG Footage'!B2:B209="Port Charlotte")*--(IF($D$5="All",TRUE,'Tillman UG Footage'!P2:P209=$D$5))*--(IF($F$5="All",TRUE,ISNUMBER(FIND($F$5,'Tillman UG Footage'!D2:D209&" "))))*--(IF($H$5="All",TRUE,ISNUMBER(FIND($H$5,'Tillman UG Footage'!F2:F209&" ")))))} -> 4 | C21: {=SUMPRODUCT(((('Tillman UG Footage'!P2:P209="In Process")+('Tillman UG Footage'!P2:P209="Not Started")+('Tillman UG Footage'!P2:P209="Locates Called"))>0)*1*--('Tillman UG Footage'!B2:B209="Port Charlotte")*--(IF($D$5="All",TRUE,'Tillman UG Footage'!P2:P209=$D$5))*--(IF($F$5="All",TRUE,ISNUMBER(FIND($F$5,'Tillman UG Footage'!D2:D209&" "))))*--(IF($H$5="All",TRUE,ISNUMBER(FIND($H$5,'Tillman UG Footage'!F2:F209&" "))))*(IF(ISNUMBER('Tillman UG Footage'!V2:V209),'Tillman UG Footage'!V2:V209,0)))} -> 10662 | D21: {=IFERROR(SUMPRODUCT(((('Tillman UG Footage'!P2:P209="In Process")+('Tillman UG Footage'!P2:P209="Not Started")+('Tillman UG Footage'!P2:P209="Locates Called"))>0)*1*--('Tillman UG Footage'!B2:B209="Port Charlotte")*--(IF($D$5="All",TRUE,'Tillman UG Footage'!P2:P209=$D$5))*--(IF($F$5="All",TRUE,ISNUMBER(FIND($F$5,'Tillman UG Footage'!D2:D209&" "))))*--(IF($H$5="All",TRUE,ISNUMBER(FIND($H$5,'Tillman UG Footage'!F2:F209&" "))))*(IF(ISNUMBER('Tillman UG Footage'!W2:W209),'Tillman UG Footage'!W2:W209,0)))/C21,0)} -> 0.55946352 | F21: TOTAL | G21: =SUM(G17:G20) -> 179 | H21: =SUM(H17:H20) -> 1102621 | I21: =SUM(I17:I20) -> 10558746
A22: Naples | B22: {=SUMPRODUCT(((('Tillman UG Footage'!P2:P209="In Process")+('Tillman UG Footage'!P2:P209="Not Started")+('Tillman UG Footage'!P2:P209="Locates Called"))>0)*1*--('Tillman UG Footage'!B2:B209="Naples")*--(IF($D$5="All",TRUE,'Tillman UG Footage'!P2:P209=$D$5))*--(IF($F$5="All",TRUE,ISNUMBER(FIND($F$5,'Tillman UG Footage'!D2:D209&" "))))*--(IF($H$5="All",TRUE,ISNUMBER(FIND($H$5,'Tillman UG Footage'!F2:F209&" ")))))} -> 0 | C22: {=SUMPRODUCT(((('Tillman UG Footage'!P2:P209="In Process")+('Tillman UG Footage'!P2:P209="Not Started")+('Tillman UG Footage'!P2:P209="Locates Called"))>0)*1*--('Tillman UG Footage'!B2:B209="Naples")*--(IF($D$5="All",TRUE,'Tillman UG Footage'!P2:P209=$D$5))*--(IF($F$5="All",TRUE,ISNUMBER(FIND($F$5,'Tillman UG Footage'!D2:D209&" "))))*--(IF($H$5="All",TRUE,ISNUMBER(FIND($H$5,'Tillman UG Footage'!F2:F209&" "))))*(IF(ISNUMBER('Tillman UG Footage'!V2:V209),'Tillman UG Footage'!V2:V209,0)))} -> 0 | D22: {=IFERROR(SUMPRODUCT(((('Tillman UG Footage'!P2:P209="In Process")+('Tillman UG Footage'!P2:P209="Not Started")+('Tillman UG Footage'!P2:P209="Locates Called"))>0)*1*--('Tillman UG Footage'!B2:B209="Naples")*--(IF($D$5="All",TRUE,'Tillman UG Footage'!P2:P209=$D$5))*--(IF($F$5="All",TRUE,ISNUMBER(FIND($F$5,'Tillman UG Footage'!D2:D209&" "))))*--(IF($H$5="All",TRUE,ISNUMBER(FIND($H$5,'Tillman UG Footage'!F2:F209&" "))))*(IF(ISNUMBER('Tillman UG Footage'!W2:W209),'Tillman UG Footage'!W2:W209,0)))/C22,0)} -> 0
A23: Kissimmee | B23: {=SUMPRODUCT(((('Tillman UG Footage'!P2:P209="In Process")+('Tillman UG Footage'!P2:P209="Not Started")+('Tillman UG Footage'!P2:P209="Locates Called"))>0)*1*--('Tillman UG Footage'!B2:B209="Kissimmee")*--(IF($D$5="All",TRUE,'Tillman UG Footage'!P2:P209=$D$5))*--(IF($F$5="All",TRUE,ISNUMBER(FIND($F$5,'Tillman UG Footage'!D2:D209&" "))))*--(IF($H$5="All",TRUE,ISNUMBER(FIND($H$5,'Tillman UG Footage'!F2:F209&" ")))))} -> 54 | C23: {=SUMPRODUCT(((('Tillman UG Footage'!P2:P209="In Process")+('Tillman UG Footage'!P2:P209="Not Started")+('Tillman UG Footage'!P2:P209="Locates Called"))>0)*1*--('Tillman UG Footage'!B2:B209="Kissimmee")*--(IF($D$5="All",TRUE,'Tillman UG Footage'!P2:P209=$D$5))*--(IF($F$5="All",TRUE,ISNUMBER(FIND($F$5,'Tillman UG Footage'!D2:D209&" "))))*--(IF($H$5="All",TRUE,ISNUMBER(FIND($H$5,'Tillman UG Footage'!F2:F209&" "))))*(IF(ISNUMBER('Tillman UG Footage'!V2:V209),'Tillman UG Footage'!V2:V209,0)))} -> 379857 | D23: {=IFERROR(SUMPRODUCT(((('Tillman UG Footage'!P2:P209="In Process")+('Tillman UG Footage'!P2:P209="Not Started")+('Tillman UG Footage'!P2:P209="Locates Called"))>0)*1*--('Tillman UG Footage'!B2:B209="Kissimmee")*--(IF($D$5="All",TRUE,'Tillman UG Footage'!P2:P209=$D$5))*--(IF($F$5="All",TRUE,ISNUMBER(FIND($F$5,'Tillman UG Footage'!D2:D209&" "))))*--(IF($H$5="All",TRUE,ISNUMBER(FIND($H$5,'Tillman UG Footage'!F2:F209&" "))))*(IF(ISNUMBER('Tillman UG Footage'!W2:W209),'Tillman UG Footage'!W2:W209,0)))/C23,0)} -> 0.038611899
A24: Miami | B24: {=SUMPRODUCT(((('Tillman UG Footage'!P2:P209="In Process")+('Tillman UG Footage'!P2:P209="Not Started")+('Tillman UG Footage'!P2:P209="Locates Called"))>0)*1*--('Tillman UG Footage'!B2:B209="Miami")*--(IF($D$5="All",TRUE,'Tillman UG Footage'!P2:P209=$D$5))*--(IF($F$5="All",TRUE,ISNUMBER(FIND($F$5,'Tillman UG Footage'!D2:D209&" "))))*--(IF($H$5="All",TRUE,ISNUMBER(FIND($H$5,'Tillman UG Footage'!F2:F209&" ")))))} -> 2 | C24: {=SUMPRODUCT(((('Tillman UG Footage'!P2:P209="In Process")+('Tillman UG Footage'!P2:P209="Not Started")+('Tillman UG Footage'!P2:P209="Locates Called"))>0)*1*--('Tillman UG Footage'!B2:B209="Miami")*--(IF($D$5="All",TRUE,'Tillman UG Footage'!P2:P209=$D$5))*--(IF($F$5="All",TRUE,ISNUMBER(FIND($F$5,'Tillman UG Footage'!D2:D209&" "))))*--(IF($H$5="All",TRUE,ISNUMBER(FIND($H$5,'Tillman UG Footage'!F2:F209&" "))))*(IF(ISNUMBER('Tillman UG Footage'!V2:V209),'Tillman UG Footage'!V2:V209,0)))} -> 16213 | D24: {=IFERROR(SUMPRODUCT(((('Tillman UG Footage'!P2:P209="In Process")+('Tillman UG Footage'!P2:P209="Not Started")+('Tillman UG Footage'!P2:P209="Locates Called"))>0)*1*--('Tillman UG Footage'!B2:B209="Miami")*--(IF($D$5="All",TRUE,'Tillman UG Footage'!P2:P209=$D$5))*--(IF($F$5="All",TRUE,ISNUMBER(FIND($F$5,'Tillman UG Footage'!D2:D209&" "))))*--(IF($H$5="All",TRUE,ISNUMBER(FIND($H$5,'Tillman UG Footage'!F2:F209&" "))))*(IF(ISNUMBER('Tillman UG Footage'!W2:W209),'Tillman UG Footage'!W2:W209,0)))/C24,0)} -> 0.84086844
A25: Pinellas | B25: {=SUMPRODUCT(((('Tillman UG Footage'!P2:P209="In Process")+('Tillman UG Footage'!P2:P209="Not Started")+('Tillman UG Footage'!P2:P209="Locates Called"))>0)*1*--('Tillman UG Footage'!B2:B209="Pinellas")*--(IF($D$5="All",TRUE,'Tillman UG Footage'!P2:P209=$D$5))*--(IF($F$5="All",TRUE,ISNUMBER(FIND($F$5,'Tillman UG Footage'!D2:D209&" "))))*--(IF($H$5="All",TRUE,ISNUMBER(FIND($H$5,'Tillman UG Footage'!F2:F209&" ")))))} -> 30 | C25: {=SUMPRODUCT(((('Tillman UG Footage'!P2:P209="In Process")+('Tillman UG Footage'!P2:P209="Not Started")+('Tillman UG Footage'!P2:P209="Locates Called"))>0)*1*--('Tillman UG Footage'!B2:B209="Pinellas")*--(IF($D$5="All",TRUE,'Tillman UG Footage'!P2:P209=$D$5))*--(IF($F$5="All",TRUE,ISNUMBER(FIND($F$5,'Tillman UG Footage'!D2:D209&" "))))*--(IF($H$5="All",TRUE,ISNUMBER(FIND($H$5,'Tillman UG Footage'!F2:F209&" "))))*(IF(ISNUMBER('Tillman UG Footage'!V2:V209),'Tillman UG Footage'!V2:V209,0)))} -> 177702 | D25: {=IFERROR(SUMPRODUCT(((('Tillman UG Footage'!P2:P209="In Process")+('Tillman UG Footage'!P2:P209="Not Started")+('Tillman UG Footage'!P2:P209="Locates Called"))>0)*1*--('Tillman UG Footage'!B2:B209="Pinellas")*--(IF($D$5="All",TRUE,'Tillman UG Footage'!P2:P209=$D$5))*--(IF($F$5="All",TRUE,ISNUMBER(FIND($F$5,'Tillman UG Footage'!D2:D209&" "))))*--(IF($H$5="All",TRUE,ISNUMBER(FIND($H$5,'Tillman UG Footage'!F2:F209&" "))))*(IF(ISNUMBER('Tillman UG Footage'!W2:W209),'Tillman UG Footage'!W2:W209,0)))/C25,0)} -> 0.080032864
A26: TOTAL | B26: =SUM(B17:B25) -> 130 | C26: =SUM(C17:C25) -> 817395 | D26: =IFERROR(H10/D10,0) -> 0.18377653
A28: TOP VENDORS | F28: SUPERVISOR ASSIGNMENTS | R28: HELPER – Vendors (auto) | S28: Active | T28: Completed | U28: Total
A29: Vendor | B29: Active | C29: Completed | D29: Total | F29: Supervisor | G29: Active | H29: Completed | I29: Total | R29: {=_xlfn._xlws.SORT(_xlfn.UNIQUE(_xlfn.VSTACK(_xlfn._xlws.FILTER(TRIM('Tillman UG Footage'!D2:D209),(TRIM('Tillman UG Footage'!D2:D209)<>"")*(TRIM('Tillman UG Footage'!D2:D209)<>"Vendor Assignment")),_xlfn._xlws.FILTER(TRIM('Pending Resto-COP Packages'!D2:D101),(TRIM('Pending Resto-COP Packages'!D2:D101)<>"")*(TRIM('Pending Resto-COP Packages'!D2:D101)<>"Vendor Assignment")))))} -> A1 Broadband | S29: {=_xlfn.BYROW(_xlfn.ANCHORARRAY(R29),_xlfn.LAMBDA(_xlpm.v,COUNTIF('Tillman UG Footage'!D:D,"*"&_xlpm.v&"*")))} -> 2 | T29: {=_xlfn.BYROW(_xlfn.ANCHORARRAY(R29),_xlfn.LAMBDA(_xlpm.v,COUNTIF('Pending Resto-COP Packages'!D:D,"*"&_xlpm.v&"*")))} -> 1 | U29: {=_xlfn.ANCHORARRAY(S29)+_xlfn.ANCHORARRAY(T29)} -> 3
A30: Lightspeed In-House | B30: =COUNTIF('Tillman UG Footage'!D:D,"*Lightspeed*") -> 2 | C30: =COUNTIF('Pending Resto-COP Packages'!D:D,"*Lightspeed*") -> 15 | D30: =B30+C30 -> 17 | F30: Joshua | G30: =COUNTIFS('Tillman UG Footage'!F:F,"*"&F30&"*",'Tillman UG Footage'!B:B,"<>AREA") -> 26 | H30: =COUNTIF('Pending Resto-COP Packages'!F:F,"*"&F30&"*") -> 41 | I30: =G30+H30 -> 67 | R30: AG QUALITY | S30: 1 | T30: 0 | U30: 1
A31: GN Systems | B31: =COUNTIF('Tillman UG Footage'!D:D,"*GN Systems*") -> 4 | C31: =COUNTIF('Pending Resto-COP Packages'!D:D,"*GN Systems*") -> 6 | D31: =B31+C31 -> 10 | F31: Cody | G31: =COUNTIFS('Tillman UG Footage'!F:F,"*"&F31&"*",'Tillman UG Footage'!B:B,"<>AREA") -> 1 | H31: =COUNTIF('Pending Resto-COP Packages'!F:F,"*"&F31&"*") -> 3 | I31: =G31+H31 -> 4 | R31: AGN | S31: 6 | T31: 5 | U31: 11
A32: North Path | B32: =COUNTIF('Tillman UG Footage'!D:D,"*North Path*") -> 10 | C32: =COUNTIF('Pending Resto-COP Packages'!D:D,"*North Path*") -> 8 | D32: =B32+C32 -> 18 | F32: Travis | G32: =COUNTIFS('Tillman UG Footage'!F:F,"*"&F32&"*",'Tillman UG Footage'!B:B,"<>AREA") -> 0 | H32: =COUNTIF('Pending Resto-COP Packages'!F:F,"*"&F32&"*") -> 0 | I32: =G32+H32 -> 0 | R32: AGN Undergrounds | S32: 2 | T32: 0 | U32: 2
A33: Brothers | B33: =COUNTIF('Tillman UG Footage'!D:D,"*Brother*") -> 8 | C33: =COUNTIF('Pending Resto-COP Packages'!D:D,"*Brother*") -> 16 | D33: =B33+C33 -> 24 | F33: Johnnie | G33: =COUNTIFS('Tillman UG Footage'!F:F,"*"&F33&"*",'Tillman UG Footage'!B:B,"<>AREA") -> 6 | H33: =COUNTIF('Pending Resto-COP Packages'!F:F,"*"&F33&"*") -> 10 | I33: =G33+H33 -> 16 | R33: Alpha Omega | S33: 3 | T33: 2 | U33: 5
A34: Kattle One | B34: =COUNTIF('Tillman UG Footage'!D:D,"*Kattle One*") -> 5 | C34: =COUNTIF('Pending Resto-COP Packages'!D:D,"*Kattle One*") -> 0 | D34: =B34+C34 -> 5 | F34: Miguel | G34: =COUNTIFS('Tillman UG Footage'!F:F,"*"&F34&"*",'Tillman UG Footage'!B:B,"<>AREA") -> 7 | H34: =COUNTIF('Pending Resto-COP Packages'!F:F,"*"&F34&"*") -> 2 | I34: =G34+H34 -> 9 | R34: AMB Communications | S34: 3 | T34: 0 | U34: 3
A35: Yosep AER | B35: =COUNTIF('Tillman UG Footage'!D:D,"*Yosep AER*") -> 2 | C35: =COUNTIF('Pending Resto-COP Packages'!D:D,"*Yosep AER*") -> 7 | D35: =B35+C35 -> 9 | F35: Eric | G35: =COUNTIFS('Tillman UG Footage'!F:F,"*"&F35&"*",'Tillman UG Footage'!B:B,"<>AREA") -> 1 | H35: =COUNTIF('Pending Resto-COP Packages'!F:F,"*"&F35&"*") -> 0 | I35: =G35+H35 -> 1 | R35: APT Communications | S35: 4 | T35: 3 | U35: 7
A36: APT Communications | B36: =COUNTIF('Tillman UG Footage'!D:D,"*APT Communications*") -> 4 | C36: =COUNTIF('Pending Resto-COP Packages'!D:D,"*APT Communications*") -> 3 | D36: =B36+C36 -> 7 | F36: Anthony | G36: =COUNTIFS('Tillman UG Footage'!F:F,"*"&F36&"*",'Tillman UG Footage'!B:B,"<>AREA") -> 4 | H36: =COUNTIF('Pending Resto-COP Packages'!F:F,"*"&F36&"*") -> 11 | I36: =G36+H36 -> 15 | R36: APT Communications / New Gen Unlimited | S36: 1 | T36: 0 | U36: 1
A37: Lopez Underground | B37: =COUNTIF('Tillman UG Footage'!D:D,"*Lopez*") -> 7 | C37: =COUNTIF('Pending Resto-COP Packages'!D:D,"*Lopez*") -> 16 | D37: =B37+C37 -> 23 | F37: James | G37: =COUNTIFS('Tillman UG Footage'!F:F,"*"&F37&"*",'Tillman UG Footage'!B:B,"<>AREA") -> 0 | H37: =COUNTIF('Pending Resto-COP Packages'!F:F,"*"&F37&"*") -> 0 | I37: =G37+H37 -> 0 | R37: APT Communications/Kattleone | S37: 0 | T37: 1 | U37: 1
A38: Power Connect | B38: =COUNTIF('Tillman UG Footage'!D:D,"*Power Connect*") -> 7 | C38: =COUNTIF('Pending Resto-COP Packages'!D:D,"*Power Connect*") -> 5 | D38: =B38+C38 -> 12 | F38: Marcelo | G38: =COUNTIFS('Tillman UG Footage'!F:F,"*"&F38&"*",'Tillman UG Footage'!B:B,"<>AREA") -> 1 | H38: =COUNTIF('Pending Resto-COP Packages'!F:F,"*"&F38&"*") -> 5 | I38: =G38+H38 -> 6 | R38: APT Communications/North Path | S38: 1 | T38: 0 | U38: 1
A39: HAS Global | B39: =COUNTIF('Tillman UG Footage'!D:D,"*HAS Global*") -> 1 | C39: =COUNTIF('Pending Resto-COP Packages'!D:D,"*HAS Global*") -> 2 | D39: =B39+C39 -> 3 | F39: Matthew Nunes | G39: =COUNTIFS('Tillman UG Footage'!F:F,"*"&F39&"*",'Tillman UG Footage'!B:B,"<>AREA") -> 2 | H39: =COUNTIF('Pending Resto-COP Packages'!F:F,"*"&F39&"*") -> 6 | I39: =G39+H39 -> 8 | R39: ASM | S39: 3 | T39: 4 | U39: 7
A40: Legant | B40: =COUNTIF('Tillman UG Footage'!D:D,"*Legant*") -> 4 | C40: =COUNTIF('Pending Resto-COP Packages'!D:D,"*Legant*") -> 2 | D40: =B40+C40 -> 6 | F40: Treyvon | G40: =COUNTIFS('Tillman UG Footage'!F:F,"*"&F40&"*",'Tillman UG Footage'!B:B,"<>AREA") -> 8 | H40: =COUNTIF('Pending Resto-COP Packages'!F:F,"*"&F40&"*") -> 4 | I40: =G40+H40 -> 12 | R40: ASM Utilities | S40: 2 | T40: 4 | U40: 6
A41: Mid Florida Contractors | B41: =COUNTIF('Tillman UG Footage'!D:D,"*Mid Florida*") -> 0 | C41: =COUNTIF('Pending Resto-COP Packages'!D:D,"*Mid Florida*") -> 1 | D41: =B41+C41 -> 1 | F41: Wilson | G41: =COUNTIFS('Tillman UG Footage'!F:F,"*"&F41&"*",'Tillman UG Footage'!B:B,"<>AREA") -> 0 | H41: =COUNTIF('Pending Resto-COP Packages'!F:F,"*"&F41&"*") -> 0 | I41: =G41+H41 -> 0 | R41: BICOM | S41: 5 | T41: 2 | U41: 7
A42: R&F Underground | B42: =COUNTIF('Tillman UG Footage'!D:D,"*R&F*") -> 0 | C42: =COUNTIF('Pending Resto-COP Packages'!D:D,"*R&F*") -> 2 | D42: =B42+C42 -> 2 | F42: Efrian | G42: =COUNTIFS('Tillman UG Footage'!F:F,"*"&F42&"*",'Tillman UG Footage'!B:B,"<>AREA") -> 0 | H42: =COUNTIF('Pending Resto-COP Packages'!F:F,"*"&F42&"*") -> 2 | I42: =G42+H42 -> 2 | R42: Brothers | S42: 8 | T42: 16 | U42: 24
A43: NIA Underground | B43: =COUNTIF('Tillman UG Footage'!D:D,"*NIA*") -> 0 | C43: =COUNTIF('Pending Resto-COP Packages'!D:D,"*NIA*") -> 2 | D43: =B43+C43 -> 2 | F43: TOTAL | G43: =SUM(G30:G42) -> 56 | H43: =SUM(H30:H42) -> 84 | I43: =SUM(I30:I42) -> 140 | R43: DMC Boring | S43: 2 | T43: 2 | U43: 4
A44: Alpha Omega | B44: =COUNTIF('Tillman UG Footage'!D:D,"*Alpha Omega*") -> 3 | C44: =COUNTIF('Pending Resto-COP Packages'!D:D,"*Alpha Omega*") -> 2 | D44: =B44+C44 -> 5 | R44: DMG - JOHN | S44: 1 | T44: 0 | U44: 1
A45: J Garcia Underground | B45: =COUNTIF('Tillman UG Footage'!D:D,"*Garcia*") -> 0 | C45: =COUNTIF('Pending Resto-COP Packages'!D:D,"*Garcia*") -> 0 | D45: =B45+C45 -> 0 | R45: Full Circle In-House/Saul/Felipe | S45: 1 | T45: 0 | U45: 1
A46: Splice Only | B46: =COUNTIF('Tillman UG Footage'!D:D,"*Splice*") -> 1 | C46: =COUNTIF('Pending Resto-COP Packages'!D:D,"*Splice*") -> 0 | D46: =B46+C46 -> 1 | R46: GN Systems | S46: 4 | T46: 6 | U46: 10
A47: TOTAL | B47: =SUM(B30:B46) -> 58 | C47: =SUM(C30:C46) -> 87 | D47: =SUM(D30:D46) -> 145 | R47: Gulfstream | S47: 1 | T47: 5 | U47: 6
R48: HAS Global | S48: 1 | T48: 2 | U48: 3
R49: HD Cable | S49: 3 | T49: 1 | U49: 4
R50: HDD Underground / R&F Underground Construction Inc | S50: 0 | T50: 1 | U50: 1
R51: ITG In-House | S51: 3 | T51: 0 | U51: 3
R52: Kattle One | S52: 5 | T52: 0 | U52: 5
R53: Kattle One/LSCG | S53: 1 | T53: 0 | U53: 1
R54: Legant Livings | S54: 4 | T54: 2 | U54: 6
A55: CHARTS | R55: Lightspeed In-House | S55: 2 | T55: 15 | U55: 17
R56: Lightspeed In-House / GN Systems | S56: 0 | T56: 1 | U56: 1
R57: Lightspeed In-House/North Path | S57: 0 | T57: 1 | U57: 1
R58: Lopez Underground | S58: 7 | T58: 16 | U58: 23
R59: Mid Florida Contractors | S59: 0 | T59: 1 | U59: 1
R60: NIA Underground | S60: 0 | T60: 2 | U60: 2
R61: North Path | S61: 10 | T61: 8 | U61: 18
R62: Power Connect | S62: 7 | T62: 5 | U62: 12
R63: Quinteros Cable Installation | S63: 3 | T63: 0 | U63: 3
R64: R&F Underground Construction Inc | S64: 0 | T64: 2 | U64: 2
R65: Randy's Utilities | S65: 2 | T65: 0 | U65: 2
R66: RDA Solutions | S66: 9 | T66: 0 | U66: 9
R67: Restoring Pro | S67: 2 | T67: 1 | U67: 3
... R71: Yosep AER | S71: 2 | T71: 7 | U71: 9
R90: HELPER – Supervisors (auto) | S90: Active | T90: Completed
R91: {=_xlfn._xlws.SORT(_xlfn.UNIQUE(_xlfn.VSTACK(_xlfn._xlws.FILTER(TRIM('Tillman UG Footage'!F2:F209),(TRIM('Tillman UG Footage'!F2:F209)<>"")*(TRIM('Tillman UG Footage'!F2:F209)<>"Assigned Supervisor")),_xlfn._xlws.FILTER(TRIM('Pending Resto-COP Packages'!F2:F101),(TRIM('Pending Resto-COP Packages'!F2:F101)<>"")*(TRIM('Pending Resto-COP Packages'!F2:F101)<>"Assigned Supervisor")))))} -> Aldo Layedra | S91: {=_xlfn.BYROW(_xlfn.ANCHORARRAY(R91),_xlfn.LAMBDA(_xlpm.s,COUNTIFS('Tillman UG Footage'!F:F,"*"&_xlpm.s&"*",'Tillman UG Footage'!B:B,"<>AREA")))} -> 49 | T91: {=_xlfn.BYROW(_xlfn.ANCHORARRAY(R91),_xlfn.LAMBDA(_xlpm.s,COUNTIF('Pending Resto-COP Packages'!F:F,"*"&_xlpm.s&"*")))} -> 14 | U91: {=_xlfn.ANCHORARRAY(S91)+_xlfn.ANCHORARRAY(T91)} -> 63
R92: Allen Johns | S92: 8 | T92: 0 | U92: 8
R93: Anthony Adum | S93: 4 | T93: 11 | U93: 15
R94: Brenton Copelin | S94: 2 | T94: 9 | U94: 11
R95: Cody | S95: 1 | T95: 3 | U95: 4
R96: Danny Combs | S96: 7 | T96: 1 | U96: 8
R97: Efrian | S97: 0 | T97: 2 | U97: 2
R98: Eric | S98: 1 | T98: 0 | U98: 1
R99: Johnnie Williams | S99: 6 | T99: 10 | U99: 16
R100: Jose | S100: 2 | T100: 5 | U100: 7
R101: Joshua | S101: 26 | T101: 41 | U101: 67
R102: Joshua Pacheco | S102: 8 | T102: 4 | U102: 12
R103: Joshua Wheatcroft | S103: 0 | T103: 32 | U103: 32
... R111: Treyvon Tillman | S111: 8 | T111: 4 | U111: 12
A115: COMPLETED PROJECTS PENDING PAPERWORK
A135: NTP Number | B135: Area | C135: Vendor | D135: Supervisor | E135: HHP | F135: Footage UG | G135: Completed Footage | H135: Est. Cost
A136: =IF('Pending Resto-COP Packages'!A2="","",'Pending Resto-COP Packages'!A2) -> BHU-FLX-01-E | B136: =IF('Pending Resto-COP Packages'!A2="","",'Pending Resto-COP Packages'!B2) -> Bradenton | C136: =IF('Pending Resto-COP Packages'!A2="","",'Pending Resto-COP Packages'!D2) -> Lightspeed In-House | D136: =IF('Pending Resto-COP Packages'!A2="","",'Pending Resto-COP Packages'!F2) -> Johnnie Williams | E136: =IF('Pending Resto-COP Packages'!A2="","",'Pending Resto-COP Packages'!H2) -> 0 | F136: =IF('Pending Resto-COP Packages'!A2="","",'Pending Resto-COP Packages'!V2) -> 3109 | G136: =IF('Pending Resto-COP Packages'!A2="","",'Pending Resto-COP Packages'!W2) -> 3128 | H136: =IF('Pending Resto-COP Packages'!A2="","",'Pending Resto-COP Packages'!N2) -> 49846.95
A137: =IF('Pending Resto-COP Packages'!A3="","",'Pending Resto-COP Packages'!A3) -> BHUD-FOE-401-W | B137: =IF('Pending Resto-COP Packages'!A3="","",'Pending Resto-COP Packages'!B3) -> Bradenton | C137: =IF('Pending Resto-COP Packages'!A3="","",'Pending Resto-COP Packages'!D3) -> North Path | D137: =IF('Pending Resto-COP Packages'!A3="","",'Pending Resto-COP Packages'!F3) -> Cody | E137: =IF('Pending Resto-COP Packages'!A3="","",'Pending Resto-COP Packages'!H3) -> 0 | F137: =IF('Pending Resto-COP Packages'!A3="","",'Pending Resto-COP Packages'!V3) -> 1412 | G137: =IF('Pending Resto-COP Packages'!A3="","",'Pending Resto-COP Packages'!W3) -> 1406 | H137: =IF('Pending Resto-COP Packages'!A3="","",'Pending Resto-COP Packages'!N3) -> 18856.2
A138: =IF('Pending Resto-COP Packages'!A4="","",'Pending Resto-COP Packages'!A4) -> D-HAL113 | B138: =IF('Pending Resto-COP Packages'!A4="","",'Pending Resto-COP Packages'!B4) -> Bradenton | C138: =IF('Pending Resto-COP Packages'!A4="","",'Pending Resto-COP Packages'!D4) -> North Path | D138: =IF('Pending Resto-COP Packages'!A4="","",'Pending Resto-COP Packages'!F4) -> Brenton Copelin | E138: =IF('Pending Resto-COP Packages'!A4="","",'Pending Resto-COP Packages'!H4) -> 86 | F138: =IF('Pending Resto-COP Packages'!A4="","",'Pending Resto-COP Packages'!V4) -> 3508 | G138: =IF('Pending Resto-COP Packages'!A4="","",'Pending Resto-COP Packages'!W4) -> 3492 | H138: =IF('Pending Resto-COP Packages'!A4="","",'Pending Resto-COP Packages'!N4) -> 52728
A139: =IF('Pending Resto-COP Packages'!A5="","",'Pending Resto-COP Packages'!A5) -> D-HAL114 | B139: =IF('Pending Resto-COP Packages'!A5="","",'Pending Resto-COP Packages'!B5) -> Bradenton | C139: =IF('Pending Resto-COP Packages'!A5="","",'Pending Resto-COP Packages'!D5) -> North Path | D139: =IF('Pending Resto-COP Packages'!A5="","",'Pending Resto-COP Packages'!F5) -> Brenton Copelin | E139: =IF('Pending Resto-COP Packages'!A5="","",'Pending Resto-COP Packages'!H5) -> 62 | F139: =IF('Pending Resto-COP Packages'!A5="","",'Pending Resto-COP Packages'!V5) -> 3148 | G139: =IF('Pending Resto-COP Packages'!A5="","",'Pending Resto-COP Packages'!W5) -> 3199 | H139: =IF('Pending Resto-COP Packages'!A5="","",'Pending Resto-COP Packages'!N5) -> 42744
A140: =IF('Pending Resto-COP Packages'!A6="","",'Pending Resto-COP Packages'!A6) -> D-HAL116 | B140: =IF('Pending Resto-COP Packages'!A6="","",'Pending Resto-COP Packages'!B6) -> Bradenton | C140: =IF('Pending Resto-COP Packages'!A6="","",'Pending Resto-COP Packages'!D6) -> North Path | D140: =IF('Pending Resto-COP Packages'!A6="","",'Pending Resto-COP Packages'!F6) -> Brenton Copelin | E140: =IF('Pending Resto-COP Packages'!A6="","",'Pending Resto-COP Packages'!H6) -> 81 | F140: =IF('Pending Resto-COP Packages'!A6="","",'Pending Resto-COP Packages'!V6) -> 4065 | G140: =IF('Pending Resto-COP Packages'!A6="","",'Pending Resto-COP Packages'!W6) -> 4167 | H140: =IF('Pending Resto-COP Packages'!A6="","",'Pending Resto-COP Packages'!N6) -> 52593.6
A141: =IF('Pending Resto-COP Packages'!A7="","",'Pending Resto-COP Packages'!A7) -> D-HLX421 | B141: =IF('Pending Resto-COP Packages'!A7="","",'Pending Resto-COP Packages'!B7) -> Bradenton | C141: =IF('Pending Resto-COP Packages'!A7="","",'Pending Resto-COP Packages'!D7) -> GN Systems | D141: =IF('Pending Resto-COP Packages'!A7="","",'Pending Resto-COP Packages'!F7) -> Cody | E141: =IF('Pending Resto-COP Packages'!A7="","",'Pending Resto-COP Packages'!H7) -> 20 | F141: =IF('Pending Resto-COP Packages'!A7="","",'Pending Resto-COP Packages'!V7) -> 1322 | G141: =IF('Pending Resto-COP Packages'!A7="","",'Pending Resto-COP Packages'!W7) -> 1322 | H141: =IF('Pending Resto-COP Packages'!A7="","",'Pending Resto-COP Packages'!N7) -> 23501
A142: =IF('Pending Resto-COP Packages'!A8="","",'Pending Resto-COP Packages'!A8) -> D-HLX503 | B142: =IF('Pending Resto-COP Packages'!A8="","",'Pending Resto-COP Packages'!B8) -> Bradenton | C142: =IF('Pending Resto-COP Packages'!A8="","",'Pending Resto-COP Packages'!D8) -> North Path | D142: =IF('Pending Resto-COP Packages'!A8="","",'Pending Resto-COP Packages'!F8) -> Brenton Copelin | E142: =IF('Pending Resto-COP Packages'!A8="","",'Pending Resto-COP Packages'!H8) -> 85 | F142: =IF('Pending Resto-COP Packages'!A8="","",'Pending Resto-COP Packages'!V8) -> 4380 | G142: =IF('Pending Resto-COP Packages'!A8="","",'Pending Resto-COP Packages'!W8) -> 4475 | H142: =IF('Pending Resto-COP Packages'!A8="","",'Pending Resto-COP Packages'!N8) -> 60062
A143: =IF('Pending Resto-COP Packages'!A9="","",'Pending Resto-COP Packages'!A9) -> D-HLX505 | B143: =IF('Pending Resto-COP Packages'!A9="","",'Pending Resto-COP Packages'!B9) -> Bradenton | C143: =IF('Pending Resto-COP Packages'!A9="","",'Pending Resto-COP Packages'!D9) -> North Path | D143: =IF('Pending Resto-COP Packages'!A9="","",'Pending Resto-COP Packages'!F9) -> Brenton Copelin | E143: =IF('Pending Resto-COP Packages'!A9="","",'Pending Resto-COP Packages'!H9) -> 87 | F143: =IF('Pending Resto-COP Packages'!A9="","",'Pending Resto-COP Packages'!V9) -> 4888 | G143: =IF('Pending Resto-COP Packages'!A9="","",'Pending Resto-COP Packages'!W9) -> 5016 | H143: =IF('Pending Resto-COP Packages'!A9="","",'Pending Resto-COP Packages'!N9) -> 64040
A144: =IF('Pending Resto-COP Packages'!A10="","",'Pending Resto-COP Packages'!A10) -> FB-HLR201 | B144: =IF('Pending Resto-COP Packages'!A10="","",'Pending Resto-COP Packages'!B10) -> Bradenton | C144: =IF('Pending Resto-COP Packages'!A10="","",'Pending Resto-COP Packages'!D10) -> Lightspeed In-House / GN Systems | D144: =IF('Pending Resto-COP Packages'!A10="","",'Pending Resto-COP Packages'!F10) -> Cody | E144: =IF('Pending Resto-COP Packages'!A10="","",'Pending Resto-COP Packages'!H10) -> 0 | F144: =IF('Pending Resto-COP Packages'!A10="","",'Pending Resto-COP Packages'!V10) -> 9840 | G144: =IF('Pending Resto-COP Packages'!A10="","",'Pending Resto-COP Packages'!W10) -> 9806 | H144: =IF('Pending Resto-COP Packages'!A10="","",'Pending Resto-COP Packages'!N10) -> 144972.5
A145: =IF('Pending Resto-COP Packages'!A11="","",'Pending Resto-COP Packages'!A11) -> FB-HLX175 | B145: =IF('Pending Resto-COP Packages'!A11="","",'Pending Resto-COP Packages'!B11) -> Bradenton | C145: =IF('Pending Resto-COP Packages'!A11="","",'Pending Resto-COP Packages'!D11) -> Lightspeed In-House/North Path | D145: =IF('Pending Resto-COP Packages'!A11="","",'Pending Resto-COP Packages'!F11) -> Brenton Copelin | E145: =IF('Pending Resto-COP Packages'!A11="","",'Pending Resto-COP Packages'!H11) -> 0 | F145: =IF('Pending Resto-COP Packages'!A11="","",'Pending Resto-COP Packages'!V11) -> 3036 | G145: =IF('Pending Resto-COP Packages'!A11="","",'Pending Resto-COP Packages'!W11) -> 3056 | H145: =IF('Pending Resto-COP Packages'!A11="","",'Pending Resto-COP Packages'!N11) -> 36166.65
A146: =IF('Pending Resto-COP Packages'!A12="","",'Pending Resto-COP Packages'!A12) -> FB-HOE401-V6 | B146: =IF('Pending Resto-COP Packages'!A12="","",'Pending Resto-COP Packages'!B12) -> Bradenton | C146: =IF('Pending Resto-COP Packages'!A12="","",'Pending Resto-COP Packages'!D12) -> Lightspeed In-House | D146: =IF('Pending Resto-COP Packages'!A12="","",'Pending Resto-COP Packages'!F12) -> Brenton Copelin | E146: =IF('Pending Resto-COP Packages'!A12="","",'Pending Resto-COP Packages'!H12) -> 0 | F146: =IF('Pending Resto-COP Packages'!A12="","",'Pending Resto-COP Packages'!V12) -> 194 | G146: =IF('Pending Resto-COP Packages'!A12="","",'Pending Resto-COP Packages'!W12) -> 200 | H146: =IF('Pending Resto-COP Packages'!A12="","",'Pending Resto-COP Packages'!N12) -> 3232.9
A147: =IF('Pending Resto-COP Packages'!A13="","",'Pending Resto-COP Packages'!A13) -> D-HPP607 | B147: =IF('Pending Resto-COP Packages'!A13="","",'Pending Resto-COP Packages'!B13) -> Clearwater | C147: =IF('Pending Resto-COP Packages'!A13="","",'Pending Resto-COP Packages'!D13) -> Lightspeed In-House | D147: =IF('Pending Resto-COP Packages'!A13="","",'Pending Resto-COP Packages'!F13) -> Treyvon Tillman | E147: =IF('Pending Resto-COP Packages'!A13="","",'Pending Resto-COP Packages'!H13) -> 46 | F147: =IF('Pending Resto-COP Packages'!A13="","",'Pending Resto-COP Packages'!V13) -> 5649 | G147: =IF('Pending Resto-COP Packages'!A13="","",'Pending Resto-COP Packages'!W13) -> 5893 | H147: =IF('Pending Resto-COP Packages'!A13="","",'Pending Resto-COP Packages'!N13) -> 71754.5
... A247: =IF('Pending Resto-COP Packages'!A113="","",'Pending Resto-COP Packages'!A113) -> FB-HTG308 | B247: =IF('Pending Resto-COP Packages'!A113="","",'Pending Resto-COP Packages'!B113) -> Lee | C247: =IF('Pending Resto-COP Packages'!A113="","",'Pending Resto-COP Packages'!D113) -> AGN | D247: =IF('Pending Resto-COP Packages'!A113="","",'Pending Resto-COP Packages'!F113) -> Aldo Layedra | E247: =IF('Pending Resto-COP Packages'!A113="","",'Pending Resto-COP Packages'!H113) -> 0 | F247: =IF('Pending Resto-COP Packages'!A113="","",'Pending Resto-COP Packages'!V113) -> 590 | G247: =IF('Pending Resto-COP Packages'!A113="","",'Pending Resto-COP Packages'!W113) -> 590 | H247: =IF('Pending Resto-COP Packages'!A113="","",'Pending Resto-COP Packages'!N113) -> 0
A248: TOTAL | E248: =SUM(E136:E247) -> 6451 | F248: =SUM(F136:F247) -> 606783 | G248: =SUM(G136:G247) -> 602710 | H248: =SUM(H136:H247) -> 6933979.1

Sheet Raw Data
B1: YTD | C1: JAN | D1: FEB | E1: MARCH | F1: APR | G1: MAY | H1: JUNE | I1: JULY | J1: AUG | K1: SEPT | L1: OCT | M1: NOV | N1: DEC
A2: Total Completed | B2: =SUM(C2:N2) -> 23 | C2: 23
A3: Total Goal | B3: =SUM(C3:N3) -> 13721 | C3: 921 | D3: 11888 | E3: 753 | F3: 159
A4: DOY | B4: =SUM(C4:N4) -> 15 | C4: 15 | D4: 0 | E4: 0 | F4: 0 | G4: 0 | H4: 0 | I4: 0 | J4: 0 | K4: 0 | L4: 0 | M4: 0 | N4: 0
A5: % to Year End | B5: =B4/B8 -> 0.059760956 | C5: =C4/C8 -> 0.68181818 | D5: =D4/D8 -> 0 | E5: =E4/E8 -> 0 | F5: =F4/F8 -> 0 | G5: =G4/G8 -> 0 | H5: =H4/H8 -> 0 | I5: =I4/I8 -> 0 | ... N5: =N4/N8 -> 0
A6: Achieved % to Goal | B6: =B2/B3 -> 0.0016762627 | C6: =C2/C3 -> 0.024972856 | D6: =D2/D3 -> 0 | E6: =E2/E3 -> 0 | F6: =F2/F3 -> 0 | G6: =G2/G3 -> #DIV/0! | H6: =H2/H3 -> #DIV/0! | I6: =I2/I3 -> #DIV/0! | ... N6: =N2/N3 -> #DIV/0!
A7: Total % | B7: 1 | C7: 1 | D7: 1 | E7: 1 | F7: 1 | G7: 1 | H7: 1 | I7: 1 | J7: 1 | K7: 1 | L7: 1 | M7: 1 | N7: 1
B8: 251 | C8: 22 | D8: 20 | E8: 21 | F8: 22 | G8: 22 | H8: 22 | I8: 22 | J8: 22 | K8: 22 | L8: 22 | M8: 22 | N8: 22

Sheet UG Condensed
A1: NTP Number | B1: AREA | C1: SOW TSD Date | D1: Penguin ID | H1: HHP | I1: On Track or In Jeopardy | J1: NTP Received | K1: SOW Received | L1: Permit Status | M1: Door Tag Date | N1: Constuction Status | O1: Locate Date | P1: UG Conduit Status | Q1: Proofing Conduits-ABF Tested | R1: Pulling Fiber | S1: Stingrays | T1: Fiber Spliced | U1: Restoration | V1: Tillman QC Status | W1: COP Package To Biz-Ops Date | X1: Invoice | Y1: {=VLOOKUP(#REF!,#REF!, FALSE)} -> #REF!
A2: BHT-FOE-03 | B2: Bradenton | C2: 45991 | D2: MAN97574 | H2: 0 | J2: Yes | K2: Yes | L2: Received | M2: 45852 | N2: In Process | O2: 45852 | P2: In Process | Q2: In Process | R2: In Process | S2: Not Required | T2: In Process | U2: Pending | V2: Pending
A3: BHUD-FOE-02-W | B3: Bradenton | C3: 45742 | D3: MAN92070 | H3: 0 | J3: Yes | K3: Yes | L3: Received | M3: 45716 | N3: Completed | O3: 45721 | P3: Completed | Q3: Completed | R3: Completed | S3: Not Required | T3: Completed | U3: Completed | V3: Pending | X3: Pending | Y3: =VLOOKUP(A3,#REF!,2,FALSE) -> #REF!
A4: BHUD-FOE-06-E | B4: Bradenton | C4: 45742 | D4: MAN92243 | H4: 0 | J4: Yes | K4: Yes | L4: Received | M4: 45716 | N4: In Process | O4: 45721 | P4: In Process | Q4: In Process | R4: In Process | S4: Not Required | T4: In Process | U4: Pending | V4: Pending | X4: Pending | Y4: =VLOOKUP(A4,#REF!,2,FALSE) -> #REF!
A5: BHZD-FOE-03-W | B5: Bradenton | C5: 45991 | D5: PPM89496 | H5: 0 | J5: Yes | K5: Yes | L5: Received | M5: 45793 | N5: In Process | O5: 45793 | P5: In Process | Q5: In Process | R5: In Process | S5: Not Required | T5: In Process | U5: Pending | V5: Pending | X5: Pending
A6: D-HOE102 | B6: Bradenton | C6: 45747 | D6: MAN89819 | H6: 56 | J6: Yes | K6: Yes | L6: Received | M6: 45701 | N6: Completed | O6: 45718 | P6: Completed | Q6: Completed | R6: Not Req | S6: Completed | T6: Completed | U6: Completed | V6: Pending | X6: Pending | Y6: =VLOOKUP(A6,#REF!,2,FALSE) -> #REF!
A7: D-HOE111 | B7: Bradenton | C7: 45742 | D7: PPM92353 | H7: 60 | J7: Yes | K7: Yes | L7: Received | M7: 45716 | N7: Completed | O7: Completed | P7: Completed | Q7: Completed | R7: Not Req | S7: Completed | T7: Completed | U7: Completed | V7: Pending | X7: Pending | Y7: =VLOOKUP(A7,#REF!,2,FALSE) -> #REF!
A8: D-HOE116 | B8: Bradenton | C8: 45742 | D8: PPM90592 | H8: 84 | J8: Yes | K8: Yes | L8: Received | M8: 45716 | N8: Completed | O8: Completed | P8: Completed | Q8: Completed | R8: Not Req | S8: Completed | T8: Completed | U8: Completed | V8: Pending | X8: Pending | Y8: =VLOOKUP(A8,#REF!,2,FALSE) -> #REF!
A9: D-HOE117 | B9: Bradenton | C9: 45742 | D9: MAN90788 | H9: 79 | J9: Yes | K9: Yes | L9: Received | M9: 45716 | N9: Completed | O9: 45718 | P9: Completed | Q9: Completed | R9: Not Req | S9: Completed | T9: Completed | U9: Completed | V9: Pending | X9: Pending | Y9: =VLOOKUP(A9,#REF!,2,FALSE) -> #REF!
A10: D-HOE120 | B10: Bradenton | C10: 45742 | D10: MAN90778 | H10: 83 | J10: Yes | K10: Yes | L10: Received | M10: 45716 | N10: Completed | O10: Completed | P10: Completed | Q10: Completed | R10: Not Req | S10: Completed | T10: Completed | U10: Completed | V10: Pending | X10: Pending | Y10: =VLOOKUP(A10,#REF!,2,FALSE) -> #REF!
A11: D-HOE206 | B11: Bradenton | C11: 45991 | D11: PPM92353 | E11: 31 | H11: 31 | J11: Yes | K11: Yes | L11: Received | M11: 45716 | N11: In Process | O11: 45716 | P11: Completed | Q11: Completed | R11: Not Req | S11: Completed | T11: Completed | U11: Pending | V11: Pending
A12: D-HOE215 | B12: Bradenton | C12: 45772 | D12: PPM92353 | H12: 31 | J12: Yes | K12: Yes | L12: Received | M12: 45716 | N12: In Process | O12: 45716 | P12: Completed | Q12: Completed | R12: Not Req | S12: Completed | T12: Completed | U12: Pending | V12: Pending | X12: Pending | Y12: =VLOOKUP(A12,#REF!,2,FALSE) -> #REF!
A13: FB-HLR201 | B13: Bradenton | C13: 45960 | D13: MAN98152 | H13: 0 | J13: Yes | K13: Yes | L13: Received | M13: 45867 | N13: In Process | O13: 45867 | P13: In Process | Q13: In Process | R13: In Process | S13: Not Required | T13: In Process | U13: Pending | V13: Pending
A14: D-HOE302 | B14: Bradenton | C14: 45991 | D14: MAN98158 | H14: 57 | J14: Yes | K14: Yes | L14: Received | M14: 45863 | N14: In Process | O14: 45863 | P14: In Process | Q14: In Process | R14: In Process | S14: Not Required | T14: In Process | U14: Pending | V14: Pending
A15: FB-HOE117 | B15: Bradenton | C15: 45711 | D15: MAN89824 | H15: 0 | J15: Yes | K15: Yes | L15: Received | M15: 45701 | N15: Completed | O15: 45718 | P15: Completed | Q15: Completed | R15: Completed | S15: Not Required | T15: Completed | U15: Completed | V15: Completed | W15: 45856 | X15: Submitted | Y15: =VLOOKUP(A15,#REF!,2,FALSE) -> #REF!
A16: FB-HOE201 | B16: Bradenton | C16: 45742 | D16: MAN91981 | H16: 0 | J16: Yes | K16: Yes | L16: Received | M16: 2/29/2025 | N16: Completed | O16: 2/29/2025 | P16: Completed | Q16: Completed | R16: Completed | S16: Not Required | T16: Completed | U16: Pending | V16: Pending | X16: Pending | Y16: =VLOOKUP(A16,#REF!,2,FALSE) -> #REF!
A17: FB-HOE301 | B17: Bradenton | C17: 45991 | D17: MAN98180 | H17: 0 | J17: Yes | K17: Yes | L17: Received | M17: 45863 | N17: Completed | O17: 45863 | P17: Completed | Q17: Completed | R17: Completed | S17: Not Required | T17: Completed | U17: Pending | V17: Pending
A18: FB-HOE375 | B18: Bradenton | C18: 45991 | D18: MAN99383 | H18: 0 | J18: Yes | K18: Yes | L18: Received | M18: 45881 | N18: Completed | O18: 45881 | P18: Completed | Q18: Completed | R18: Completed | S18: Not Required | T18: Completed | U18: Pending | V18: Pending
A19: 12 Oaks MHP | B19: Lakeland | C19: 45899 | H19: 50 | J19: Yes | K19: Yes | L19: Not Required | M19: 45873 | N19: Completed | O19: 45873 | P19: Completed | Q19: Completed | R19: Completed | S19: Not Required | T19: Completed | U19: Completed | V19: Pending
A20: BHT-FWP-06 | B20: Lakeland | C20: 45742 | D20: PLK89457 | H20: 0 | J20: Yes | K20: Yes | L20: Received | M20: 45708 | N20: Completed | O20: 45709 | P20: Completed | Q20: Completed | R20: Completed | S20: Not Required | T20: Completed | U20: Completed | V20: Completed | W20: 45811 | X20: Submitted | Y20: =VLOOKUP(A20,#REF!,2,FALSE) -> #REF!
A21: BHT-FWP-07 | B21: Lakeland | C21: 45772 | D21: PLK91807 | H21: 0 | J21: Yes | K21: Yes | L21: Received | M21: 45708 | N21: Completed | O21: 45737 | P21: Completed | Q21: Completed | R21: Completed | S21: Not Required | T21: Completed | U21: Completed | V21: Completed | W21: 45779 | X21: Submitted | Y21: =VLOOKUP(A21,#REF!,2,FALSE) -> #REF!
A22: BHT-FWP-08 | B22: Lakeland | C22: 45868 | D22: PLK96231 | H22: 0 | J22: Yes | K22: Yes | L22: Received | M22: Not Required | N22: Completed | O22: 45814 | P22: Completed | Q22: Completed | R22: Completed | S22: Not Required | T22: Completed | U22: Completed | V22: Completed | W22: 45848 | X22: Submitted
A23: BHT-FWP-09 | B23: Lakeland | C23: 45838 | D23: PLK95075 | H23: 0 | J23: Yes | K23: Yes | L23: Received | M23: 45786 | N23: Completed | O23: 45789 | P23: Completed | Q23: Completed | R23: Completed | S23: Not Required | T23: Completed | U23: Completed | V23: Completed
A24: BHT-FWP-10 | B24: Lakeland | C24: 45807 | D24: PLK94470 | H24: 0 | J24: Yes | K24: Yes | L24: Received | M24: 45778 | N24: Completed | O24: 45782 | P24: Completed | Q24: Completed | R24: Completed | S24: Not Required | T24: Completed | U24: Completed | V24: Completed | W24: 45826 | X24: Submitted
A25: BHUD-FWP-08-E | B25: Lakeland | C25: 45787 | D25: PLK91306 | H25: 0 | J25: Yes | K25: Yes | L25: Received | M25: 45716 | N25: Completed | O25: 45716 | P25: Completed | Q25: Completed | R25: Completed | S25: Not Required | T25: Completed | U25: Completed | V25: Completed | W25: 45793 | X25: Submitted | Y25: =VLOOKUP(A25,#REF!,2,FALSE) -> #REF!
A26: BHUD-FWP-13-W | B26: Lakeland | C26: 45868 | D26: PLK95092 | H26: 0 | J26: Yes | K26: Yes | L26: Received | M26: Not Required | N26: Completed | O26: 45840 | P26: Completed | Q26: Completed | R26: Completed | S26: Not Required | T26: Completed | U26: Completed | V26: Completed
A27: BHZD-FWP-11-W | B27: Lakeland | C27: 45868 | D27: PLK97102 | H27: 0 | J27: Yes | K27: Yes | L27: Received | M27: Not Required | N27: Completed | O27: 45853 | P27: Completed | Q27: Completed | R27: Completed | S27: Not Required | T27: Completed | U27: Completed | V27: Completed
A28: BHZD-FWP-13-E | B28: Lakeland | C28: 45868 | D28: PLK95389 | H28: 0 | J28: Yes | K28: Yes | L28: Received | M28: 45793 | N28: Completed | O28: 45793 | P28: Completed | Q28: Completed | R28: Completed | S28: Not Required | T28: Completed | U28: Completed | V28: Completed
A29: D-HWP102 | B29: Lakeland | C29: 45711 | D29: MAN91697 | H29: 54 | J29: Yes | K29: Yes | L29: Received | M29: 45659 | N29: Completed | O29: 45692 | P29: Completed | Q29: Completed | R29: Completed | S29: Completed | T29: Completed | U29: Completed | V29: Completed | W29: 45789 | X29: Submitted | Y29: =VLOOKUP(A29,#REF!,2,FALSE) -> #REF!
A30: D-HWP103 | B30: Lakeland | C30: 45711 | D30: PLK88967 | H30: 49 | J30: Yes | K30: Yes | L30: Received | M30: 45713 | N30: Completed | O30: 45692 | P30: Completed | Q30: Completed | R30: Completed | S30: Completed | T30: Completed | U30: Completed | V30: Completed | W30: 45789 | X30: Submitted | Y30: =VLOOKUP(A30,#REF!,2,FALSE) -> #REF!
A31: D-HWP105 | B31: Lakeland | C31: 45716 | D31: PLK90239 | H31: 56 | J31: Yes | K31: Yes | L31: Received | M31: 45707 | N31: Completed | O31: 45707 | P31: Completed | Q31: Completed | R31: Not Req | S31: Completed | T31: Completed | U31: Completed | V31: Completed | W31: 45779 | X31: Submitted | Y31: =VLOOKUP(A31,#REF!,2,FALSE) -> #REF!
A32: D-HWP1304 | B32: Lakeland | C32: 45772 | D32: PLK93497 | H32: 82 | J32: Yes | K32: Yes | L32: Received | M32: 45756 | N32: Completed | O32: 45756 | P32: Completed | Q32: Completed | R32: Not Req | S32: Completed | T32: Completed | U32: Completed | V32: Completed | W32: 45792 | X32: Submitted
A33: D-HWP1306 | B33: Lakeland | C33: 45772 | D33: PLK92368 | H33: 79 | J33: Yes | K33: Yes | L33: Received | M33: 45749 | N33: Completed | O33: 45749 | P33: Completed | Q33: Completed | R33: Not Req | S33: Completed | T33: Completed | U33: Completed | V33: Completed | W33: 45812 | X33: Submitted | Y33: =VLOOKUP(A33,#REF!,2,FALSE) -> #REF!
A34: D-HWP1309 | B34: Lakeland | C34: 45772 | D34: PLK92363 | H34: 59 | J34: Yes | K34: Yes | L34: Received | M34: 45750 | N34: Completed | O34: 45750 | P34: Completed | Q34: Completed | R34: Not Req | S34: Completed | T34: Completed | U34: Completed | V34: Completed | W34: 45797 | X34: Submitted
A35: D-HWP412 | B35: Lakeland | C35: 45688 | D35: PLK87663 | H35: 23 | J35: Yes | K35: Yes | L35: Received | M35: 45659 | N35: Completed | O35: 45659 | P35: Completed | Q35: Completed | R35: Not Req | S35: Completed | T35: Completed | U35: Completed | V35: Completed | W35: 45789 | X35: Submitted | Y35: =VLOOKUP(A35,#REF!,2,FALSE) -> #REF!
A36: D-HWP415 | B36: Lakeland | C36: 45688 | D36: PLK88133 | H36: 70 | J36: Yes | K36: Yes | L36: Received | M36: 45659 | N36: Completed | O36: 45659 | P36: Completed | Q36: Completed | R36: Not Req | S36: Completed | T36: Completed | U36: Completed | V36: Completed | W36: 45824 | X36: Submitted | Y36: =VLOOKUP(A36,#REF!,2,FALSE) -> #REF!
A37: D-HWP425 | B37: Lakeland | C37: 45688 | D37: PLK88584 | H37: 75 | J37: Yes | K37: Yes | L37: Received | M37: Completed | N37: Completed | O37: 45672 | P37: Completed | Q37: Completed | R37: Not Req | S37: Completed | T37: Completed | U37: Completed | V37: Completed | W37: 45789 | X37: Submitted | Y37: =VLOOKUP(A37,#REF!,2,FALSE) -> #REF!
A38: D-HWP436 | B38: Lakeland | C38: 45688 | D38: PLK88375 | H38: 65 | J38: Yes | K38: Yes | L38: Received | M38: 45673 | N38: Completed | O38: 45673 | P38: Completed | Q38: Completed | R38: Not Req | S38: Completed | T38: Completed | U38: Completed | V38: Completed | W38: 45789 | X38: Submitted | Y38: =VLOOKUP(A38,#REF!,2,FALSE) -> #REF!
A39: D-HWP441 | B39: Lakeland | C39: 45688 | D39: PLK88853 | H39: 81 | J39: Yes | K39: Yes | L39: Received | M39: Completed | N39: Completed | O39: 45672 | P39: Completed | Q39: Completed | R39: Not Req | S39: Completed | T39: Completed | U39: Completed | V39: Completed | W39: 45789 | X39: Submitted | Y39: =VLOOKUP(A39,#REF!,2,FALSE) -> #REF!
A40: D-HWP701 | B40: Lakeland | C40: 45742 | D40: PLK89401 | H40: 50 | J40: Yes | K40: Yes | L40: Received | M40: 45705 | N40: Completed | O40: 45715 | P40: Completed | Q40: Completed | R40: Completed | S40: Completed | T40: Completed | U40: Completed | V40: Completed | W40: 45789 | X40: Submitted | Y40: =VLOOKUP(A40,#REF!,2,FALSE) -> #REF!
A41: D-HWP702 | B41: Lakeland | C41: 45742 | D41: PLK92108 | H41: 52 | J41: Yes | K41: Yes | L41: Received | M41: 45741 | N41: Completed | O41: 45729 | P41: Completed | Q41: Completed | R41: Completed | S41: Completed | T41: Completed | U41: Completed | V41: Completed | W41: 45789 | X41: Submitted | Y41: =VLOOKUP(A41,#REF!,2,FALSE) -> #REF!
A42: D-HWP703 | B42: Lakeland | C42: 45772 | D42: PLK92329 | H42: 86 | J42: Yes | K42: Yes | L42: Received | M42: 45737 | N42: Completed | O42: 45737 | P42: Completed | Q42: Completed | R42: Completed | S42: Completed | T42: Completed | U42: Completed | V42: Completed | W42: 45789 | X42: Submitted | Y42: =VLOOKUP(A42,#REF!,2,FALSE) -> #REF!
A43: D-HWP705 | B43: Lakeland | C43: 45716 | D43: PLK91019 | H43: 51 | J43: Yes | K43: Yes | L43: Received | M43: Completed | N43: Completed | O43: 45726 | P43: Completed | Q43: Completed | R43: Completed | S43: Completed | T43: Completed | U43: Completed | V43: Completed | W43: 45786 | X43: Submitted | Y43: =VLOOKUP(A43,#REF!,2,FALSE) -> #REF!
A44: D-HWP707 | B44: Lakeland | C44: 45772 | D44: PLK91963 | H44: 35 | J44: Yes | K44: Yes | L44: Received | M44: 45736 | N44: Completed | O44: 45741 | P44: Completed | Q44: Completed | R44: Completed | S44: Completed | T44: Completed | U44: Completed | V44: Completed | W44: 45789 | X44: Submitted | Y44: =VLOOKUP(A44,#REF!,2,FALSE) -> #REF!
A45: D-HWP713 | B45: Lakeland | C45: 45711 | D45: PLK89267 | H45: 22 | J45: Yes | K45: Yes | L45: Received | M45: Completed | N45: Completed | O45: 45695 | P45: Completed | Q45: Completed | R45: Completed | S45: Completed | T45: Completed | U45: Completed | V45: Completed | W45: 45789 | X45: Submitted | Y45: =VLOOKUP(A45,#REF!,2,FALSE) -> #REF!
A46: D-HWP801 | B46: Lakeland | C46: 45868 | D46: PLK95087 | H46: 90 | J46: Yes | K46: Yes | L46: Received | M46: 45797 | N46: Completed | O46: 45810 | P46: Completed | Q46: Completed | R46: Completed | S46: Completed | T46: Completed | U46: Completed | V46: Completed | W46: 45847 | X46: Submitted
A47: D-HWP803 | B47: Lakeland | C47: 45899 | D47: PLK97105 | H47: 62 | J47: Yes | K47: Yes | L47: Received | M47: 45880 | N47: Completed | O47: 45880 | P47: Completed | Q47: Completed | R47: Completed | S47: Not Required | T47: Completed | U47: Completed | V47: Pending
A48: D-HWP805 | B48: Lakeland | C48: 45930 | D48: PLK97109 | H48: 85 | J48: Yes | K48: Yes | L48: Received | M48: 45882 | N48: Completed | O48: 45882 | P48: Completed | Q48: Completed | R48: Completed | S48: Completed | T48: Completed | U48: Completed | V48: Pending
A49: D-HWP812 | B49: Lakeland | C49: 45899 | D49: PLK97117 | H49: 77 | J49: Yes | K49: Yes | L49: Received | M49: 45840 | N49: Completed | O49: 45840 | P49: Completed | Q49: Completed | R49: Completed | S49: Not Required | T49: Completed | U49: Completed | V49: Completed | W49: 45877 | X49: Submitted
A50: D-HWP814 | B50: Lakeland | C50: 45899 | D50: PLK97122 | H50: 81 | J50: Yes | K50: Yes | L50: Received | M50: 45847 | N50: Completed | O50: 45847 | P50: Completed | Q50: Completed | R50: Completed | S50: Not Required | T50: Completed | U50: Completed | V50: Completed | W50: 45895 | X50: Submitted
A51: D-HWP815 | B51: Lakeland | C51: 45899 | D51: PLK97093 | H51: 86 | J51: Yes | K51: Yes | L51: Received | M51: 45840 | N51: Completed | O51: 45840 | P51: Completed | Q51: Completed | R51: Completed | S51: Not Required | T51: Completed | U51: Completed | V51: Completed | W51: 45877 | X51: Submitted
A52: D-HWP821 | B52: Lakeland | C52: 45868 | D52: PLK96634 | H52: 66 | J52: Yes | K52: Yes | L52: Received | M52: 45833 | N52: Completed | O52: 45833 | P52: Completed | Q52: Completed | R52: Completed | S52: Completed | T52: Completed | U52: Completed | V52: Completed | W52: 45848 | X52: Submitted
A53: D-HWP822 | B53: Lakeland | C53: 45868 | D53: PLK97098 | H53: 43 | J53: Yes | K53: Yes | L53: Received | M53: 45840 | N53: Completed | O53: 45840 | P53: Completed | Q53: Not Required | R53: Completed | S53: Completed | T53: Completed | U53: Completed | V53: Completed | W53: 45916 | X53: Submitted
A54: D-HWP824 | B54: Lakeland | C54: 45899 | H54: 73 | J54: Yes | K54: Yes | L54: Received | M54: 45887 | N54: Completed | O54: 45887 | P54: Completed | Q54: Completed | R54: Completed | S54: Completed | T54: Completed | U54: Completed | V54: Pending
A55: D-HWP825 | B55: Lakeland | C55: 45899 | H55: 70 | J55: Yes | K55: Yes | L55: Received | M55: 45887 | N55: Completed | O55: 45887 | P55: Completed | Q55: Completed | R55: Completed | S55: Completed | T55: Completed | U55: Completed | V55: Pending
A56: D-HWP826 | B56: Lakeland | C56: 45899 | H56: 84 | J56: Yes | K56: Yes | L56: Received | M56: 45887 | N56: Completed | O56: 45887 | P56: Completed | Q56: Completed | R56: Completed | S56: Completed | T56: Completed | U56: Completed | V56: Pending
A57: D-HWP902 | B57: Lakeland | C57: 45862 | D57: PLK93385 | H57: 62 | J57: Yes | K57: Yes | L57: Received | M57: 45762 | N57: Completed | O57: 45783 | P57: Completed | Q57: Completed | R57: Not Req | S57: Completed | T57: Completed | U57: Completed | V57: Completed | W57: 45813 | X57: Submitted
A58: D-HWP903 | B58: Lakeland | C58: 45862 | D58: PLK93393 | H58: 89 | J58: Yes | K58: Yes | L58: Received | M58: 45762 | N58: Completed | O58: 45776 | P58: Completed | Q58: Completed | R58: Not Req | S58: Completed | T58: Completed | U58: Completed | V58: Completed | W58: 45796 | X58: Submitted
A59: D-HWP904 | B59: Lakeland | C59: 45862 | D59: PLK93379 | H59: 87 | J59: Yes | K59: Yes | L59: Received | M59: 45762 | N59: Completed | O59: 5/52025 | P59: Completed | Q59: Completed | R59: Not Req | S59: Completed | T59: Completed | U59: Completed | V59: Completed | W59: 45796 | X59: Submitted
A60: D-HWP905 | B60: Lakeland | C60: 45868 | D60: PLK94794 | H60: 60 | J60: Yes | K60: Yes | L60: Received | M60: 45790 | N60: Completed | O60: 45812 | P60: Completed | Q60: Completed | R60: Not Req | S60: Completed | T60: Completed | U60: Completed | V60: Completed | W60: 45824 | X60: Submitted
A61: FB-HWP101 | B61: Lakeland | C61: 45688 | D61: PLK88377 | H61: 0 | J61: Yes | K61: Yes | L61: Received | M61: Completed | N61: Completed | O61: 45673 | P61: Completed | Q61: Completed | R61: In Process | S61: Not Required | T61: Completed | U61: Completed | V61: Completed | W61: 45758 | X61: Submitted | Y61: =VLOOKUP(A61,#REF!,2,FALSE) -> #REF!
A62: FB-HWP1302 | B62: Lakeland | C62: 45868 | D62: PLK97344 | H62: 0 | J62: Yes | K62: Yes | L62: Received | M62: 45848 | N62: Completed | O62: 45848 | P62: Completed | Q62: Completed | R62: Completed | S62: Not Required | T62: Completed | U62: Completed | V62: Completed | W62: 45876 | X62: Submitted
A63: FB-HWP1310 | B63: Lakeland | C63: 45930 | H63: 0 | J63: Yes | K63: Yes | L63: Received | M63: 45884 | N63: Completed | O63: 45882 | P63: Completed | Q63: Completed | R63: Completed | S63: Not Required | T63: Completed | U63: Pending | V63: Pending
A64: FB-HWP1375 | B64: Lakeland | C64: 45899 | D64: PLK97346 | H64: 0 | J64: Yes | K64: Yes | L64: Received | M64: 45884 | N64: Completed | O64: 45884 | P64: Completed | Q64: Completed | R64: Completed | S64: Not Required | T64: Completed | U64: Completed | V64: Completed | W64: 45908
A65: FB-HWP1376 | B65: Lakeland | C65: 45868 | D65: PLK96627 | H65: 0 | J65: Yes | K65: Yes | L65: Received | M65: 45824 | N65: Completed | O65: 45824 | P65: Completed | Q65: Completed | R65: Completed | S65: Not Required | T65: Completed | U65: Pending | V65: Pending | X65: Pending
A66: FB-HWP175 | B66: Lakeland | C66: 45838 | D66: PLK96355 | H66: 0 | J66: Yes | K66: Yes | L66: Received | M66: 45818 | N66: Completed | O66: 45817 | P66: Completed | Q66: Completed | R66: Completed | S66: Not Required | T66: Completed | U66: Completed | V66: Completed | W66: 45876 | X66: Submitted
A67: FB-HWP375 | B67: Lakeland | C67: 45899 | H67: 0 | J67: Yes | K67: Yes | L67: Received | M67: 45876 | N67: Completed | O67: 45876 | P67: Completed | Q67: Completed | R67: Completed | S67: Not Required | T67: Completed | U67: Pending | V67: Pending | W67: 45905
A68: FB-HWP401 | B68: Lakeland | C68: 45716 | H68: 0 | J68: No | K68: No | L68: Received | M68: Completed | N68: Completed | O68: Completed | P68: Completed | Q68: Completed | R68: Completed | S68: Not Required | T68: Completed | U68: Completed | V68: Completed | X68: Pending | Y68: =VLOOKUP(A68,#REF!,2,FALSE) -> #REF!
A69: FB-HWP482 | B69: Lakeland | C69: 45899 | D69: PLK97720 | H69: 0 | J69: Yes | K69: Yes | L69: Received | M69: 45870 | N69: Completed | O69: 45870 | P69: Completed | Q69: Completed | R69: Completed | S69: Not Required | T69: Completed | U69: Pending | V69: Pending
A70: FB-HWP701 | B70: Lakeland | C70: 45716 | D70: PLK89265 | H70: 0 | J70: Yes | K70: Yes | L70: Received | M70: 45705 | N70: Completed | O70: 45705 | P70: Completed | Q70: Completed | R70: Completed | S70: Not Required | T70: Completed | U70: Completed | V70: Completed | X70: Submitted | Y70: =VLOOKUP(A70,#REF!,2,FALSE) -> #REF!
A71: FB-HWP775 | B71: Lakeland | C71: 45899 | D71: PLK98767 | H71: 0 | J71: Yes | K71: Yes | L71: Received | M71: 45870 | N71: Completed | O71: 45870 | P71: Completed | Q71: Completed | R71: Completed | S71: Not Required | T71: Completed | U71: Pending | V71: Pending
A72: FB-HWP776 | B72: Lakeland | C72: 45899 | H72: 0 | J72: Yes | K72: Yes | L72: Received | M72: 45882 | N72: Completed | O72: 45882 | P72: Completed | Q72: Completed | R72: Completed | S72: Not Required | T72: Completed | U72: Completed | V72: Completed | W72: 45908
A73: FB-HWP801 | B73: Lakeland | C73: 45838 | D73: PLK94839 | H73: 0 | J73: Yes | K73: Yes | L73: Received | M73: 45790 | N73: Completed | O73: 45790 | P73: Completed | Q73: Completed | R73: Completed | S73: Not Required | T73: Completed | U73: Completed | V73: Completed | W73: 45821 | X73: Pending
A74: FB-HWP802 | B74: Lakeland | C74: 45899 | D74: PLK98828 | H74: 0 | J74: Yes | K74: Yes | L74: Received | M74: 45868 | N74: Completed | O74: 45871 | P74: Completed | Q74: Completed | R74: Completed | S74: Not Required | T74: Completed | U74: Pending | V74: Pending | W74: 45909
A75: FB-HWP804 | B75: Lakeland | C75: 45868 | D75: PLK97717 | H75: 0 | J75: Yes | K75: Yes | L75: Received | M75: 45853 | N75: Completed | O75: 45853 | P75: Completed | Q75: Completed | R75: Completed | S75: Not Required | T75: Completed | U75: Completed | V75: Completed | W75: 45905 | X75: Submitted
A76: FB-HWP902 | B76: Lakeland | C76: 45868 | D76: PLK97335 | H76: 0 | J76: Yes | K76: Yes | L76: Received | M76: 45838 | N76: Completed | O76: 45838 | P76: Completed | Q76: Completed | R76: Completed | S76: Not Required | T76: Completed | U76: Completed | V76: Completed | W76: 45895 | X76: Submitted
A77: FB-HWP975 | B77: Lakeland | C77: 45930 | H77: 0 | J77: Yes | K77: Yes | L77: Received | M77: 45902 | N77: Completed | O77: 45902 | P77: Completed | Q77: Completed | R77: Completed | S77: Not Required | T77: Completed | U77: Pending | V77: Pending | W77: 45923
A78: FB-HWP1075 | B78: Lakeland | C78: 45930 | H78: 0 | J78: Yes | K78: Yes | L78: Received | M78: 45902 | N78: Completed | O78: 45902 | P78: Completed | Q78: Completed | R78: Completed | S78: Not Required | T78: Completed | U78: Pending | V78: Pending | W78: 45925
A79: FX4-FWP-08 | B79: Lakeland | C79: 45792 | D79: PLK89273 | H79: 0 | J79: Yes | K79: Yes | L79: Received | M79: Completed | N79: Completed | O79: Completed | P79: Completed | Q79: Not Required | R79: Not Required | S79: Not Required | T79: Completed | U79: Completed | V79: Completed | W79: 45820 | X79: Submitted | Y79: =VLOOKUP(A79,#REF!,2,FALSE) -> #REF!
A80: FX4-FWP-13 | B80: Lakeland | C80: 45787 | D80: PLK93160 | H80: 0 | J80: Yes | K80: Yes | L80: Received | M80: TBD | N80: Completed | O80: TBD | P80: Completed | Q80: Not Required | R80: Not Required | S80: Not Required | T80: Completed | U80: Completed | V80: Completed | W80: 45848 | X80: Pending
A81: Golden Wings MHP | B81: Lakeland | C81: 45688 | D81: PLK88370 | H81: 48 | J81: Yes | K81: Yes | L81: Not Required | M81: Completed | N81: Completed | O81: 45678 | P81: Completed | Q81: Completed | R81: Not Req | S81: Completed | T81: Completed | U81: Completed | V81: Completed | W81: 45789 | X81: Submitted | Y81: =VLOOKUP(A81,#REF!,2,FALSE) -> #REF!
A82: Skyview Estates MHP | B82: Lakeland | C82: 45899 | H82: 208 | J82: Yes | K82: Yes | L82: Not Required | M82: 45874 | N82: Completed | O82: 45874 | P82: Completed | Q82: Completed | R82: Not Req | S82: Completed | T82: Completed | U82: Completed | V82: Completed
A83: BHU-FDH-01-W | B83: St Petersburg | C83: 45716 | D83: PPM89496 | H83: 0 | J83: Yes | K83: Yes | L83: Received | M83: 45705 | N83: Completed | O83: 45706 | P83: Completed | Q83: Completed | R83: Completed | S83: Not Required | T83: Completed | U83: Completed | V83: Completed | W83: 45818 | X83: Pending | Y83: =VLOOKUP(A83,#REF!,2,FALSE) -> #REF!
A84: D-H0220A | B84: St Petersburg | C84: 45742 | D84: PPM95827 | H84: 57 | J84: Yes | K84: Yes | L84: Received | M84: 45728 | N84: Completed | O84: 45728 | P84: Completed | Q84: Completed | R84: Not Req | S84: Completed | T84: Completed | U84: Completed | V84: Completed | W84: 45875 | X84: Submitted | Y84: =VLOOKUP(A84,#REF!,2,FALSE) -> #REF!
A85: D-H0220B | B85: St Petersburg | C85: 45742 | D85: PPM91680 | H85: 60 | J85: Yes | K85: Yes | L85: Received | M85: 45716 | N85: Completed | O85: 45719 | P85: Completed | Q85: Completed | R85: Not Req | S85: Completed | T85: Completed | U85: Completed | V85: Completed | W85: 45874 | X85: Submitted | Y85: =VLOOKUP(A85,#REF!,2,FALSE) -> #REF!
A86: D-H0220C | B86: St Petersburg | C86: 45742 | D86: PPM91630 | H86: 80 | J86: Yes | K86: Yes | L86: Received | M86: 45728 | N86: Completed | O86: 45728 | P86: Completed | Q86: Completed | R86: Not Req | S86: Completed | T86: Completed | U86: Completed | V86: Completed | W86: 45824 | X86: Submitted | Y86: =VLOOKUP(A86,#REF!,2,FALSE) -> #REF!
A87: D-H0220D | B87: St Petersburg | C87: 45742 | D87: PPM90335 | H87: 68 | J87: Yes | K87: Yes | L87: Received | M87: 45716 | N87: Completed | O87: Completed | P87: Completed | Q87: Completed | R87: Not Req | S87: Completed | T87: Completed | U87: Completed | V87: Pending | X87: Pending | Y87: =VLOOKUP(A87,#REF!,2,FALSE) -> #REF!
A88: D-H0221A | B88: St Petersburg | C88: 45742 | D88: PPM91357 | H88: 80 | J88: Yes | K88: Yes | L88: Received | M88: 45728 | N88: Completed | O88: 45728 | P88: Completed | Q88: Completed | R88: Not Req | S88: Completed | T88: Completed | U88: Completed | V88: Completed | W88: 45757 | X88: Pending | Y88: =VLOOKUP(A88,#REF!,2,FALSE) -> #REF!
A89: D-H0221B | B89: St Petersburg | C89: 45742 | D89: PPM91351 | H89: 56 | J89: Yes | K89: Yes | L89: Received | M89: 45716 | N89: Completed | O89: 45722 | P89: Completed | Q89: Completed | R89: Not Req | S89: Completed | T89: Completed | U89: Pending | V89: Pending | W89: 45825 | X89: Pending | Y89: =VLOOKUP(A89,#REF!,2,FALSE) -> #REF!
A90: D-H0221C | B90: St Petersburg | C90: 45742 | D90: PPM91690 | H90: 71 | J90: Yes | K90: Yes | L90: Received | M90: 45716 | N90: Completed | O90: 45727 | P90: Completed | Q90: Completed | R90: Not Req | S90: Completed | T90: Completed | U90: Pending | V90: Pending | W90: 45828 | X90: Pending | Y90: =VLOOKUP(A90,#REF!,2,FALSE) -> #REF!
A91: D-H0221D | B91: St Petersburg | C91: 45742 | D91: PPM91321 | H91: 81 | J91: Yes | K91: Yes | L91: Received | M91: 45716 | N91: Completed | O91: 45723 | P91: Completed | Q91: Completed | R91: Not Req | S91: Completed | T91: Completed | U91: Completed | V91: Completed | W91: 45831 | X91: Submitted | Y91: =VLOOKUP(A91,#REF!,2,FALSE) -> #REF!
A92: D-H0221E | B92: St Petersburg | C92: 45742 | D92: PPM90342 | H92: 38 | J92: Yes | K92: Yes | L92: Received | M92: 45716 | N92: Completed | O92: 45726 | P92: Completed | Q92: Completed | R92: Not Req | S92: Completed | T92: Completed | U92: Completed | V92: Pending | X92: Pending | Y92: =VLOOKUP(A92,#REF!,2,FALSE) -> #REF!
A93: D-H0221F | B93: St Petersburg | C93: 45772 | D93: PPM91656 | H93: 83 | J93: Yes | K93: Yes | L93: Received | M93: 45716 | N93: Completed | O93: 45727 | P93: Completed | Q93: Completed | R93: Not Req | S93: Completed | T93: Completed | U93: Completed | V93: Completed | W93: 45789 | X93: Submitted | Y93: =VLOOKUP(A93,#REF!,2,FALSE) -> #REF!
A94: D-H0222A | B94: St Petersburg | C94: 45711 | D94: PPM89513 | H94: 86 | J94: Yes | K94: Yes | L94: Received | M94: 45714 | N94: Completed | O94: 45693 | P94: Completed | Q94: Completed | R94: Not Req | S94: Completed | T94: Completed | U94: Pending | V94: Pending | X94: Pending | Y94: =VLOOKUP(A94,#REF!,2,FALSE) -> #REF!
A95: D-H0222B | B95: St Petersburg | C95: 45711 | D95: PPM89528 | H95: 76 | J95: Yes | K95: Yes | L95: Received | M95: 45692 | N95: Completed | O95: 45694 | P95: Completed | Q95: Completed | R95: Not Req | S95: Completed | T95: Completed | U95: Completed | V95: Completed | W95: 45814 | X95: Submitted | Y95: =VLOOKUP(A95,#REF!,2,FALSE) -> #REF!
A96: D-H0222C | B96: St Petersburg | C96: 45711 | D96: PPM89539 | H96: 89 | J96: Yes | K96: Yes | L96: Received | M96: 45695 | N96: Completed | O96: 45694 | P96: Completed | Q96: Completed | R96: Not Req | S96: Completed | T96: Completed | U96: Pending | V96: Pending | X96: Pending | Y96: =VLOOKUP(A96,#REF!,2,FALSE) -> #REF!
A97: D-H0222D | B97: St Petersburg | C97: 45711 | D97: PPM89539 | H97: 86 | J97: Yes | K97: Yes | L97: Received | M97: 45698 | N97: Completed | O97: 45688 | P97: Completed | Q97: Completed | R97: Not Req | S97: Completed | T97: Completed | U97: Completed | V97: Completed | W97: 45824 | X97: Submitted | Y97: =VLOOKUP(A97,#REF!,2,FALSE) -> #REF!
A98: D-H0223A | B98: St Petersburg | C98: 45711 | D98: PPM89575 | H98: 77 | J98: Yes | K98: Yes | L98: Received | M98: 45686 | N98: Completed | O98: 45692 | P98: Completed | Q98: Completed | R98: Not Req | S98: Completed | T98: Completed | U98: Pending | V98: Pending | W98: 45840 | X98: Pending | Y98: =VLOOKUP(A98,#REF!,2,FALSE) -> #REF!
A99: D-H0223C | B99: St Petersburg | C99: 45711 | D99: PPM89447 | H99: 81 | J99: Yes | K99: Yes | L99: Received | M99: 45700 | N99: Completed | O99: 45692 | P99: Completed | Q99: Completed | R99: Not Req | S99: Completed | T99: Completed | U99: Completed | V99: Completed | W99: 45814 | X99: Submitted | Y99: =VLOOKUP(A99,#REF!,2,FALSE) -> #REF!
A100: D-H0223D | B100: St Petersburg | C100: 45711 | D100: PPM89579 | H100: 81 | J100: Yes | K100: Yes | L100: Received | M100: 45699 | N100: Completed | O100: 45691 | P100: Completed | Q100: Completed | R100: Not Req | S100: Completed | T100: Completed | U100: Completed | V100: Completed | W100: 45789 | X100: Pending | Y100: =VLOOKUP(A100,#REF!,2,FALSE) -> #REF!
...

Sheet Completed Jobs Summary
B1: CURRENT ASSIGNMENTS | E1: MONTHLY ASSIGNED FOOTAGE
B2: Sum of Footage UG | E2: Vendor Assignment | F2: (Multiple Items) | P2: On Track or In Jeopardy | Q2: In Jeopardy
B3: Vendor Assignment | C3: Total | K3: Tillman forecasted Month | L3: APRIL | P3: Tillman forecasted Month | Q3: APRIL
B4: Brothers | C4: 53127 | E4: Sum of Footage UG | F4: Total | W4: Working Day | X4: 22
B5: Lightspeed In-House | C5: 12248 | E5: Total | F5: 107526 | K5: Count of Job No | P5: Count of Job No | W5: Day to Month | X5: 13
B6: (blank) | C6: 48410 | K6: On Track or In Jeopardy | L6: Job No | M6: Total | P6: Blockers | Q6: Job No | R6: Total
B7: Vendor Assignment | C7: 0 | K7: In Jeopardy | L7: BHT-FWP-06 | M7: 1 | P7: Manpower | R7: 1 | X7: % Month | Y7: % to Goal
B8: North Path | C8: 42234 | L8: BHT-FWP-07 | M8: 1 | P8: NTP Permit | R8: 1 | V8: Monthly Forecast Footage | W8: 203521 | X8: =X5/X4 -> 0.59090909 | Y8: =W9/W8 -> 0.31446386
B9: GN Systems | C9: 22737 | L9: D-HDH40 | M9: 1 | P9: Tie-ends | Q9: D-HDH40 | R9: 1 | V9: Footage Complete | W9: 64000
B10: Splice Only Project | C10: 3 | L10: D-HDH41 | M10: 1 | Q10: D-HDH42 | R10: 1
B11: Kattle One | C11: 24711 | L11: D-HDH42 | M11: 1 | Q11: D-HDH43 | R11: 1
B12: Kattle One/LSCG | C12: 6182 | L12: D-HDH43 | M12: 1 | Q12: D-HDH51 | R12: 1
B13: APT Communications / New Gen Unlimited | C13: 30807 | L13: D-HDH44 | M13: 1 | Q13: D-HDH62 | R13: 1
B14: Lopez Underground | C14: 58481 | L14: D-HDH50 | M14: 1 | P14: Tie-ends Total | R14: 5
B15: Power Connect | C15: 42151 | L15: D-HDH51 | M15: 1 | P15: (blank) | R15: 12
B16: Alpha Omega | C16: 18823 | L16: D-HDH52 | M16: 1 | P16: Grand Total | R16: 19
B17: HAS Global | C17: 3106 | L17: D-HDH53 | M17: 1
B18: APT Communications | C18: 15600 | L18: D-HDH54 | M18: 1
B19: ASM Utilities | C19: 11043 | L19: D-HDH55 | M19: 1
B20: HD Cable | C20: 16923 | L20: D-HDH57 | M20: 1
B21: Legant Livings | C21: 24336 | L21: D-HDH61 | M21: 1
B22: Gulfstream | C22: 10070 | L22: D-HDH62 | M22: 1
B23: Restoring Pro | C23: 19892 | L23: D-HDH80 | M23: 1
B24: Randy's Utilities | C24: 13494 | L24: FB-HDH02A | M24: 1
B25: A1 Broadband | C25: 13430 | L25: FB-HWP601 | M25: 1
B26: Full Circle In-House/Saul/Felipe | C26: 5350 | K26: In Jeopardy Total | M26: 19
B27: Sosa Line | C27: 7602 | K27: Complete | L27: D-HDH47 | M27: 1
B28: APT Communications/North Path | C28: 9133 | L28: D-HDH48 | M28: 1
B29: ASM | C29: 9260 | L29: D-HDH49 | M29: 1
B30: ITG In-House | C30: 7068 | L30: D-HDH56 | M30: 1
B31: Grand Total | C31: 526221 | L31: D-HDH58 | M31: 1
L32: D-HDH59 | M32: 1
L33: D-HDH60 | M33: 1
L34: D-HDH82 | M34: 1
L35: D-HWP702 | M35: 1
L36: D-HWP703 | M36: 1
L37: D-HWP706 | M37: 1
L38: D-HWP707 | M38: 1
K39: Complete Total | M39: 12
K40: Grand Total | M40: 31

Sheet Project Summary 
H1: D&E Update | Q1: Constuction Status
R2: Prism | S2: Local Team | T2: Penguin Task | U2: Penguin Task | V2: Penguin Task | W2: Penguin Task | X2: PLC | Y2: Noes
A3: Job No | B3: AREA | C3: TSD | D3: HHP | E3: Tillman forecasted Month | F3: Days | G3: On Track or In Jeopardy | H3: Permit Status | I3: Funding | J3: Required Permits | K3: Drafting | L3: Submitted | M3: Approved | N3: Pending Permits | O3: % Complete | P3: Blockers | Q3: Constuction Status | R3: Funding | S3: Materials | T3: Construction Start | U3: UG Percentage Complete | V3: Aerial Percentage Complete | W3: Splicing Percentage Complete | X3: Construction Total Percent Complete | Y3: Additional Information | Z3: Required Footage
A4: FB-HNP104 | B4: St Petersburg | C4: 45807 | E4: APRIL, MAY | G4: In Jeopardy | P4: Locates | Q4: Locates Called | R4: Funded | Z4: =VLOOKUP(A4,#REF!,9,FALSE) -> #REF!
A5: D-HNP107 | B5: St Petersburg | C5: 45807 | E5: APRIL, MAY | G5: In Jeopardy | P5: Locates | Q5: Locates Called | R5: Funded | Z5: =VLOOKUP(A5,#REF!,9,FALSE) -> #REF!
A6: D-HNP106 | B6: St Petersburg | C6: 45807 | E6: APRIL, MAY | G6: In Jeopardy | P6: Locates | Q6: Locates Called | R6: Funded | Z6: =VLOOKUP(A6,#REF!,9,FALSE) -> #REF!
A7: D-HNP110 | B7: St Petersburg | C7: 45807 | E7: APRIL, MAY | G7: In Jeopardy | P7: Locates | Q7: Locates Called | R7: Funded | Z7: =VLOOKUP(A7,#REF!,9,FALSE) -> #REF!
A8: D-HNP109 | B8: St Petersburg | C8: 45807 | E8: APRIL, MAY | G8: In Jeopardy | P8: NTP Permit | Q8: Hold | R8: Missing | Z8: =VLOOKUP(A8,#REF!,9,FALSE) -> #REF!
A9: D-HNP108 | B9: St Petersburg | C9: 45807 | E9: APRIL, MAY | G9: In Jeopardy | P9: Locates | Q9: Locates Called | R9: Funded | Z9: =VLOOKUP(A9,#REF!,9,FALSE) -> #REF!
A10: D-HNP104 | B10: St Petersburg | C10: #N/A | E10: APRIL, MAY | G10: In Jeopardy | P10: Locates | Q10: Not Started | R10: Funded | Z10: =VLOOKUP(A10,#REF!,9,FALSE) -> #REF!
A11: FB-HNP111 | B11: St Petersburg | C11: 45807 | E11: APRIL, MAY | G11: In Jeopardy | P11: Locates | Q11: Locates Called | R11: Funded | Z11: =VLOOKUP(A11,#REF!,9,FALSE) -> #REF!
A12: D-HNP114 | B12: St Petersburg | C12: #N/A | E12: APRIL, MAY | G12: In Jeopardy | P12: Locates | Q12: Locates Called | R12: Funded | Z12: =VLOOKUP(A12,#REF!,9,FALSE) -> #REF!
A13: D-HNP111 | B13: St Petersburg | C13: #N/A | E13: APRIL, MAY | G13: In Jeopardy | P13: Locates | Q13: Locates Called | R13: Funded | Z13: =VLOOKUP(A13,#REF!,9,FALSE) -> #REF!
A14: D-HNP113 | B14: St Petersburg | C14: 45807 | E14: APRIL, MAY | G14: In Jeopardy | P14: Locates | Q14: Locates Called | R14: Funded | Z14: =VLOOKUP(A14,#REF!,9,FALSE) -> #REF!
A15: D-HNP117 | B15: St Petersburg | C15: #N/A | E15: APRIL, MAY | G15: In Jeopardy | P15: Locates | Q15: Locates Called | R15: Funded | Z15: =VLOOKUP(A15,#REF!,9,FALSE) -> #REF!
A16: D-HNP115 | B16: St Petersburg | C16: #N/A | E16: APRIL, MAY | G16: In Jeopardy | P16: Locates | Q16: Locates Called | R16: Funded | Z16: =VLOOKUP(A16,#REF!,9,FALSE) -> #REF!
A17: FB-HDH02A | B17: St Petersburg | C17: #N/A | E17: APRIL | G17: In Jeopardy | Q17: Locates Called | R17: Funded | Z17: =VLOOKUP(A17,#REF!,9,FALSE) -> #REF!
A18: D-HDH80 | B18: St Petersburg | C18: 45807 | E18: APRIL | G18: In Jeopardy | P18: Manpower | R18: Funded | Z18: =VLOOKUP(A18,#REF!,9,FALSE) -> #REF!
A19: D-HDH82 | B19: St Petersburg | C19: #N/A | E19: APRIL | G19: Complete | Q19: Complete | R19: Funded | Z19: =VLOOKUP(A19,#REF!,9,FALSE) -> #REF!
A20: D-HDH47 | B20: St Petersburg | C20: #N/A | E20: APRIL | G20: Complete | Q20: Complete | R20: Funded | Z20: =VLOOKUP(A20,#REF!,9,FALSE) -> #REF!
A21: D-HDH44 | B21: #N/A | C21: 45807 | E21: APRIL | G21: In Jeopardy | Q21: In Process | R21: Funded | Y21: Need to follow-up if we need to place any additional underground conduit for the tie ins | Z21: =VLOOKUP(A21,#REF!,9,FALSE) -> #REF!
A22: D-HDH48 | B22: St Petersburg | C22: #N/A | E22: APRIL | G22: Complete | Q22: Complete | R22: Funded | Z22: =VLOOKUP(A22,#REF!,9,FALSE) -> #REF!
A23: D-HDH41 | B23: St Petersburg | C23: #N/A | E23: APRIL | G23: In Jeopardy | Q23: In Process | R23: Funded | Y23: blowing sting ray 5.1 | Z23: =VLOOKUP(A23,#REF!,9,FALSE) -> #REF!
A24: D-HDH40 | B24: #N/A | C24: 45716 | E24: APRIL | G24: In Jeopardy | P24: Tie-ends | Q24: In Process | R24: Funded | Y24: blowing sting ray 5.1 | Z24: =VLOOKUP(A24,#REF!,9,FALSE) -> #REF!
A25: D-HDH42 | B25: St Petersburg | C25: 45772 | E25: APRIL | G25: In Jeopardy | P25: Tie-ends | Q25: In Process | R25: Funded | Z25: =VLOOKUP(A25,#REF!,9,FALSE) -> #REF!
A26: D-HDH43 | B26: St Petersburg | C26: 45772 | E26: APRIL | G26: In Jeopardy | P26: Tie-ends | Q26: In Process | R26: Funded | Z26: =VLOOKUP(A26,#REF!,9,FALSE) -> #REF!
A27: D-HDH62 | B27: St Petersburg | C27: 45772 | E27: APRIL | G27: In Jeopardy | P27: Tie-ends | Q27: In Process | R27: Funded | Z27: =VLOOKUP(A27,#REF!,9,FALSE) -> #REF!
A28: D-HDH51 | E28: APRIL | G28: In Jeopardy | P28: Tie-ends | Q28: In Process | R28: Funded | Y28: Need to follow-up if we need to place any additional underground conduit for the tie ins | Z28: =VLOOKUP(A28,#REF!,9,FALSE) -> #REF!
A29: D-HDH61 | B29: #N/A | C29: #N/A | E29: APRIL | G29: In Jeopardy | Q29: In Process | R29: Funded | Y29: Need to follow-up if we need to place any additional underground conduit for the tie ins | Z29: =VLOOKUP(A29,#REF!,9,FALSE) -> #REF!
A30: D-HDH56 | B30: St Petersburg | C30: 45772 | E30: APRIL | G30: Complete | Q30: Complete | R30: Funded | Z30: =VLOOKUP(A30,#REF!,9,FALSE) -> #REF!
A31: D-HDH60 | B31: St Petersburg | C31: 45772 | E31: APRIL | G31: Complete | Q31: Complete | R31: Funded | Y31: Pending: confirm rock adder w/ Tillman Inspector to complete measurements | Z31: =VLOOKUP(A31,#REF!,9,FALSE) -> #REF!
A32: D-HDH58 | B32: St Petersburg | C32: 45772 | E32: APRIL | G32: Complete | Q32: Complete | R32: Funded | Z32: =VLOOKUP(A32,#REF!,9,FALSE) -> #REF!
A33: D-HDH53 | B33: St Petersburg | C33: 45831 | E33: APRIL | G33: In Jeopardy | Q33: In Process | R33: Funded | Z33: =VLOOKUP(A33,#REF!,9,FALSE) -> #REF!
A34: D-HDH50 | B34: St Petersburg | C34: 45831 | E34: APRIL | G34: In Jeopardy | Q34: In Process | R34: Funded | Z34: =VLOOKUP(A34,#REF!,9,FALSE) -> #REF!
A35: D-HDH52 | B35: St Petersburg | C35: 45831 | E35: APRIL | G35: In Jeopardy | Q35: In Process | R35: Funded | Z35: =VLOOKUP(A35,#REF!,9,FALSE) -> #REF!
A36: D-HDH49 | B36: St Petersburg | C36: 45772 | E36: APRIL | G36: Complete | Q36: Complete | R36: Funded | Z36: =VLOOKUP(A36,#REF!,9,FALSE) -> #REF!
A37: D-HDH54 | B37: St Petersburg | C37: 45831 | E37: APRIL | G37: In Jeopardy | Q37: In Process | R37: Funded | Z37: =VLOOKUP(A37,#REF!,9,FALSE) -> #REF!
A38: D-HDH55 | B38: St Petersburg | C38: 45831 | E38: APRIL | G38: In Jeopardy | Q38: In Process | R38: Funded | Z38: =VLOOKUP(A38,#REF!,9,FALSE) -> #REF!
A39: D-HDH59 | B39: #N/A | C39: #N/A | E39: APRIL | G39: Complete | Q39: Complete | R39: Funded | Y39: Need to follow-up if we need to place any additional underground conduit for the tie ins | Z39: =VLOOKUP(A39,#REF!,9,FALSE) -> #REF!
A40: D-HDH57 | B40: St Petersburg | C40: 45831 | E40: APRIL | G40: In Jeopardy | Q40: In Process | R40: Funded | Z40: =VLOOKUP(A40,#REF!,9,FALSE) -> #REF!
A41: FB-HNP144 | B41: St Petersburg | C41: 45807 | E41: APRIL, MAY | G41: In Jeopardy | P41: Locates | Q41: Not Started | R41: Funded | Z41: =VLOOKUP(A41,#REF!,9,FALSE) -> #REF!
A42: FB-HNP138 | B42: St Petersburg | C42: 45807 | E42: APRIL, MAY | G42: In Jeopardy | P42: Locates | Q42: In Process | R42: Funded | Z42: =VLOOKUP(A42,#REF!,9,FALSE) -> #REF!
A43: FB-HNP133 | B43: St Petersburg | C43: 45807 | E43: APRIL, MAY | G43: In Jeopardy | P43: Locates | Q43: Not Started | R43: Funded | Z43: =VLOOKUP(A43,#REF!,9,FALSE) -> #REF!
A44: FB-HNP118 | B44: St Petersburg | C44: 45807 | E44: APRIL, MAY | G44: In Jeopardy | P44: Manpower | Q44: In Process | R44: Funded | Z44: =VLOOKUP(A44,#REF!,9,FALSE) -> #REF!
A45: BHT-FWP-06 | B45: St Petersburg | C45: 45807 | E45: APRIL | G45: In Jeopardy | Q45: Not Started | R45: Funded | Z45: =VLOOKUP(A45,#REF!,9,FALSE) -> #REF!
A46: BHT-FWP-07 | B46: St Petersburg | C46: 45807 | E46: APRIL | G46: In Jeopardy | Q46: Not Started | R46: Funded | Z46: =VLOOKUP(A46,#REF!,9,FALSE) -> #REF!
A47: FB-HWP601 | B47: St Petersburg | C47: 45807 | E47: APRIL | G47: In Jeopardy | P47: NTP Permit | Q47: Not Started | R47: Missing | Z47: =VLOOKUP(A47,#REF!,9,FALSE) -> #REF!
A48: D-HWP707 | B48: St Petersburg | C48: 45807 | E48: APRIL | G48: Complete | P48: QC | Q48: Complete | R48: Funded | Z48: =VLOOKUP(A48,#REF!,9,FALSE) -> #REF!
A49: D-HWP703 | B49: Lakeland | C49: 45772 | E49: APRIL | G49: Complete | P49: QC | Q49: Complete | R49: Funded | Z49: =VLOOKUP(A49,#REF!,9,FALSE) -> #REF!
A50: D-HWP702 | B50: Lakeland | C50: 45772 | E50: APRIL | G50: Complete | P50: QC | Q50: Complete | R50: Funded | Z50: =VLOOKUP(A50,#REF!,9,FALSE) -> #REF!
A51: D-HWP706 | B51: #N/A | C51: #N/A | E51: APRIL | G51: Complete | P51: QC | Q51: Complete | R51: Funded | Z51: =VLOOKUP(A51,#REF!,9,FALSE) -> #REF!
A52: D-HWP1306 | B52: Lakeland | C52: 45925 | E52: APRIL, MAY | G52: In Jeopardy | P52: Locates | Q52: In Process | R52: Funded | Z52: =VLOOKUP(A52,#REF!,9,FALSE) -> #REF!
A53: D-HWP1309 | B53: Lakeland | C53: 45925 | E53: APRIL, MAY | G53: In Jeopardy | P53: Locates | Q53: In Process | R53: Funded | Z53: =VLOOKUP(A53,#REF!,9,FALSE) -> #REF!
A54: D-HWP1304 | B54: Lakeland | C54: 45925 | E54: APRIL, MAY | G54: In Jeopardy | P54: Locates | Q54: In Process | R54: Funded | Z54: =VLOOKUP(A54,#REF!,9,FALSE) -> #REF!
A55: D-HWP905 | B55: Lakeland | C55: 45862 | E55: APRIL, MAY | G55: In Jeopardy | P55: NTP Permit | Q55: Not Started | R55: Missing | Z55: =VLOOKUP(A55,#REF!,9,FALSE) -> #REF!
A56: D-HWP603 | C56: #N/A | E56: APRIL, MAY | G56: In Jeopardy | P56: SOW | Q56: Not Started | R56: Missing | Z56: =VLOOKUP(A56,#REF!,9,FALSE) -> #REF!
A57: BHT-FWP-10 | B57: Lakeland | C57: 45787 | E57: APRIL, MAY | G57: In Jeopardy | P57: NTP Permit | Q57: Not Started | R57: Missing | Z57: =VLOOKUP(A57,#REF!,9,FALSE) -> #REF!
A58: D-HWP1304 | B58: St Petersburg | C58: 45807 | E58: APRIL | G58: In Jeopardy | Q58: In Process | R58: Funded
A59: D-HWP1306 | B59: Lakeland | C59: 45772 | E59: APRIL | G59: In Jeopardy | Q59: In Process | R59: Funded
A60: D-HWP1309 | B60: Lakeland | C60: 45772 | E60: APRIL | G60: In Jeopardy | Q60: In Process | R60: Funded
B61: #N/A | C61: #N/A
B62: Lakeland | C62: 45925
B63: Lakeland | C63: 45925
B64: Lakeland | C64: 45925
B65: Lakeland | C65: 45862
C66: #N/A
A70: Drafting | B70: =SUM(K4:K9) -> 0 | C70: =B70/B73 -> #DIV/0!
A71: Submitted | B71: =SUM(L4:L9) -> 0 | C71: =B71/B73 -> #DIV/0!
A72: Approved | B72: =SUM(M4:M9) -> 0 | C72: =B72/B73 -> #DIV/0!
A73: Total | B73: =SUM(B70:B72) -> 0
A80: Locates - St Pete
A81: Locates - WOW
A82: Locates
A83: Locates - USIC
A84: Permits

Sheet Tillman UG Footage
A1: Market 1 NTP Number | B1: AREA | C1: SOW TSD Date | D1: Vendor Assignment | E1: Date Assigned | F1: Assigned Supervisor | G1: Penguin ID | H1: HHP | I1: On Track or In Jeopardy | J1: Permit Status | K1: Blockers/Risks | L1: Door Tag Date | M1: SOW Received | N1: SOW Estimated Cost | O1: NTP Received | P1: Constuction Status | Q1: Locate Date | R1: Restoration Completed | S1: QC Requested Date | T1: QC Sheet Phase 1 Received | U1: QC Sheet Phase 2 Received | V1: Footage UG | W1: Actual Redline Completed Footage UG | X1: Footage Remaining | Y1: UG Percentage Complete | Z1: Construction Start Date | AA1: Construction End Date | AB1: Fiber Placement Percentage Complete | AC1: Splicing Percentage Complete | AD1: Fiber Placement and Splice Only Footage | AE1: Notes
A2: D-HPP630 | B2: Clearwater | C2: 46325 | D2: Brothers | E2: 46171 | F2: Marcelo Zaldivar | H2: 67 | I2: On Track | J2: Received | M2: Yes | N2: 100866 | O2: Yes | P2: Completed | Q2: 46175 | V2: 9021 | W2: 8341 | X2: =SUM(V2-W2) -> 680 | Y2: =IFERROR($W2/$V2, 0) -> 0.92462033 | Z2: 46195 | AA2: 46230 | AB2: 0 | AC2: 0 | AD2: 0 | AE2: 5/1 NTP Package Received.
A3: D-HPP631 | B3: Clearwater | C3: 46325 | D3: Brothers | E3: 46170 | F3: Treyvon Tillman | H3: 93 | I3: On Track | J3: Received | M3: Yes | N3: 104934 | O3: Yes | P3: Completed | Q3: 46176 | V3: 8701 | W3: 7811 | X3: =SUM(V3-W3) -> 890 | Y3: =IFERROR($W3/$V3, 0) -> 0.89771291 | Z3: 46191 | AA3: 46261 | AB3: 0 | AC3: 0 | AD3: 0 | AE3: 5/1 NTP Package Received.
A4: D-HPP637 | B4: Clearwater | C4: 46325 | D4: Lightspeed In-House | E4: 46171 | F4: Treyvon Tillman | H4: 40 | I4: On Track | J4: Received | L4: 46182 | M4: Yes | N4: 91774 | O4: Yes | P4: In Process | Q4: 46171 | V4: 7530 | W4: 7204 | X4: =SUM(V4-W4) -> 326 | Y4: =IFERROR($W4/$V4, 0) -> 0.95670651 | Z4: 46217 | AB4: 0 | AC4: 0 | AD4: 0 | AE4: 5/1 NTP Package Received.
A5: FB-HPP612-2 | B5: Clearwater | C5: 46305 | F5: Anthony Adum | H5: 0 | I5: On Track | J5: Received | M5: No | N5: 649 | O5: Yes | P5: Not Started | V5: 0 | X5: =SUM(V5-W5) -> 0 | Y5: =IFERROR($W5/$V5, 0) -> 0 | AB5: 0 | AC5: 0 | AD5: 0 | AE5: 9/23 NTP Package Received--PO In Full Circle's Name Not ITG--Tillman Needs To Upload A New PO. Aerial Work Project.
A6: D-HNP108/D-H0102E | B6: St Petersburg | C6: 46080 | D6: Kattle One/LSCG | E6: 46018 | F6: Johnnie Williams | G6: PPM91941 | H6: 89 | I6: On Track | J6: Received | L6: 46028 | M6: Yes | N6: 72131.5 | O6: Yes | P6: In Process | Q6: 46014 | V6: 6182 | W6: 5899 | X6: =SUM(V6-W6) -> 283 | Y6: =IFERROR($W6/$V6, 0) -> 0.95422193 | Z6: 45891 | AB6: 0 | AC6: 0 | AD6: 0 | AE6: 5/11 - Stop work in place for City of St. Pete till 5/15 - 5/4 Will have to redrill 380' K1 drilled to deep and did not install the 2 tobys, Locates Called in - 4-28 JW // REPAIRED 1 OF 2 DAPs. NEED TO FIND ISSUE WITH THE 2ND DAP LOCATION - 3.16 JW // LSCG QC discovered missing section of Route 2, called in locates and they are pending
A9: Market 1 NTP Number Pinellas | B9: AREA | C9: SOW TSD Date | D9: Vendor Assignment | E9: Date Assigned | F9: Assigned Supervisor | G9: Penguin ID | H9: HHP | I9: On Track or In Jeopardy | J9: Permit Status | K9: Blockers/Risks | L9: Door Tag Date | M9: SOW Received | N9: SOW Estimated Cost | O9: NTP Received | P9: Constuction Status | Q9: Locate Date | R9: Restoration Completed | S9: QC Requested Date | T9: QC Sheet Phase 1 Received | U9: QC Sheet Phase 2 Received | V9: Footage UG | W9: Actual Redline Completed Footage UG | X9: Footage Remaining | Y9: UG Percentage Complete | Z9: Construction Start Date | AA9: Construction End Date | AB9: Fiber Placement Percentage Complete | AC9: Splicing Percentage Complete | AD9: Fiber Placement and Splice Only Footage | AE9: Notes
A10: D-HLC505 | B10: Pinellas | C10: 46325 | D10: Brothers | E10: 46295 | F10: Joshua Pacheco | H10: 41 | I10: On Track | J10: Received | K10: Pending Locates | L10: 46225 | M10: Yes | N10: 78963.5 | O10: Yes | P10: Locates Called | Q10: 46225 | V10: 5973 | X10: =SUM(V10-W10) -> 5973 | Y10: =IFERROR($W10/$V10, 0) -> 0 | AB10: 0 | AC10: 0 | AD10: 0 | AE10: 7/13 NTP Package Received. 7/17 PO Received And Approved.
A11: D-HLC508 | B11: Pinellas | C11: 46295 | D11: ASM Utilities | E11: 46223 | F11: Danny Combs | H11: 69 | I11: Completed -Missed TSD | J11: Received | M11: Yes | N11: 84458.5 | O11: Yes | P11: Completed | Q11: 46230 | V11: 6831 | W11: 5274 | X11: =SUM(V11-W11) -> 1557 | Y11: =IFERROR($W11/$V11, 0) -> 0.77206851 | Z11: 46281 | AA11: 46296 | AB11: 1 | AC11: 1 | AD11: 0 | AE11: 7/13 NTP Package Received. 7/17 PO Received And Approved.
A12: D-HLC509 | B12: Pinellas | C12: 46325 | D12: Brothers | E12: 46288 | F12: Anthony Adum | H12: 72 | I12: On Track | J12: Received | K12: Pending Locates | M12: No | N12: 69525.5 | O12: Yes | P12: Locates Called | Q12: 46288 | V12: 5407 | X12: =SUM(V12-W12) -> 5407 | Y12: =IFERROR($W12/$V12, 0) -> 0 | AB12: 0 | AC12: 0 | AD12: 0 | AE12: 9/18 NTP Package Received. PO Approved 9/24.
A13: D-HLC510 | B13: Pinellas | C13: 46325 | D13: Lightspeed In-House | E13: 46223 | F13: Treyvon Tillman | H13: 102 | I13: On Track | J13: Received | L13: 46224 | M13: Yes | N13: 59181 | O13: Yes | P13: In Process | Q13: 46230 | V13: 4718 | W13: 3520 | X13: =SUM(V13-W13) -> 1198 | Y13: =IFERROR($W13/$V13, 0) -> 0.74607885 | Z13: 46283 | AB13: 0 | AC13: 0 | AD13: 0 | AE13: 7/13 NTP Package Received. 7/17 PO Received And Approved.
A14: D-HLC514 | B14: Pinellas | C14: 46295 | D14: APT Communications | E14: 46219 | F14: Joshua Pacheco | G14: PPM112724 | H14: 83 | I14: Completed | J14: Received | K14: Pending Locates | L14: 46223 | M14: Yes | N14: 87651 | O14: Yes | P14: Completed | Q14: 46223 | V14: 7199 | W14: 6948 | X14: =SUM(V14-W14) -> 251 | Y14: =IFERROR($W14/$V14, 0) -> 0.96513405 | Z14: 46287 | AA14: 46296 | AB14: 1 | AC14: 1 | AD14: 0 | AE14: 7/13 NTP Package Received. 7/17 PO Received And Approved.
A15: D-HLC515 | B15: Pinellas | C15: 46295 | D15: Randy's Utilities | E15: 46241 | F15: Joshua Pacheco | H15: 18 | I15: Completed | J15: Received | K15: Pending Locates | L15: 46246 | M15: Yes | N15: 80560 | O15: Yes | P15: Completed | Q15: 46246 | V15: 6416 | W15: 6040 | X15: =SUM(V15-W15) -> 376 | Y15: =IFERROR($W15/$V15, 0) -> 0.94139651 | Z15: 46275 | AA15: 46289 | AB15: 1 | AC15: 1 | AD15: 0 | AE15: 8/5 NTP Package Received--8/6 PO Received.
A16: D-HLC516 | B16: Pinellas | C16: 46295 | D16: Legant Livings | E16: 46241 | F16: Joshua Pacheco | H16: 90 | I16: Completed | J16: Received | K16: Pending Locates | L16: 46237 | M16: Yes | N16: 113855.5 | O16: Yes | P16: Completed | Q16: 46260 | V16: 8970 | W16: 8050 | X16: =SUM(V16-W16) -> 920 | Y16: =IFERROR($W16/$V16, 0) -> 0.8974359 | Z16: 46274 | AA16: 46300 | AB16: 1 | AC16: 1 | AD16: 0 | AE16: 7/31 NTP Package Received.
A17: D-HLC520 | B17: Pinellas | C17: 46356 | D17: Power Connect | E17: 46301 | F17: Johnnie Williams | H17: 101 | I17: On Track | J17: Received | K17: Pending Locates | L17: 46275 | M17: Yes | N17: 72023 | O17: Yes | P17: Not Started | V17: 5644 | X17: 5644 | Y17: =IFERROR($W17/$V17, 0) -> 0 | AB17: 0 | AC17: 0 | AD17: 0 | AE17: 8/24 NTP Package and PO Received.
A18: D-HLC521 | B18: Pinellas | C18: 46325 | D18: Legant Livings | E18: 46267 | F18: Joshua Pacheco | H18: 108 | I18: On Track | J18: Received | K18: Pending Locates | M18: Yes | N18: 105904.5 | O18: Yes | P18: Locates Called | Q18: 46273 | V18: 8808 | X18: 8808 | Y18: =IFERROR($W18/$V18, 0) -> 0 | AB18: 0 | AC18: 0 | AD18: 0 | AE18: 8/24 NTP Package and PO Received.
A19: D-HLC522 | B19: Pinellas | C19: 46325 | D19: Legant Livings | E19: 46267 | F19: Joshua Pacheco | H19: 71 | I19: On Track | J19: Received | K19: Pending Locates | M19: Yes | N19: 79435.5 | O19: Yes | P19: Locates Called | Q19: 46274 | V19: 6374 | X19: 6374 | Y19: =IFERROR($W19/$V19, 0) -> 0 | AB19: 0 | AC19: 0 | AD19: 0 | AE19: 8/24 NTP Package and PO Received.
A20: D-HLC523 | B20: Pinellas | C20: 46356 | D20: Full Circle In-House/Saul/Felipe | E20: 46269 | F20: Johnnie Williams | H20: 92 | I20: On Track | J20: Received | K20: Pending Locates | M20: Yes | N20: 66908 | O20: Yes | P20: Locates Called | Q20: 46291 | V20: 5350 | X20: 5350 | Y20: =IFERROR($W20/$V20, 0) -> 0 | AB20: 0 | AC20: 0 | AD20: 0 | AE20: 8/24 NTP Package and PO Received.
A21: D-HLC524 | B21: Pinellas | C21: 46325 | D21: Randy's Utilities | E21: 46268 | F21: Joshua Pacheco | H21: 89 | I21: On Track | J21: Received | K21: Pending Locates | M21: Yes | N21: 86487 | O21: Yes | P21: Locates Called | Q21: 46281 | V21: 7078 | X21: =SUM(V21-W21) -> 7078 | Y21: =IFERROR($W21/$V21, 0) -> 0 | Z21: 46303 | AB21: 0 | AC21: 0 | AD21: 0 | AE21: 8/24 NTP Package and PO Received.
A22: D-HLC525 | B22: Pinellas | C22: 46356 | H22: 77 | I22: On Track | J22: Received | M22: Yes | N22: 92514.5 | O22: Yes | P22: Not Started | V22: 7434 | X22: =SUM(V22-W22) -> 7434 | Y22: =IFERROR($W22/$V22, 0) -> 0 | AB22: 0 | AC22: 0 | AD22: 0 | AE22: 9/30 NTP Package Received--Pending SOW/PO To Be Uploaded Into SiteTracker and For The Change Order To Be Approved By Tillman. 10/5 PO Approved--James H No Change Order Due At This Time.
A23: D-HLC527 | B23: Pinellas | C23: 46356 | H23: 69 | I23: On Track | J23: Received | M23: Yes | N23: 41647.5 | O23: Yes | P23: Not Started | V23: 3170 | X23: =SUM(V23-W23) -> 3170 | Y23: =IFERROR($W23/$V23, 0) -> 0 | AB23: 0 | AC23: 0 | AD23: 0 | AE23: 9/30 NTP Package Received--Pending SOW/PO To Be Uploaded Into SiteTracker and For The Change Order To Be Approved By Tillman. 10/5 PO Approved--James H No Change Order Due At This Time.
A24: D-HLC538 | B24: Pinellas | C24: 46356 | D24: APT Communications | E24: 46288 | F24: Johnnie Williams | H24: 37 | I24: On Track | J24: Received | K24: Pending Locates | M24: Yes | N24: 105048 | O24: Yes | P24: Locates Called | Q24: 46288 | V24: 8401 | X24: =SUM(V24-W24) -> 8401 | Y24: =IFERROR($W24/$V24, 0) -> 0 | AB24: 0 | AC24: 0 | AD24: 0 | AE24: 8/31 NTP Package and PO Received.
A25: D-HLC540 | B25: Pinellas | C25: 46356 | D25: Sosa Line | E25: 46297 | F25: Matthew Nunes | H25: 110 | I25: On Track | J25: Received | M25: Yes | N25: 54275 | O25: Yes | P25: Locates Called | Q25: 46297 | V25: 4386 | X25: 4386 | Y25: =IFERROR($W25/$V25, 0) -> 0 | AB25: 0 | AC25: 0 | AD25: 0 | AE25: 8/25 NTP Package and PO Received.
A26: D-HLC541 | B26: Pinellas | C26: 46356 | H26: 50 | I26: On Track | J26: Received | M26: Yes | N26: 82194.5 | O26: Yes | P26: Not Started | V26: 6948 | X26: =SUM(V26-W26) -> 6948 | Y26: =IFERROR($W26/$V26, 0) -> 0 | AB26: 0 | AC26: 0 | AD26: 0 | AE26: 9/30 NTP Package Received--Pending SOW/PO To Be Uploaded Into SiteTracker and For The Change Order To Be Approved By Tillman. 10/5 PO Approved--James H No Change Order Due At This Time.
A27: D-HLC547 | B27: Pinellas | C27: 46356 | D27: ASM Utilities | E27: 46297 | F27: Matthew Nunes | H27: 51 | I27: On Track | J27: Received | M27: Yes | N27: 53744.5 | O27: Yes | P27: Locates Called | Q27: 46297 | V27: 4212 | X27: 4212 | Y27: =IFERROR($W27/$V27, 0) -> 0 | AB27: 0 | AC27: 0 | AD27: 0 | AE27: 8/26 NTP Package and PO Received.
A28: D-HPP837 | B28: Pinellas | C28: 46325 | D28: Kattle One | E28: 46268 | F28: Danny Combs | H28: 23 | I28: On Track | J28: Received | M28: Yes | N28: 62033 | O28: Yes | P28: Locates Called | Q28: 46273 | V28: 4828 | X28: 4828 | Y28: =IFERROR($W28/$V28, 0) -> 0 | AB28: 0 | AC28: 0 | AD28: 0 | AE28: 8/25 NTP Package and PO Received.
A29: D-HPP838 | B29: Pinellas | C29: 46325 | D29: Kattle One | E29: 46268 | F29: Danny Combs | H29: 77 | I29: On Track | J29: Received | K29: Pending Locates | M29: Yes | N29: 64431 | O29: Yes | P29: Locates Called | Q29: 46273 | V29: 4931 | X29: 4931 | Y29: =IFERROR($W29/$V29, 0) -> 0 | AB29: 0 | AC29: 0 | AD29: 0 | AE29: 8/25 NTP Package and PO Received.
A30: D-HPP839 | B30: Pinellas | C30: 46325 | D30: Kattle One | E30: 46268 | F30: Danny Combs | H30: 65 | I30: On Track | J30: Received | K30: Pending Locates | M30: Yes | N30: 80031 | O30: Yes | P30: In Process | Q30: 46273 | V30: 6185 | W30: 5196 | X30: 6185 | Y30: =IFERROR($W30/$V30, 0) -> 0.84009701 | Z30: 46294 | AB30: 0 | AC30: 0 | AD30: 0 | AE30: 8/25 NTP Package and PO Received.
A31: D-HPP852 | B31: Pinellas | C31: 46325 | D31: Power Connect | E31: 46302 | F31: Treyvon Tillman | H31: 62 | I31: On Track | J31: Received | K31: Pending Locates | M31: Yes | N31: 95912 | O31: Yes | P31: Locates Called | Q31: 46301 | V31: 7541 | X31: 7541 | Y31: =IFERROR($W31/$V31, 0) -> 0 | AB31: 0 | AC31: 0 | AD31: 0 | AE31: 8/25 NTP Package and PO Received.
A32: D-HPP853 | B32: Pinellas | C32: 46325 | D32: Power Connect | E32: 46261 | F32: Treyvon Tillman | H32: 44 | I32: On Track | J32: Received | K32: Pending Locates | M32: Yes | N32: 89669 | O32: Yes | P32: Locates Called | Q32: 46304 | V32: 7072 | X32: 7072 | Y32: =IFERROR($W32/$V32, 0) -> 0 | AB32: 0 | AC32: 0 | AD32: 0 | AE32: 8/25 NTP Package and PO Received.
A33: D-HPP855 | B33: Pinellas | C33: 46325 | D33: Power Connect | E33: 46261 | F33: Treyvon Tillman | H33: 110 | I33: On Track | J33: Received | K33: Pending Locates | M33: Yes | N33: 96644.5 | O33: Yes | P33: Locates Called | Q33: 46301 | V33: 8090 | X33: 8090 | Y33: =IFERROR($W33/$V33, 0) -> 0 | AB33: 0 | AC33: 0 | AD33: 0 | AE33: 8/24 NTP Package and PO Received.
A34: D-HPP856 | B34: Pinellas | C34: 46325 | D34: Brothers | E34: 46288 | F34: Treyvon Tillman | H34: 45 | I34: On Track | J34: Received | K34: Pending Locates | M34: Yes | N34: 99698.5 | O34: Yes | P34: Locates Called | Q34: 46289 | V34: 8469 | X34: 8469 | Y34: =IFERROR($W34/$V34, 0) -> 0 | AB34: 0 | AC34: 0 | AD34: 0 | AE34: 8/24 NTP Package and PO Received.
A35: D-HPP857 | B35: Pinellas | C35: 46325 | D35: ASM | E35: 46288 | F35: Treyvon Tillman | H35: 90 | I35: On Track | J35: Received | K35: Pending Locates | M35: Yes | N35: 111605.5 | O35: Yes | P35: Locates Called | Q35: 46294 | V35: 9260 | X35: 9260 | Y35: =IFERROR($W35/$V35, 0) -> 0 | AB35: 0 | AC35: 0 | AD35: 0 | AE35: 8/24 NTP Package and PO Received.
A36: D-HPP860 | B36: Pinellas | C36: 46325 | D36: Brothers | E36: 46261 | F36: Anthony Adum | H36: 95 | I36: On Track | J36: Received | K36: Pending Locates | L36: 46267 | M36: Yes | N36: 69986 | O36: Yes | P36: Locates Called | Q36: 46284 | V36: 5310 | X36: 5310 | Y36: =IFERROR($W36/$V36, 0) -> 0 | AB36: 0 | AC36: 0 | AD36: 0 | AE36: 8/25 NTP Package and PO Received.
A37: D-HPP882 | B37: Pinellas | C37: 46325 | D37: Power Connect | E37: 46262 | F37: Danny Combs | H37: 64 | I37: On Track | J37: Received | K37: Pending Locates | M37: Yes | N37: 69701 | O37: Yes | P37: Locates Called | Q37: 46304 | V37: 5357 | X37: 5357 | Y37: =IFERROR($W37/$V37, 0) -> 0 | AB37: 0 | AC37: 0 | AD37: 0 | AE37: 8/26 NTP Package and PO Received.
A38: D-HPP883 | B38: Pinellas | C38: 46325 | D38: Power Connect | E38: 46262 | F38: Danny Combs | H38: 90 | I38: On Track | J38: Received | K38: Pending Locates | M38: Yes | N38: 92174.5 | O38: Yes | P38: Locates Called | Q38: 46304 | V38: 7153 | W38: 2088 | X38: 7153 | Y38: =IFERROR($W38/$V38, 0) -> 0.29190549 | Z38: 46287 | AB38: 0 | AC38: 0 | AD38: 0 | AE38: 8/26 NTP Package and PO Received.
A39: D-HPP884 | B39: Pinellas | C39: 46325 | D39: Kattle One | E39: 46282 | F39: Danny Combs | H39: 72 | I39: On Track | J39: Received | K39: Pending Locates | M39: Yes | N39: 105926.5 | O39: Yes | P39: Locates Called | Q39: 46296 | V39: 8767 | X39: 8767 | Y39: =IFERROR($W39/$V39, 0) -> 0 | AB39: 0 | AC39: 0 | AD39: 0 | AE39: 8/26 NTP Package and PO Received.
A40: FB-HLC521 | B40: Pinellas | C40: 46325 | D40: Legant Livings | E40: 46267 | F40: Joshua Pacheco | H40: 0 | I40: On Track | J40: Received | M40: Yes | N40: 2524 | O40: Yes | P40: Locates Called | Q40: 46273 | V40: 184 | X40: =SUM(V40-W40) -> 184 | Y40: =IFERROR($W40/$V40, 0) -> 0 | AB40: 0 | AC40: 0 | AD40: 0 | AE40: 8/26 NTP Package and PO Received.
A41: FB-HLC524 | B41: Pinellas | C41: 46325 | D41: Power Connect | E41: 46269 | F41: Johnnie Williams | H41: 0 | I41: On Track | J41: Received | M41: Yes | N41: 16946.9 | O41: Yes | P41: Locates Called | Q41: 46270 | V41: 1294 | X41: 1294 | Y41: =IFERROR($W41/$V41, 0) -> 0 | AB41: 0 | AC41: 0 | AD41: 0 | AE41: 8/26 NTP Package and PO Received.
A42: FB-HLC538 | B42: Pinellas | C42: 46353 | D42: Sosa Line | E42: 46283 | F42: Johnnie Williams | H42: 0 | I42: On Track | J42: Received | M42: Yes | N42: 41225.6 | O42: Yes | P42: In Process | Q42: 46287 | V42: 3216 | W42: 1739 | X42: 3216 | Y42: =IFERROR($W42/$V42, 0) -> 0.54073383 | Z42: 46301 | AB42: 0 | AC42: 0 | AD42: 0 | AE42: 8/26 NTP Package and PO Received.
A43: FB-HPP854 | B43: Pinellas | C43: 46325 | D43: Brothers | E43: 46261 | F43: Anthony Adum | H43: 0 | I43: On Track | J43: Received | K43: Pending Locates | L43: 46267 | M43: Yes | N43: 77452.2 | O43: Yes | P43: Locates Called | Q43: 46286 | V43: 6142 | W43: 1679 | X43: =SUM(V43-W43) -> 4463 | Y43: =IFERROR($W43/$V43, 0) -> 0.27336373 | Z43: 46294 | AB43: 0 | AC43: 0 | AD43: 0 | AE43: 8/26 NTP Package and PO Received.
A46: Market 2 NTP Number | B46: AREA | C46: SOW TSD Date | D46: Vendor Assignment | E46: Date Assigned | F46: Assigned Supervisor | G46: Penguin ID | H46: HHP | I46: On Track or In Jeopardy | J46: Permit Status | K46: Blockers/Risks | L46: Door Tag Date | M46: SOW Received | N46: SOW Estimated Cost | O46: NTP Received | P46: Constuction Status | Q46: Locate Date | R46: Restoration Completed | S46: QC Requested Date | T46: QC Sheet Phase 1 Received | U46: QC Sheet Phase 2 Received | V46: Footage UG | W46: Actual Redline Completed Footage UG | X46: Footage Remaining | Y46: UG Percentage Complete | Z46: Construction Start Date | AA46: Construction End Date | AB46: Fiber Placement Percentage Complete | AC46: Splicing Percentage Complete | AD46: Fiber Placement and Splice Only Footage | AE46: Notes
A47: FB-HWP376 | B47: Lakeland | C47: 46006 | D47: Brothers | E47: 45936 | F47: Miguel Herrero | G47: PLK102584 | H47: 0 | I47: On Track | J47: Received | K47: On Hold Per Tillman | L47: N/A | M47: Yes | N47: 54857.5 | O47: Yes | P47: In Process | Q47: 45933 | V47: 4104 | W47: 3928 | X47: =SUM(V47-W47) -> 176 | Y47: =IFERROR($W47/$V47, 0) -> 0.95711501 | Z47: 45938 | AB47: 0 | AC47: 0 | AD47: 0 | AE47: 9/29 FDOT Permit Received.Assigned to brothers 9-30/CX Began 10/8. 10/21 FDOT is complete, wtg on city permit 12-15, 10/8/26 - Tillman is working on plan to get Fiber Pulled and Spliced (Jesse)
A48: FB-HWP881 | B48: Lakeland | C48: 46142 | D48: Splice Only Project | F48: Eric | G48: PLK105476 | H48: 0 | I48: On Track | J48: Received | K48: On Hold Per Tillman | M48: Yes | N48: 255.05 | O48: Yes | P48: Locates Called | V48: 3 | X48: =SUM(V48-W48) -> 3 | Y48: =IFERROR($W48/$V48, 0) -> 0 | AB48: 0 | AC48: 0 | AD48: 0 | AE48: 11/17 Pending Permit.-Splice Only Project.
A51: Market 3 NTP Number | B51: AREA | C51: SOW TSD Date | D51: Vendor Assignment | E51: Date Assigned | F51: Assigned Supervisor | G51: Penguin ID | H51: HHP | I51: On Track or In Jeopardy | J51: Permit Status | K51: Blockers/Risks | L51: Door Tag Date | M51: SOW Received | N51: SOW Estimated Cost | O51: NTP Received | P51: Constuction Status | Q51: Locate Date | R51: Restoration Completed | S51: QC Requested Date | T51: QC Sheet Phase 1 Received | U51: QC Sheet Phase 2 Received | V51: Footage UG | W51: Actual Redline Completed Footage UG | X51: Footage Remaining | Y51: UG Percentage Complete | Z51: Construction Start Date | AA51: Construction End Date | AB51: Fiber Placement Percentage Complete | AC51: Splicing Percentage Complete | AD51: Fiber Placement and Splice Only Footage | AE51: Notes
A52: D-HLX101 | B52: Bradenton | C52: 46344 | D52: North Path | E52: 46292 | F52: Allen Johns | H52: 75 | I52: On Track | J52: Received | L52: 46292 | M52: Yes | N52: 73339.6 | O52: Yes | P52: In Process | Q52: 46292 | V52: 5791 | W52: 1706 | X52: =SUM(V52-W52) -> 4085 | Y52: =IFERROR($W52/$V52, 0) -> 0.29459506 | Z52: 46300 | AB52: 0 | AC52: 0 | AD52: 0 | AE52: 9/29 NTP Package Received--Pending SOW/PO To Be Uploaded Into SiteTracker and For The Change Order To Be Approved By Tillman. 10/5 PO and Change Order Approved.
A53: D-HLX102 | B53: Bradenton | C53: 46344 | D53: North Path | F53: Allen Johns | H53: 75 | I53: On Track | J53: Received | M53: No | O53: Yes | P53: Not Started | V53: 5465 | X53: =SUM(V53-W53) -> 5465 | Y53: =IFERROR($W53/$V53, 0) -> 0 | AB53: 0 | AC53: 0 | AD53: 0 | AE53: 9/29 NTP Package Received--Pending SOW/PO To Be Uploaded Into SiteTracker and For The Change Order To Be Approved By Tillman.
A54: D-HLX103 | B54: Bradenton | C54: 46344 | D54: North Path | F54: Allen Johns | H54: 86 | I54: On Track | J54: Received | M54: No | O54: Yes | P54: Not Started | V54: 5520 | X54: =SUM(V54-W54) -> 5520 | Y54: =IFERROR($W54/$V54, 0) -> 0 | AB54: 0 | AC54: 0 | AD54: 0 | AE54: 9/29 NTP Package Received--Pending SOW/PO To Be Uploaded Into SiteTracker and For The Change Order To Be Approved By Tillman.
A55: D-HLX104 | B55: Bradenton | C55: 46344 | D55: North Path | F55: Allen Johns | H55: 83 | I55: On Track | J55: Received | M55: No | O55: Yes | P55: Not Started | V55: 6204 | X55: =SUM(V55-W55) -> 6204 | Y55: =IFERROR($W55/$V55, 0) -> 0 | AB55: 0 | AC55: 0 | AD55: 0 | AE55: 9/29 NTP Package Received--Pending SOW/PO To Be Uploaded Into SiteTracker and For The Change Order To Be Approved By Tillman.
A56: D-HLX105 | B56: Bradenton | C56: 46344 | D56: North Path | F56: Allen Johns | H56: 36 | I56: On Track | J56: Received | M56: No | O56: Yes | P56: Not Started | V56: 3700 | X56: =SUM(V56-W56) -> 3700 | Y56: =IFERROR($W56/$V56, 0) -> 0 | AB56: 0 | AC56: 0 | AD56: 0 | AE56: 9/29 NTP Package Received--Pending SOW/PO To Be Uploaded Into SiteTracker and For The Change Order To Be Approved By Tillman.
A57: D-HLX106 | B57: Bradenton | C57: 46344 | D57: North Path | F57: Allen Johns | H57: 67 | I57: On Track | J57: Received | M57: No | O57: Yes | P57: Not Started | V57: 5013 | X57: =SUM(V57-W57) -> 5013 | Y57: =IFERROR($W57/$V57, 0) -> 0 | AB57: 0 | AC57: 0 | AD57: 0 | AE57: 9/29 NTP Package Received--Pending SOW/PO To Be Uploaded Into SiteTracker and For The Change Order To Be Approved By Tillman.
A58: D-HLX107 | B58: Bradenton | C58: 46344 | D58: North Path | F58: Allen Johns | H58: 47 | I58: On Track | J58: Received | M58: No | O58: Yes | P58: Not Started | V58: 4414 | X58: =SUM(V58-W58) -> 4414 | Y58: =IFERROR($W58/$V58, 0) -> 0 | AB58: 0 | AC58: 0 | AD58: 0 | AE58: 9/29 NTP Package Received--Pending SOW/PO To Be Uploaded Into SiteTracker and For The Change Order To Be Approved By Tillman.
A59: D-HLX108 | B59: Bradenton | C59: 46344 | D59: North Path | F59: Allen Johns | H59: 69 | I59: On Track | J59: Received | M59: Yes | N59: 65485.9 | O59: Yes | P59: Locates Called | Q59: 46287 | V59: 4613 | X59: =SUM(V59-W59) -> 4613 | Y59: =IFERROR($W59/$V59, 0) -> 0 | AB59: 0 | AC59: 0 | AD59: 0 | AE59: 9/29 NTP Package Received--Pending SOW/PO To Be Uploaded Into SiteTracker and For The Change Order To Be Approved By Tillman. 10/9 PO and Change Order Approved.
A60: FB-HOE179 | B60: Bradenton | C60: 46040 | D60: North Path | E60: 46125 | F60: Cody | G60: MAN104758 | H60: 0 | I60: On Track | J60: Received | M60: Yes | N60: 18171.6 | O60: Yes | P60: Locates Called | Q60: 46126 | V60: 1514 | X60: =SUM(V60-W60) -> 1514 | Y60: =IFERROR($W60/$V60, 0) -> 0 | AB60: 0 | AC60: 0 | AD60: 0 | AE60: 10/27 FDOT Permit Received--NTP Package Missing The Fiber Details Splicing Document. 4-24-25 On hold per Tillman
A61: FB-HLX101 | B61: Bradenton | C61: 46344 | H61: 0 | I61: On Track | J61: Received | M61: Yes | N61: 21152.35 | O61: Yes | P61: Not Started | V61: 1469 | X61: =SUM(V61-W61) -> 1469 | Y61: =IFERROR($W61/$V61, 0) -> 0 | AB61: 0 | AC61: 0 | AD61: 0 | AE61: 10/6 NTP Package Received--Pending Change Order To Be Approved By Tillman, Once Received I Can Approve The PO.
A62: Plantation Bay - 4 | B62: Bradenton | C62: 46233 | D62: APT Communications/North Path | E62: 46251 | F62: Brenton Copelin | G62: FM112414 | H62: 88 | I62: On Track | J62: Not Required | L62: 46251 | M62: Yes | N62: 101036.5 | O62: Yes | P62: In Process | Q62: 46224 | V62: 9133 | W62: 8984 | X62: =SUM(V62-W62) -> 149 | Y62: =IFERROR($W62/$V62, 0) -> 0.98368554 | Z62: 46275 | AB62: 1 | AC62: 1 | AD62: 0 | AE62: 6/11 NTP Package Received.
A63: BHCD-FPW-03-E | B63: Fort Myers | C63: 46233 | D63: Lopez Underground | E63: 46196 | F63: Joshua | H63: 0 | I63: On Track | J63: Received | M63: Yes | N63: 43061.3 | O63: Yes | P63: In Process | Q63: 46126 | V63: 11789 | W63: 10232 | X63: =SUM(V63-W63) -> 1557 | Y63: =IFERROR($W63/$V63, 0) -> 0.86792773 | Z63: 46210 | AB63: 0 | AC63: 0 | AD63: 0
A64: D-HDF708 | B64: Fort Myers | C64: 46081 | D64: GN Systems | E64: 46038 | F64: Joshua | G64: MAN104766 | H64: 88 | I64: On Track | J64: Pending | K64: Permits | L64: 46021 | M64: Yes | N64: 79638 | O64: Yes | P64: In Process | Q64: 46028 | V64: 6613 | W64: 6302 | X64: =SUM(V64-W64) -> 311 | Y64: =IFERROR($W64/$V64, 0) -> 0.95297142 | Z64: 46042 | AB64: 0 | AC64: 0 | AD64: 0 | AE64: 10/31 Permit Received With NTP Package./ 2/4 CX Construction Continues--Progress At 75% Complete./ 2/5 CX Construction Continues--Progress At 85% Complete./ 2/6 CX Construction Continues--Progress At 85% Complete./ 2/25 CX Construction Continues--Progress at 95% Complete.
A65: D-HDF709 | B65: Fort Myers | C65: 46344 | H65: 80 | I65: On Track | J65: Received | M65: Yes | N65: 71500 | O65: Yes | P65: Not Started | V65: 5625 | X65: =SUM(V65-W65) -> 5625 | Y65: =IFERROR($W65/$V65, 0) -> 0 | AE65: 10/7 NTP Package Received--PO Approved No Change Order Is Required.
A66: D-HDF712 | B66: Fort Myers | C66: 46081 | D66: GN Systems | E66: 46055 | F66: Joshua | G66: MAN108516 | H66: 86 | I66: On Track | J66: Pending | K66: Permits | L66: 46056 | M66: Yes | N66: 97494 | O66: Yes | P66: In Process | Q66: 46062 | V66: 8265 | W66: 8140 | X66: =SUM(V66-W66) -> 125 | Y66: =IFERROR($W66/$V66, 0) -> 0.98487598 | Z66: 46064 | AB66: 0 | AC66: 0 | AD66: 0 | AE66: 2/12 CX Construction Continues--Progress At 58% Complete./ 2/13 CX Construction Continues--Progress At 77% Complete./ 2/23 CX Construction Continues--Progress At 90% Complete./ 2/25 CX Construction Continues--Progress At 98% Complete.
A67: D-HDF717 | B67: Fort Myers | C67: 46325 | D67: ITG In-House | E67: 46304 | F67: Scott | H67: 86 | I67: On Track | J67: Received | L67: 46294 | M67: Yes | N67: 83702 | O67: Yes | P67: Locates Called | Q67: 46301 | V67: 6907 | X67: =SUM(V67-W67) -> 6907 | Y67: =IFERROR($W67/$V67, 0) -> 0 | AB67: 0 | AC67: 0 | AD67: 0 | AE67: 8/12 NTP Package and PO Received--PO In Full Circles Name Not ITG.
A68: D-HDF740 | B68: Fort Myers | C68: 46171 | D68: GN Systems | E68: 46043 | F68: Joshua | G68: MAN104770 | H68: 26 | I68: On Track | J68: Pending | K68: Permits | M68: Yes | N68: 35576 | O68: Yes | P68: In Process | Q68: 46028 | V68: 3150 | W68: 2970 | X68: =SUM(V68-W68) -> 180 | Y68: =IFERROR($W68/$V68, 0) -> 0.94285714 | Z68: 46043 | AB68: 0 | AC68: 0 | AD68: 0 | AE68: 10/29 Permit Received With NTP Package./ Requires FDOT Permit.
A69: D-HPW326 | B69: Fort Myers | C69: 46295 | D69: Lopez Underground | E69: 46255 | F69: Joshua | G69: FM113100 | H69: 81 | I69: On Track | J69: Received | M69: Yes | N69: 77302 | O69: Yes | P69: Locates Called | Q69: 46276 | V69: 6384 | X69: =SUM(V69-W69) -> 6384 | Y69: =IFERROR($W69/$V69, 0) -> 0 | AB69: 0 | AC69: 0 | AD69: 0 | AE69: 7/29 NTP Package Recived
A70: D-HPW327 | B70: Fort Myers | C70: 46295 | D70: Lopez Underground | E70: 46255 | F70: Joshua | G70: FM113101 | H70: 85 | I70: On Track | J70: Received | M70: Yes | N70: 78787 | O70: Yes | P70: Locates Called | Q70: 46268 | V70: 6242 | X70: =SUM(V70-W70) -> 6242 | Y70: =IFERROR($W70/$V70, 0) -> 0 | AB70: 0 | AC70: 0 | AD70: 0 | AE70: 7/29 NTP Package Recived
A71: D-HPW328 | B71: Fort Myers | C71: 46295 | D71: Lopez Underground | E71: 46255 | F71: Joshua | G71: FM113102 | H71: 84 | I71: On Track | J71: Received | M71: Yes | N71: 45941.5 | O71: Yes | P71: Locates Called | Q71: 46275 | V71: 3794 | X71: =SUM(V71-W71) -> 3794 | Y71: =IFERROR($W71/$V71, 0) -> 0 | AB71: 0 | AC71: 0 | AD71: 0 | AE71: 7/29 NTP Package Recived
A72: D-HPW329 | B72: Fort Myers | C72: 46295 | D72: Lopez Underground | E72: 46255 | F72: Joshua | G72: FM113103 | H72: 71 | I72: On Track | J72: Received | M72: Yes | N72: 71012.5 | O72: Yes | P72: Locates Called | Q72: 46268 | V72: 5739 | X72: =SUM(V72-W72) -> 5739 | Y72: =IFERROR($W72/$V72, 0) -> 0 | AB72: 0 | AC72: 0 | AD72: 0 | AE72: 7/24 NTP Package Recived
A73: D-HPW330 | B73: Fort Myers | C73: 46295 | D73: Lopez Underground | E73: 46255 | F73: Joshua | G73: FM113104 | H73: 80 | I73: On Track | J73: Received | M73: Yes | N73: 78742 | O73: Yes | P73: In Process | Q73: 46246 | V73: 6179 | W73: 2958 | X73: =SUM(V73-W73) -> 3221 | Y73: =IFERROR($W73/$V73, 0) -> 0.47871824 | Z73: 46261 | AB73: 0 | AC73: 0 | AD73: 0 | AE73: 7/29 NTP Package Recived
A74: D-HPW349 | B74: Fort Myers | C74: 46260 | D74: Alpha Omega | E74: 46274 | F74: Scott | G74: FM112767 | H74: 80 | I74: On Track | J74: Received | M74: Yes | N74: 77657.7 | O74: Yes | P74: Locates Called | Q74: 46294 | V74: 6243 | X74: =SUM(V74-W74) -> 6243 | Y74: =IFERROR($W74/$V74, 0) -> 0 | AB74: 0 | AC74: 0 | AD74: 0 | AE74: 6/11 NTP Package Received.
A75: D-HPW350 | B75: Fort Myers | C75: 46295 | D75: A1 Broadband | E75: 46288 | F75: Scott | G75: FM113097 | H75: 76 | I75: On Track | J75: Received | M75: Yes | N75: 88272 | O75: Yes | P75: Locates Called | Q75: 46291 | V75: 7206 | W75: 2730 | X75: =SUM(V75-W75) -> 4476 | Y75: =IFERROR($W75/$V75, 0) -> 0.37885096 | Z75: 46300 | AB75: 0 | AC75: 0 | AD75: 0 | AE75: 7/29 NTP Package Recived
A76: D-HPW351 | B76: Fort Myers | C76: 46295 | D76: Restoring Pro | E76: 46288 | F76: Joshua | G76: FM113098 | H76: 83 | I76: On Track | J76: Received | M76: Yes | N76: 57368 | O76: Yes | P76: Locates Called | Q76: 46294 | V76: 4517 | X76: =SUM(V76-W76) -> 4517 | Y76: =IFERROR($W76/$V76, 0) -> 0 | AB76: 0 | AC76: 0 | AD76: 0 | AE76: 7/24 NTP Package Recived
A77: D-HPW361 | B77: Fort Myers | C77: 46229 | D77: Alpha Omega | E77: 46254 | F77: Scott | G77: FM113099 | H77: 82 | I77: On Track | J77: Received | M77: Yes | N77: 85513 | O77: Yes | P77: In Process | Q77: 46286 | V77: 6678 | W77: 3060 | X77: =SUM(V77-W77) -> 3618 | Y77: =IFERROR($W77/$V77, 0) -> 0.45822102 | Z77: 46274 | AB77: 0 | AC77: 0 | AD77: 0 | AE77: 6/11 NTP Package Received.
A78: D-HTG211 | B78: Fort Myers | C78: 46344 | D78: A1 Broadband | E78: 46304 | F78: Scott | H78: 68 | I78: On Track | J78: Received | M78: No | N78: 76637.05 | O78: Yes | P78: Not Started | V78: 6224 | X78: =SUM(V78-W78) -> 6224 | Y78: =IFERROR($W78/$V78, 0) -> 0 | AB78: 0 | AC78: 0 | AD78: 0 | AE78: 10/6 NTP Package Received--Pending PO To Be Approved and Verification Of BOM To See If A Change Order Is Required.
A79: D-HTG212 | B79: Fort Myers | C79: 46264 | D79: Gulfstream | E79: 46231 | F79: Joshua | G79: FM112875 | H79: 85 | I79: On Track | J79: Received | M79: Yes | N79: 64416.5 | O79: Yes | P79: In Process | Q79: 46232 | V79: 5445 | W79: 4690 | X79: =SUM(V79-W79) -> 755 | Y79: =IFERROR($W79/$V79, 0) -> 0.86134068 | Z79: 46245 | AB79: 0 | AC79: 0 | AD79: 0 | AE79: 7/24 NTP Package Recived
A80: D-HTG213 | B80: Fort Myers | C80: 46295 | D80: HD Cable | E80: 46231 | F80: Joshua | G80: FM112877 | H80: 46 | I80: On Track | J80: Received | M80: Yes | N80: 54627.5 | O80: Yes | P80: In Process | Q80: 46232 | V80: 4834 | W80: 4752 | X80: =SUM(V80-W80) -> 82 | Y80: =IFERROR($W80/$V80, 0) -> 0.98303682 | Z80: 46247 | AB80: 0 | AC80: 0 | AD80: 0 | AE80: 7/24 NTP Package Recived
A81: D-HTG214 | B81: Fort Myers | C81: 46295 | D81: HD Cable | E81: 46231 | F81: Joshua | G81: FM112878 | H81: 82 | I81: On Track | J81: Received | M81: Yes | N81: 77688.5 | O81: Yes | P81: Locates Called | Q81: 46232 | V81: 6136 | X81: =SUM(V81-W81) -> 6136 | Y81: =IFERROR($W81/$V81, 0) -> 0 | AB81: 0 | AC81: 0 | AD81: 0 | AE81: 7/24 NTP Package Recived
A82: D-HTG231 | B82: Fort Myers | C82: 46264 | D82: Restoring Pro | E82: 46231 | F82: Joshua | G82: FM112883 | H82: 90 | I82: On Track | J82: Received | M82: Yes | N82: 90888 | O82: Yes | P82: In Process | Q82: 46232 | V82: 7881 | W82: 6923 | X82: =SUM(V82-W82) -> 958 | Y82: =IFERROR($W82/$V82, 0) -> 0.87844182 | Z82: 46246 | AB82: 0 | AC82: 0 | AD82: 0 | AE82: 5/29 NTP Received
A83: D-HTG242 | B83: Fort Myers | C83: 46386 | D83: HAS Global | E83: 46304 | F83: Joshua | H83: 66 | I83: On Track | J83: Received | M83: Yes | N83: 38841 | O83: Yes | P83: Not Started | V83: 3106 | X83: =SUM(V83-W83) -> 3106 | Y83: =IFERROR($W83/$V83, 0) -> 0 | AB83: 0 | AC83: 0 | AD83: 0 | AE83: 8/17 NTP Package Received
A84: D-HTG307 | B84: Fort Myers | C84: 46203 | D84: Lopez Underground | E84: 46184 | F84: Joshua | H84: 62 | I84: On Track | J84: Received | M84: Yes | N84: 48766 | O84: Yes | P84: In Process | Q84: 46185 | V84: 4009 | W84: 3230 | X84: =SUM(V84-W84) -> 779 | Y84: =IFERROR($W84/$V84, 0) -> 0.8056872 | Z84: 46281 | AB84: 0 | AC84: 0 | AD84: 0 | AE84: 4/30 NTP Received.
A85: FB-HTG285 | B85: Fort Myers | C85: 46325 | D85: ITG In-House | E85: 46303 | F85: Scott | H85: 0 | I85: On Track | J85: Received | L85: na | M85: Yes | N85: 1721.7 | O85: Yes | P85: Not Started | Q85: 46303 | V85: 79 | X85: =SUM(V85-W85) -> 79 | Y85: =IFERROR($W85/$V85, 0) -> 0 | AB85: 0 | AC85: 0 | AD85: 0 | AE85: 10/7 NTP Package Received--PO Approved No Change Order Is Required.
A86: FB-HTG288 | B86: Fort Myers | C86: 46203 | D86: Alpha Omega | E86: 46184 | F86: Joshua | H86: 0 | I86: On Track | J86: Received | M86: Yes | N86: 75219.2 | O86: Yes | P86: In Process | Q86: 46189 | V86: 5902 | W86: 5737 | X86: =SUM(V86-W86) -> 165 | Y86: =IFERROR($W86/$V86, 0) -> 0.97204338 | Z86: 46210 | AB86: 0 | AC86: 0 | AD86: 0 | AE86: 5/8 NTP Package Received
A87: FB-HTG302 | B87: Fort Myers | C87: 46325 | D87: ITG In-House | E87: 46303 | F87: Scott | H87: 0 | I87: On Track | J87: Received | L87: na | M87: Yes | N87: 1549.65 | O87: Yes | P87: Not Started | Q87: 46303 | V87: 82 | X87: =SUM(V87-W87) -> 82 | Y87: =IFERROR($W87/$V87, 0) -> 0 | AB87: 0 | AC87: 0 | AD87: 0 | AE87: 10/7 NTP Package Received--PO Approved No Change Order Is Required.
A88: Promenades At The Forum | B88: Fort Myers | C88: 46172 | D88: APT Communications / New Gen Unlimited | H88: 402 | I88: On Track | J88: Not Required | L88: 46092 | M88: Yes | N88: 438978.5 | O88: Yes | P88: Locates Called | Q88: 46091 | V88: 30807 | X88: =SUM(V88-W88) -> 30807 | Y88: =IFERROR($W88/$V88, 0) -> 0 | AB88: 0 | AC88: 0 | AD88: 0 | AE88: 3/16/2026 on hold needs permit per tillman. 4/2 Pending Utility Permit From Tillman.
A89: D-HSF401 | B89: Port Charlotte | C89: 46295 | D89: HD Cable | E89: 46254 | F89: Joshua | G89: FM113091 | H89: 79 | I89: On Track | J89: Received | M89: Yes | N89: 75443.75 | O89: Yes | P89: In Process | Q89: 46259 | V89: 5953 | W89: 1603 | X89: =SUM(V89-W89) -> 4350 | Y89: =IFERROR($W89/$V89, 0) -> 0.269276 | Z89: 46290 | AB89: 0 | AC89: 0 | AD89: 0 | AE89: 7/24 PO Received.
A90: D-HSF420 | B90: Port Charlotte | C90: 46295 | D90: GN Systems | E90: 46254 | F90: Brenton Copelin | G90: FM113095 | H90: 49 | I90: On Track | J90: Received | M90: Yes | N90: 58273.5 | O90: No | P90: In Process | Q90: 46274 | V90: 4709 | W90: 4362 | X90: =SUM(V90-W90) -> 347 | Y90: =IFERROR($W90/$V90, 0) -> 0.92631132 | Z90: 46288 | AB90: 0 | AC90: 0 | AD90: 0 | AE90: 8/3 PO Uploaded Into SiteTracker.
A91: FB-HSF606 | B91: Port Charlotte | C91: 46111 | H91: 0 | I91: On Track | J91: Pending | K91: SOW Pending | M91: No | O91: No | P91: Not Started | X91: =SUM(V91-W91) -> 0 | Y91: =IFERROR($W91/$V91, 0) -> 0 | AB91: 0 | AC91: 0 | AD91: 0 | AE91: 2/19 Pending NTP Package and SOW.
A92: FB-HSF675 | B92: Port Charlotte | C92: 46111 | H92: 0 | I92: On Track | J92: Pending | K92: SOW Pending | M92: No | O92: No | P92: Not Started | X92: =SUM(V92-W92) -> 0 | Y92: =IFERROR($W92/$V92, 0) -> 0 | AB92: 0 | AC92: 0 | AD92: 0 | AE92: 2/19 Pending NTP Package and SOW.
A95: Market 4 NTP Number | B95: AREA | C95: SOW TSD Date | D95: Vendor Assignment | E95: Date Assigned | F95: Assigned Supervisor | G95: Penguin ID | H95: HHP | I95: On Track or In Jeopardy | J95: Permit Status | K95: Blockers/Risks | L95: Door Tag Date | M95: SOW Received | N95: SOW Estimated Cost | O95: NTP Received | P95: Constuction Status | Q95: Locate Date | R95: Restoration Completed | S95: QC Requested Date | T95: QC Sheet Phase 1 Received | U95: QC Sheet Phase 2 Received | V95: Footage UG | W95: Actual Redline Completed Footage UG | X95: Footage Remaining | Y95: UG Percentage Complete | Z95: Construction Start Date | AA95: Construction End Date | AB95: Fiber Placement Percentage Complete | AC95: Splicing Percentage Complete | AD95: Fiber Placement and Splice Only Footage | AE95: Notes
A96: D-HEF115 | B96: Lee | C96: 46344 | H96: 74 | I96: On Track | J96: Received | M96: No | N96: 42924 | O96: Yes | P96: Not Started | V96: 3159 | X96: =SUM(V96-W96) -> 3159 | Y96: =IFERROR($W96/$V96, 0) -> 0 | AB96: 0 | AC96: 0 | AD96: 0 | AE96: 10/7 NTP Package Received--Pending PO To Be Approved and Verification Of BOM To See If A Change Order Is Required.
A97: D-HEF116 | B97: Lee | C97: 46344 | H97: 87 | I97: On Track | J97: Received | M97: No | N97: 73538 | O97: Yes | P97: Not Started | V97: 5678 | X97: =SUM(V97-W97) -> 5678 | Y97: =IFERROR($W97/$V97, 0) -> 0 | AB97: 0 | AC97: 0 | AD97: 0 | AE97: 10/7 NTP Package Received--Pending PO To Be Approved and Verification Of BOM To See If A Change Order Is Required.
A98: D-HLP401 | B98: Collier | F98: Aldo Layedra | H98: 85 | I98: On Track | J98: Pending | K98: NTP Pending | M98: No | O98: No | P98: Not Started | V98: 14927 | W98: 0 | X98: =SUM(V98-W98) -> 14927 | Y98: =IFERROR($W98/$V98, 0) -> 0 | AB98: 0 | AC98: 0 | AD98: 0 | AE98: 9/7 Pending NTP Package
A99: D-HLP403 | B99: Collier | F99: Aldo Layedra | H99: 87 | I99: On Track | J99: Pending | K99: NTP Pending | M99: No | O99: No | P99: Not Started | V99: 15088 | W99: 0 | X99: =SUM(V99-W99) -> 15088 | Y99: =IFERROR($W99/$V99, 0) -> 0 | AB99: 0 | AC99: 0 | AD99: 0 | AE99: 9/7 Pending NTP Package
A100: D-HLP404 | B100: Collier | C100: 46283 | D100: DMC Boring | F100: Aldo Layedra | H100: 87 | I100: On Track | J100: Received | M100: Yes | O100: Yes | P100: In Process | Q100: 46238 | V100: 17114 | W100: 12706 | X100: =SUM(V100-W100) -> 4408 | Y100: =IFERROR($W100/$V100, 0) -> 0.7424331 | AB100: 0 | AC100: 0 | AD100: 0
A101: D-HLP405 | B101: Collier | F101: Aldo Layedra | H101: 76 | I101: On Track | J101: Pending | K101: NTP Pending | M101: No | O101: No | P101: Not Started | V101: 0 | W101: 0 | X101: =SUM(V101-W101) -> 0 | Y101: =IFERROR($W101/$V101, 0) -> 0 | AB101: 0 | AC101: 0 | AD101: 0 | AE101: 9/7 Pending NTP Package
A102: D-HLP406 | B102: Collier | F102: Aldo Layedra | H102: 86 | I102: On Track | J102: Pending | K102: NTP Pending | M102: No | O102: No | P102: Not Started | V102: 14639 | W102: 0 | X102: =SUM(V102-W102) -> 14639 | Y102: =IFERROR($W102/$V102, 0) -> 0 | AB102: 0 | AC102: 0 | AD102: 0 | AE102: 9/7 Pending NTP Package
A103: D-HLP601 | B103: Collier | F103: Aldo Layedra | H103: 83 | I103: On Track | J103: Pending | K103: NTP Pending | M103: No | O103: No | P103: Not Started | V103: 5731 | W103: 0 | X103: =SUM(V103-W103) -> 5731 | Y103: =IFERROR($W103/$V103, 0) -> 0 | AB103: 0 | AC103: 0 | AD103: 0 | AE103: 9/7 Pending NTP Package
A104: D-HLP603 | B104: Collier | F104: Aldo Layedra | H104: 84 | I104: On Track | J104: Pending | K104: NTP Pending | M104: No | O104: No | P104: Not Started | V104: 6590 | W104: 0 | X104: =SUM(V104-W104) -> 6590 | Y104: =IFERROR($W104/$V104, 0) -> 0 | AB104: 0 | AC104: 0 | AD104: 0 | AE104: 9/7 Pending NTP Package
A105: D-HLP604 | B105: Collier | F105: Aldo Layedra | H105: 87 | I105: On Track | J105: Pending | K105: NTP Pending | M105: No | O105: No | P105: Not Started | V105: 6765 | W105: 0 | X105: =SUM(V105-W105) -> 6765 | Y105: =IFERROR($W105/$V105, 0) -> 0 | AB105: 0 | AC105: 0 | AD105: 0 | AE105: 9/7 Pending NTP Package
A106: D-HLP605 | B106: Collier | F106: Aldo Layedra | H106: 79 | I106: On Track | J106: Pending | K106: NTP Pending | M106: No | O106: No | P106: Not Started | V106: 5974 | W106: 0 | X106: =SUM(V106-W106) -> 5974 | Y106: =IFERROR($W106/$V106, 0) -> 0 | AB106: 0 | AC106: 0 | AD106: 0 | AE106: 9/7 Pending NTP Package
A107: D-HLP606 | B107: Collier | F107: Aldo Layedra | H107: 82 | I107: On Track | J107: Pending | K107: NTP Pending | M107: No | O107: No | P107: Not Started | V107: 5120 | W107: 0 | X107: =SUM(V107-W107) -> 5120 | Y107: =IFERROR($W107/$V107, 0) -> 0 | AB107: 0 | AC107: 0 | AD107: 0 | AE107: 9/7 Pending NTP Package
A108: D-HLP607 | B108: Collier | C108: 46310 | D108: AGN Undergrounds | F108: Aldo Layedra | H108: 73 | I108: On Track | J108: Pending | K108: Pending Locates | M108: Yes | O108: Yes | P108: Locates Called | V108: 4585 | W108: 0 | X108: =SUM(V108-W108) -> 4585 | Y108: =IFERROR($W108/$V108, 0) -> 0 | AB108: 0 | AC108: 0 | AD108: 0
...

Sheet Pending Resto-COP Packages
A1: NTP Number | B1: AREA | C1: SOW TSD Date | D1: Vendor Assignment | E1: Date Assigned | F1: Assigned Supervisor | G1: Penguin ID | H1: HHP | I1: On Track or In Jeopardy | J1: Permit Status | K1: Blockers/Risks | L1: Door Tag Date | M1: SOW Received | N1: SOW Estimated Cost | O1: NTP Received | P1: Constuction Status | Q1: Locate Date | R1: Restoration Completed | S1: QC Requested Date | T1: QC Sheet Phase 1 Received | U1: QC Sheet Phase 2 Received | V1: Footage UG | W1: Actual Redline Completed Footage UG | X1: Footage Remaining | Y1: UG Percentage Complete | Z1: Construction Start Date | AA1: Construction End Date | AB1: Fiber Placement Percentage Complete | AC1: Splicing Percentage Complete | AD1: Fiber Placement and Splice Only Footage | AE1: Notes | AF1: Friday 09/25 updates
A2: BHU-FLX-01-E | B2: Bradenton | C2: 46172 | D2: Lightspeed In-House | E2: 46077 | F2: Johnnie Williams | G2: MAN109507 | H2: 0 | I2: Completed on Track | J2: Received | L2: N/A | M2: Yes | N2: 49846.95 | O2: Yes | P2: Completed | Q2: 46093 | R2: Yes | S2: 46182 | T2: 6/22 Failed QC | U2: 46182 | V2: 3109 | W2: 3128 | X2: =SUM(V2-W2) -> -19 | Y2: =IFERROR($W2/$V2, 0) -> 1.0061113 | Z2: 46132 | AA2: 46150 | AB2: 1 | AC2: 1 | AD2: 1 | AE2: 3/9 NTP and SOW Received.3/12 LC/4-17 Locates cleared/Cx starts 4-20 | AF2: Passed QC. Pending email
A3: BHUD-FOE-401-W | B3: Bradenton | C3: 46295 | D3: North Path | E3: 46231 | F3: Cody | G3: MAN112893 | H3: 0 | I3: Completed on Track | J3: Received | L3: N/A | M3: Yes | N3: 18856.2 | O3: Yes | P3: Completed | Q3: 46234 | R3: Yes | S3: 46279 | T3: 46283 | U3: 46283 | V3: 1412 | W3: 1406 | X3: =SUM(V3-W3) -> 6 | Y3: =IFERROR($W3/$V3, 0) -> 0.99575071 | Z3: 46252 | AA3: 46253 | AB3: 1 | AC3: 0 | AD3: 0 | AE3: 7/24 NTP Package Recived--Pending Fiber Details Splcing Document | AF3: Needs to be scheduled for QC
A4: D-HAL113 | B4: Bradenton | C4: 46295 | D4: North Path | E4: 46258 | F4: Brenton Copelin | G4: MAN113114 | H4: 86 | I4: Completed on Track | J4: Received | L4: 46265 | M4: Yes | N4: 52728 | O4: Yes | P4: Completed | Q4: 46261 | R4: Yes | S4: 46294 | T4: 46296 | U4: 46296 | V4: 3508 | W4: 3492 | X4: =SUM(V4-W4) -> 16 | Y4: =IFERROR($W4/$V4, 0) -> 0.995439 | Z4: 46280 | AA4: 46289 | AB4: 1 | AC4: 1 | AD4: 1 | AE4: 8/24 NTP Package Received | AF4: Needs change order.
A5: D-HAL114 | B5: Bradenton | C5: 46295 | D5: North Path | E5: 46251 | F5: Brenton Copelin | G5: MAN113033 | H5: 62 | I5: Completed on Track | J5: Received | L5: N/A | M5: Yes | N5: 42744 | O5: Yes | P5: Completed | Q5: 46255 | R5: Yes | S5: 46294 | T5: 46296 | U5: 46296 | V5: 3148 | W5: 3199 | X5: =SUM(V5-W5) -> -51 | Y5: =IFERROR($W5/$V5, 0) -> 1.0162008 | Z5: 46259 | AA5: 46261 | AB5: 1 | AC5: 1 | AD5: 1 | AE5: 8/17 NTP Package Received | AF5: QC turned in and start COP & Change order needed
A6: D-HAL116 | B6: Bradenton | C6: 46295 | D6: North Path | E6: 46251 | F6: Brenton Copelin | G6: MAN113039 | H6: 81 | I6: Completed on Track | J6: Received | L6: N/A | M6: Yes | N6: 52593.6 | O6: Yes | P6: Completed | Q6: 46255 | R6: Yes | S6: 46293 | T6: 46293 | U6: 46293 | V6: 4065 | W6: 4167 | X6: =SUM(V6-W6) -> -102 | Y6: =IFERROR($W6/$V6, 0) -> 1.0250923 | Z6: 46268 | AA6: 46281 | AB6: 1 | AC6: 1 | AD6: 0 | AE6: 8/17 NTP Package Received | AF6: Needs change order.
A7: D-HLX421 | B7: Bradenton | C7: 46107 | D7: GN Systems | E7: 46118 | F7: Cody | G7: MAN108652 | H7: 20 | I7: Completed on Track | J7: Received | L7: 46120 | M7: Yes | N7: 23501 | O7: Yes | P7: Completed | Q7: 46118 | R7: Yes | S7: 46171 | T7: 6/5 Failed QC | U7: 46178 | V7: 1322 | W7: 1322 | X7: =SUM(V7-W7) -> 0 | Y7: =IFERROR($W7/$V7, 0) -> 1 | Z7: 46148 | AA7: 46149 | AB7: 1 | AC7: 1 | AD7: 1 | AE7: 10/22 Permit Received. 5-29-26 sent in site tracker for QC 509' was built with BHZD-FLX-04-W. Cody to verify. 6/5 Failed Gig List Received From Tillman. | AF7: GN Systems. Need bore logs. John has been in touch
A8: D-HLX503 | B8: Bradenton | C8: 46181 | D8: North Path | E8: 46171 | F8: Brenton Copelin | H8: 85 | I8: Completed on Track | J8: Received | L8: N/A | M8: Yes | N8: 60062 | O8: Yes | P8: Completed | Q8: 46174 | R8: No | S8: Not Submitted | T8: Pending Tillman QC Form | U8: Pending Tillman QC Form | V8: 4380 | W8: 4475 | X8: =SUM(V8-W8) -> -95 | Y8: =IFERROR($W8/$V8, 0) -> 1.0216895 | Z8: 46227 | AA8: 46240 | AB8: 1 | AC8: 1 | AD8: 1 | AE8: 4/29 NTP Package Received. On hold due to community shutdown. CX start 7-13-26 again | AF8: Change order needed. Holding up billing
A9: D-HLX505 | B9: Bradenton | C9: 46191 | D9: North Path | E9: 46171 | F9: Brenton Copelin | H9: 87 | I9: Completed on Track | J9: Received | L9: N/A | M9: Yes | N9: 64040 | O9: Yes | P9: Completed | Q9: 46174 | R9: No | S9: Not Submitted | T9: Pending Tillman QC Form | U9: Pending Tillman QC Form | V9: 4888 | W9: 5016 | X9: =SUM(V9-W9) -> -128 | Y9: =IFERROR($W9/$V9, 0) -> 1.0261866 | Z9: 46237 | AA9: 46241 | AB9: 1 | AC9: 1 | AD9: 1 | AE9: 4/29 NTP Package Received. On hold due to community shutdown. CX start 7-13-26 again | AF9: Change order needed. Holding up billing
A10: FB-HLR201 | B10: Bradenton | C10: 46040 | D10: Lightspeed In-House / GN Systems | E10: 45867 | F10: Cody | G10: MAN99683 | H10: 0 | I10: Completed on Track | J10: Received | L10: N/A | M10: Yes | N10: 144972.5 | O10: Yes | P10: Completed | Q10: 45867 | R10: Yes | S10: 46190 | T10: 46192 | U10: 46192 | V10: 9840 | W10: 9806 | X10: =SUM(V10-W10) -> 34 | Y10: =IFERROR($W10/$V10, 0) -> 0.99654472 | Z10: 45884 | AA10: 46062 | AB10: 1 | AC10: 1 | AD10: 0 | AE10: 1/5 CX Construction Started. 2/5 CX Construction Complete--144F Placed Pending Splicing, 13 Ground Rods and Switches./ 2/9 695' Tracer Wire and Mule Tape. Failed Gig List Received From Tillman On 4/24. | AF10: Still needed an in house inspector to complete bore logs
A11: FB-HLX175 | B11: Bradenton | C11: 46295 | D11: Lightspeed In-House/North Path | E11: 46225 | F11: Brenton Copelin | G11: MAN112869 | H11: 0 | I11: Completed on Track | J11: Received | L11: N/A | M11: Yes | N11: 36166.65 | O11: Yes | P11: Completed | Q11: 46226 | R11: No | S11: Not Submitted | T11: Pending Tillman QC Form | U11: Pending Tillman QC Form | V11: 3036 | W11: 3056 | X11: =SUM(V11-W11) -> -20 | Y11: =IFERROR($W11/$V11, 0) -> 1.0065876 | Z11: 46239 | AA11: 46254 | AB11: 1 | AC11: 1 | AD11: 1 | AE11: 7/21 NTP Package Received | AF11: Change order needed, fiber splicing complete. needs that added to SOW
A12: FB-HOE401-V6 | B12: Bradenton | C12: 46295 | D12: Lightspeed In-House | E12: 46232 | F12: Brenton Copelin | G12: MAN112894 | H12: 0 | I12: Completed on Track | J12: Received | L12: N/A | M12: Yes | N12: 3232.9 | O12: Yes | P12: Completed | Q12: 46233 | R12: Yes | S12: 46283 | T12: 46283 | U12: 46283 | V12: 194 | W12: 200 | X12: =SUM(V12-W12) -> -6 | Y12: =IFERROR($W12/$V12, 0) -> 1.0309278 | Z12: 46251 | AA12: 46251 | AB12: 1 | AC12: 1 | AD12: 0 | AE12: 7/24 NTP Package Recived--Pending Fiber Details Splcing Document, 7/29/26 Assigned to In House | AF12: QC complete phase 1 & Phase 2. Need change order
A13: D-HPP607 | B13: Clearwater | C13: 46325 | D13: Lightspeed In-House | E13: 46143 | F13: Treyvon Tillman | G13: PPM111646 | H13: 46 | I13: Completed on Track | J13: Received | L13: 46147 | M13: Yes | N13: 71754.5 | O13: Yes | P13: Completed | Q13: 46147 | R13: No | S13: Not Submitted | T13: Pending Tillman QC Form | U13: Pending Tillman QC Form | V13: 5649 | W13: 5893 | X13: =SUM(V13-W13) -> -244 | Y13: =IFERROR($W13/$V13, 0) -> 1.0431935 | Z13: 46169 | AA13: 46211 | AB13: 0 | AC13: 0 | AD13: 0 | AE13: 5/5 Door Tag Complete : Locates Called - 5/4 Whitelined, will call locates 5/5/ - 5/1 NTP Package Received. | AF13: Passed QC. COP next week
A14: D-HPP608 | B14: Clearwater | C14: 46325 | D14: Lightspeed In-House | E14: 46161 | F14: Robert Portee | G14: PPM111675 | H14: 94 | I14: Completed on Track | J14: Received | L14: N/A | M14: Yes | N14: 94021.5 | O14: Yes | P14: Completed | Q14: 46162 | R14: No | S14: Not Submitted | T14: Pending Tillman QC Form | U14: Pending Tillman QC Form | V14: 7741 | W14: 7673 | X14: =SUM(V14-W14) -> 68 | Y14: =IFERROR($W14/$V14, 0) -> 0.99121561 | Z14: 46241 | AA14: 46283 | AB14: 0 | AC14: 0 | AD14: 0 | AE14: 5/1 NTP Package Received./Whitelined 5-19/ locates called 5-20/Will be dortagged 5-21/Pending Locates cleared, Construction Completed 9/18/2026, Path Completed, SOW incorrect
A15: D-HPP613 | B15: Clearwater | C15: 46325 | D15: APT Communications | E15: 46157 | F15: Johnnie Williams | H15: 79 | I15: Completed on Track | J15: Received | L15: 46152 | M15: Yes | N15: 100208 | O15: Yes | P15: Completed | Q15: 46149 | R15: No | S15: 46266 | T15: Pending Tillman QC Form | U15: Pending Tillman QC Form | V15: 8175 | W15: 8120 | X15: =SUM(V15-W15) -> 55 | Y15: =IFERROR($W15/$V15, 0) -> 0.99327217 | Z15: 46168 | AA15: 46211 | AB15: 0 | AC15: 0 | AD15: 0 | AE15: 5/1 NTP Package Received. | AF15: Not started
A16: D-HPP614 | B16: Clearwater | C16: 46325 | D16: Mid Florida Contractors | E16: 46161 | F16: Johnnie Williams | H16: 110 | I16: Completed on Track | J16: Received | L16: N/A | M16: Yes | N16: 101920.5 | O16: Yes | P16: Completed | Q16: 46162 | R16: No | S16: Not Submitted | T16: Pending Tillman QC Form | U16: Pending Tillman QC Form | V16: 8444 | W16: 8277 | X16: =SUM(V16-W16) -> 167 | Y16: =IFERROR($W16/$V16, 0) -> 0.98022264 | Z16: 46174 | AA16: 46231 | AB16: 0 | AC16: 0 | AD16: 0 | AE16: 5/1 NTP Package Received. | AF16: Re walk has not been set
A17: D-HPP621 | B17: Clearwater | C17: 46325 | D17: Brothers | E17: 46170 | F17: Anthony Adum | H17: 91 | I17: Completed on Track | J17: Received | L17: 46175 | M17: Yes | N17: 72668.5 | O17: Yes | P17: Completed | Q17: 46176 | R17: Yes | S17: 46275 | T17: 46287 | U17: Pending Tillman QC Form | V17: 5934 | W17: 6020 | X17: =SUM(V17-W17) -> -86 | Y17: =IFERROR($W17/$V17, 0) -> 1.0144928 | Z17: 46191 | AA17: 46204 | AB17: 0 | AC17: 0 | AD17: 0 | AE17: 5/1 NTP Package Received. | AF17: QC Passed. working on this one
A18: D-HPP625 | B18: Clearwater | C18: 46325 | D18: Brothers | E18: 46170 | F18: Treyvon Tillman | H18: 88 | I18: Completed on Track | J18: Received | L18: 46188 | M18: Yes | N18: 96607 | O18: Yes | P18: Completed | Q18: 46176 | R18: No | S18: Not Submitted | T18: Pending Tillman QC Form | U18: Pending Tillman QC Form | V18: 7623 | W18: 7341 | X18: =SUM(V18-W18) -> 282 | Y18: =IFERROR($W18/$V18, 0) -> 0.96300669 | Z18: 46195 | AA18: 46204 | AB18: 0 | AC18: 0 | AD18: 0 | AE18: 5/1 NTP Package Received. | AF18: Passed QC. COP next week
A19: D-HPP626 | B19: Clearwater | C19: 46325 | D19: Brothers | E19: 46171 | F19: Marcelo Zaldivar | H19: 75 | I19: Completed on Track | J19: Received | L19: N/A | M19: Yes | N19: 95477 | O19: Yes | P19: Completed | Q19: 46198 | R19: No | S19: Not Submitted | T19: Pending Tillman QC Form | U19: Pending Tillman QC Form | V19: 7966 | W19: 8323 | X19: =SUM(V19-W19) -> -357 | Y19: =IFERROR($W19/$V19, 0) -> 1.0448155 | Z19: 46213 | AA19: 46290 | AB19: 0 | AC19: 0 | AD19: 0 | AE19: 5/1 NTP Package Received.
A20: D-HPP627 | B20: Clearwater | C20: 46325 | D20: Brothers | E20: 46170 | F20: Marcelo Zaldivar | H20: 97 | I20: Completed on Track | J20: Received | L20: N/A | M20: Yes | N20: 94688.5 | O20: Yes | P20: Completed | Q20: 46176 | R20: Yes | S20: 46253 | T20: 46258 | U20: Pending Tillman QC Form | V20: 7856 | W20: 7519 | X20: =SUM(V20-W20) -> 337 | Y20: =IFERROR($W20/$V20, 0) -> 0.95710285 | Z20: 46190 | AA20: 46251 | AB20: 0 | AC20: 0 | AD20: 0 | AE20: 5/1 NTP Package Received. | AF20: Waiting on inspector to give final walk out footages
A21: D-HPP628 | B21: Clearwater | C21: 46325 | D21: Brothers | E21: 46171 | F21: Marcelo Zaldivar | H21: 65 | I21: Completed on Track | J21: Received | L21: N/A | M21: Yes | N21: 97700 | O21: Yes | P21: Completed | Q21: 46198 | R21: No | S21: Not Submitted | T21: Pending Tillman QC Form | U21: Pending Tillman QC Form | V21: 8047 | W21: 7881 | X21: =SUM(V21-W21) -> 166 | Y21: =IFERROR($W21/$V21, 0) -> 0.97937119 | Z21: 46212 | AA21: 46218 | AB21: 0 | AC21: 0 | AD21: 0 | AE21: 5/1 NTP Package Received. | AF21: 0
A22: D-HPP629 | B22: Clearwater | C22: 46325 | D22: Brothers | E22: 46170 | F22: Anthony Adum | H22: 51 | I22: Completed on Track | J22: Received | L22: N/A | M22: Yes | N22: 91700 | O22: Yes | P22: Completed | Q22: 46176 | R22: Yes | S22: Not Submitted | T22: 46273 | U22: Pending Tillman QC Form | V22: 7529 | W22: 7407 | X22: =SUM(V22-W22) -> 122 | Y22: =IFERROR($W22/$V22, 0) -> 0.98379599 | Z22: 46191 | AA22: 46251 | AB22: 0 | AC22: 0 | AD22: 0 | AE22: 5/1 NTP Package Received. | AF22: Bore logs sent. needs review.
A23: D-HPP633 | B23: Clearwater | C23: 46325 | D23: Power Connect | E23: 46177 | F23: Johnnie Williams | H23: 70 | I23: Completed on Track | J23: Received | L23: N/A | M23: Yes | N23: 99590 | O23: Yes | P23: Completed | Q23: 46177 | R23: No | S23: Not Submitted | T23: Pending Tillman QC Form | U23: Pending Tillman QC Form | V23: 8201 | W23: 8350 | X23: =SUM(V23-W23) -> -149 | Y23: =IFERROR($W23/$V23, 0) -> 1.0181685 | Z23: 46195 | AA23: 46234 | AB23: 0 | AC23: 0 | AD23: 0 | AE23: 5/1 NTP Package Received. | AF23: Internal QC 9/28
A24: D-HPP634 | B24: Clearwater | C24: 46325 | D24: NIA Underground | E24: 46182 | F24: Johnnie Williams | H24: 91 | I24: Completed on Track | J24: Received | L24: N/A | M24: Yes | N24: 103644.5 | O24: Yes | P24: Completed | Q24: 46183 | R24: No | S24: Not Submitted | T24: Pending Tillman QC Form | U24: Pending Tillman QC Form | V24: 8384 | W24: 8386 | X24: =SUM(V24-W24) -> -2 | Y24: =IFERROR($W24/$V24, 0) -> 1.0002385 | Z24: 46224 | AA24: 46239 | AB24: 0 | AC24: 0 | AD24: 0 | AE24: 5/11 NTP Package Received. | AF24: Internal QC 9/29
A25: D-HPP635 | B25: Clearwater | C25: 46325 | D25: NIA Underground | E25: 46182 | F25: Johnnie Williams | H25: 57 | I25: Completed on Track | J25: Received | L25: N/A | M25: Yes | N25: 106431.5 | O25: Yes | P25: Completed | Q25: 46183 | R25: No | S25: Not Submitted | T25: Pending Tillman QC Form | U25: Pending Tillman QC Form | V25: 8751 | W25: 8542 | X25: =SUM(V25-W25) -> 209 | Y25: =IFERROR($W25/$V25, 0) -> 0.97611702 | Z25: 46216 | AA25: 46246 | AB25: 0 | AC25: 0 | AD25: 0 | AE25: 5/12 NTP Package Received. | AF25: Internal QC 9/30
A26: D-HPP636 | B26: Clearwater | C26: 46325 | D26: Brothers | E26: 46182 | F26: Marcelo Zaldivar | H26: 86 | I26: Completed on Track | J26: Received | L26: N/A | M26: Yes | N26: 97386.5 | O26: Yes | P26: Completed | Q26: 46188 | R26: No | S26: Not Submitted | T26: Pending Tillman QC Form | U26: Pending Tillman QC Form | V26: 7996 | W26: 7742 | X26: =SUM(V26-W26) -> 254 | Y26: =IFERROR($W26/$V26, 0) -> 0.96823412 | Z26: 46219 | AA26: 46248 | AB26: 0 | AC26: 0 | AD26: 0 | AE26: 5/1 NTP Package Received. | AF26: 0
A27: D-HPP638 | B27: Clearwater | C27: 46325 | D27: Lightspeed In-House | E27: 47267 | F27: Treyvon Tillman | H27: 88 | I27: Completed on Track | J27: Received | L27: 46181 | M27: Yes | N27: 81059.5 | O27: Yes | P27: Completed | Q27: 46174 | R27: No | S27: Not Submitted | T27: Pending Tillman QC Form | U27: Pending Tillman QC Form | V27: 6647 | W27: 6717 | X27: =SUM(V27-W27) -> -70 | Y27: =IFERROR($W27/$V27, 0) -> 1.0105311 | Z27: 46188 | AA27: 46254 | AB27: 0 | AC27: 0 | AD27: 0 | AE27: 5/1 NTP Package Received. | AF27: Pending QC
A28: D-HPP639 | B28: Clearwater | C28: 46325 | D28: ASM Utilities | E28: 46202 | F28: Marcelo Zaldivar | H28: 88 | I28: Completed on Track | J28: Received | L28: N/A | M28: Yes | N28: 106600 | O28: Yes | P28: Completed | Q28: 46180 | R28: No | S28: Not Submitted | T28: Pending Tillman QC Form | U28: Pending Tillman QC Form | V28: 8787 | W28: 8921 | X28: =SUM(V28-W28) -> -134 | Y28: =IFERROR($W28/$V28, 0) -> 1.0152498 | Z28: 46209 | AA28: 46233 | AB28: 0 | AC28: 0 | AD28: 0 | AE28: 5/1 NTP Package Received. | AF28: Starting on the COP
A29: FB-HPP612 | B29: Clearwater | C29: 46322 | D29: Brothers | E29: 46253 | F29: Anthony Adum | H29: 0 | I29: Completed on Track | J29: Received | L29: N/A | M29: Yes | N29: 66431.7 | O29: Yes | P29: Completed | Q29: 46255 | R29: No | S29: Not Submitted | T29: Pending Tillman QC Form | U29: Pending Tillman QC Form | V29: 5251 | W29: 5190 | X29: =SUM(V29-W29) -> 61 | Y29: =IFERROR($W29/$V29, 0) -> 0.98838317 | Z29: 46280 | AA29: 46283 | AB29: 1 | AC29: 0 | AD29: 0 | AE29: 8/19 NTP Package Received--8/20 PO Received. | AF29: Phase 1 vaults are being set
A30: FB-HPP631 | B30: Clearwater | C30: 46325 | D30: Brothers | E30: 46155 | F30: Anthony Adum | G30: PPM111690 | H30: 0 | I30: Completed on Track | J30: Received | L30: 46154 | M30: Yes | N30: 65477.3 | O30: Yes | P30: Completed | Q30: 46157 | R30: No | S30: Not Submitted | T30: Pending Tillman QC Form | U30: Pending Tillman QC Form | V30: 6335 | W30: 6762 | X30: =SUM(V30-W30) -> -427 | Y30: =IFERROR($W30/$V30, 0) -> 1.0674033 | Z30: 46276 | AA30: 46297 | AB30: 1 | AC30: 1 | AD30: 1 | AE30: 7/13 NTP Package Received. 7/17 PO Received And Approved.
A31: BHCD-FPW-03-W | B31: Fort Myers | C31: 46172 | D31: North Path | E31: 46128 | F31: Joshua Wheatcroft | G31: MAN109687 | H31: 0 | I31: Completed on Track | J31: Received | L31: N/A | M31: Yes | N31: 146065.95 | O31: Yes | P31: Completed | Q31: 46087 | R31: Yes | S31: 46190 | T31: 6/24 Failed QC | U31: 6/24 Failed QC | V31: 3461 | W31: 3578 | X31: =SUM(V31-W31) -> -117 | Y31: =IFERROR($W31/$V31, 0) -> 1.0338053 | Z31: 46106 | AA31: 46136 | AB31: 1 | AC31: 0 | AD31: 0 | AE31: 3/5 Fiber Splicing Document Received. | AF31: Not started
A32: D-HDF707 | B32: Fort Myers | C32: 46081 | D32: Lightspeed In-House | E32: 46001 | F32: Joshua Wheatcroft | G32: MAN104765 | H32: 80 | I32: Completed on Track | J32: Received | L32: 46021 | M32: Yes | N32: 65843.5 | O32: Yes | P32: Completed | Q32: 45995 | R32: Yes | S32: 46190 | T32: Pending Tillman QC Form | U32: Pending Tillman QC Form | V32: 5052 | W32: 4889 | X32: =SUM(V32-W32) -> 163 | Y32: =IFERROR($W32/$V32, 0) -> 0.96773555 | Z32: 46001 | AA32: 46022 | AB32: 0 | AC32: 0 | AD32: 0 | AE32: 10/31 Permit Received With NTP Package./ | AF32: Asbuilt done, needs BOM
A33: D-HDF713 | B33: Fort Myers | C33: 46053 | D33: GN Systems | E33: 45974 | F33: Joshua Wheatcroft | G33: MAN104149 | H33: 77 | I33: Completed on Track | J33: Received | L33: 45965 | M33: Yes | N33: 90786 | O33: Yes | P33: Completed | Q33: 45965 | R33: Yes | S33: 46190 | T33: Pending Tillman QC Form | U33: Pending Tillman QC Form | V33: 8013 | W33: 7885 | X33: =SUM(V33-W33) -> 128 | Y33: =IFERROR($W33/$V33, 0) -> 0.98402596 | Z33: 45979 | AA33: 45982 | AB33: 0 | AC33: 0 | AD33: 0 | AE33: 10/29 Permit Received With NTP Package. | AF33: Pictures of DAPS needed
A34: D-HPW346 | B34: Fort Myers | C34: 46295 | D34: A1 Broadband | E34: 46245 | F34: Joshua Wheatcroft | G34: FM113017 | H34: 89 | I34: Completed on Track | J34: Received | L34: N/A | M34: Yes | N34: 93910.15 | O34: Yes | P34: Completed | Q34: 46251 | R34: No | S34: Not Submitted | T34: Pending Tillman QC Form | U34: Pending Tillman QC Form | V34: 7299 | W34: 7212 | X34: =SUM(V34-W34) -> 87 | Y34: =IFERROR($W34/$V34, 0) -> 0.98808056 | Z34: 46275 | AA34: 46297 | AB34: 0 | AC34: 0 | AD34: 0 | AE34: 7/29 NTP Package Recived
A35: D-HPW348 | B35: Fort Myers | C35: 46295 | D35: Alpha Omega | E35: 46240 | F35: Joshua Wheatcroft | G35: FM112925 | H35: 83 | I35: Completed on Track | J35: Received | L35: N/A | M35: Yes | N35: 78322 | O35: Yes | P35: Completed | Q35: 46251 | R35: No | S35: Not Submitted | T35: Pending Tillman QC Form | U35: Pending Tillman QC Form | V35: 6192 | W35: 6179 | X35: =SUM(V35-W35) -> 13 | Y35: =IFERROR($W35/$V35, 0) -> 0.99790052 | Z35: 46251 | AA35: 46286 | AB35: 0 | AC35: 0 | AD35: 0 | AE35: 7/29 NTP Package Recived 9-8-26 refreshed locates | AF35: Just completed
A36: FB-HPW331 | B36: Fort Myers | C36: 46227 | D36: Gulfstream | E36: 46213 | F36: Joshua | G36: FM112418 | H36: 0 | I36: Completed on Track | J36: Received | L36: N/A | M36: Yes | N36: 25174.45 | O36: Yes | P36: Completed | Q36: 46238 | R36: No | S36: Not Submitted | T36: Pending Tillman QC Form | U36: Pending Tillman QC Form | V36: 1797 | W36: 1781 | X36: =SUM(V36-W36) -> 16 | Y36: =IFERROR($W36/$V36, 0) -> 0.99109627 | Z36: 46252 | AA36: 46304 | AB36: 0 | AC36: 0 | AD36: 0 | AE36: 6/9 NTP Package Received. 10-9-26 path complete missing 4 HH
A37: D-HTG201 | B37: Fort Myers | C37: 46203 | D37: Lopez Underground | E37: 46171 | F37: Joshua Wheatcroft | H37: 53 | I37: Completed on Track | J37: Received | L37: N/A | M37: Yes | N37: 56455 | O37: Yes | P37: Completed | Q37: 46174 | R37: No | S37: Not Submitted | T37: Pending Tillman QC Form | U37: Pending Tillman QC Form | V37: 4814 | W37: 5133 | X37: =SUM(V37-W37) -> -319 | Y37: =IFERROR($W37/$V37, 0) -> 1.0662651 | Z37: 46184 | AA37: 46204 | AB37: 1 | AC37: 1 | AD37: 1 | AE37: 4/30 NTP Received 7-17-26 tillman approved bury the route that is on private property and close the job. | AF37: Working On asbuilt
A38: D-HTG206 | B38: Fort Myers | C38: 46171 | D38: Lopez Underground | E38: 46141 | F38: Joshua Wheatcroft | H38: 89 | I38: Completed on Track | J38: Received | L38: N/A | M38: Yes | N38: 70666 | O38: Yes | P38: Completed | Q38: 46150 | R38: Yes | S38: 46190 | T38: 6/24 Failed QC | U38: 46197 | V38: 6549 | W38: 6536 | X38: =SUM(V38-W38) -> 13 | Y38: =IFERROR($W38/$V38, 0) -> 0.99801496 | Z38: 46154 | AA38: 46163 | AB38: 1 | AC38: 1 | AD38: 1 | AE38: 4/14 NTP Received | AF38: Asbuilt complete. Pending phase 1 email
A39: D-HTG207 | B39: Fort Myers | C39: 46187 | D39: Lopez Underground | E39: 46171 | F39: Joshua Wheatcroft | H39: 76 | I39: Completed on Track | J39: Received | L39: N/A | M39: Yes | N39: 72914 | O39: Yes | P39: Completed | Q39: 46174 | R39: Yes | S39: 46190 | T39: 46213 | U39: 46213 | V39: 5649 | W39: 5777 | X39: =SUM(V39-W39) -> -128 | Y39: =IFERROR($W39/$V39, 0) -> 1.0226589 | Z39: 46177 | AA39: 46185 | AB39: 1 | AC39: 1 | AD39: 1 | AE39: 4/30 NTP Received | AF39: Started Asbuilt
A40: D-HTG208 | B40: Fort Myers | C40: 46203 | D40: Lopez Underground | E40: 46141 | F40: Joshua | H40: 74 | I40: Completed on Track | J40: Received | L40: N/A | M40: Yes | N40: 92274 | O40: Yes | P40: Completed | Q40: 46142 | R40: No | S40: Not Submitted | T40: Pending Tillman QC Form | U40: Pending Tillman QC Form | V40: 8145 | W40: 8102 | X40: =SUM(V40-W40) -> 43 | Y40: =IFERROR($W40/$V40, 0) -> 0.99472069 | Z40: 46149 | AA40: 46304 | AB40: 1 | AC40: 1 | AD40: 1 | AE40: 4/24 NTP Received 7-13-26 permit waiting on new permit
A41: D-HTG210 | B41: Fort Myers | C41: 46265 | D41: Gulfstream | E41: 46231 | F41: Joshua Wheatcroft | G41: FM112876 | H41: 77 | I41: Completed on Track | J41: Received | L41: N/A | M41: Yes | N41: 68598 | O41: Yes | P41: Completed | Q41: 46232 | R41: No | S41: Not Submitted | T41: Pending Tillman QC Form | U41: Pending Tillman QC Form | V41: 5803 | W41: 5753 | X41: =SUM(V41-W41) -> 50 | Y41: =IFERROR($W41/$V41, 0) -> 0.99138377 | Z41: 46253 | AA41: 46302 | AB41: 1 | AC41: 1 | AD41: 1 | AE41: 7/17 NTP Received. 10-6-26 Path walked out and complete.
A42: D-HTG215 | B42: Fort Myers | C42: 46264 | D42: Gulfstream | E42: 46219 | F42: Joshua | G42: FM112727 | H42: 56 | I42: Completed on Track | J42: Received | L42: N/A | M42: Yes | N42: 55008 | O42: Yes | P42: Completed | Q42: 46220 | R42: No | S42: Not Submitted | T42: Pending Tillman QC Form | U42: Pending Tillman QC Form | V42: 4625 | W42: 4596 | X42: =SUM(V42-W42) -> 29 | Y42: =IFERROR($W42/$V42, 0) -> 0.99372973 | Z42: 46231 | AA42: 46304 | AB42: 1 | AC42: 1 | AD42: 1 | AE42: 7/7 NTP Package Received.
A43: D-HTG216 | B43: Fort Myers | C43: 46295 | D43: Lopez Underground | E43: 46231 | F43: Joshua Wheatcroft | G43: FM112879 | H43: 79 | I43: Completed on Track | J43: Received | L43: N/A | M43: Yes | N43: 80274 | O43: Yes | P43: Completed | Q43: 46232 | R43: No | S43: Not Submitted | T43: Pending Tillman QC Form | U43: Pending Tillman QC Form | V43: 6786 | W43: 6598 | X43: =SUM(V43-W43) -> 188 | Y43: =IFERROR($W43/$V43, 0) -> 0.9722959 | Z43: 46241 | AA43: 46246 | AB43: 0 | AC43: 0 | AD43: 0 | AE43: 7/24 NTP Package Recived | AF43: Missing Bore logs Lopez
A44: D-HTG217 | B44: Fort Myers | C44: 46295 | D44: Lopez Underground | E44: 46231 | F44: Joshua | G44: FM112881 | H44: 77 | I44: Completed on Track | J44: Received | L44: N/A | M44: Yes | N44: 76557.5 | O44: Yes | P44: Completed | Q44: 46232 | R44: No | S44: Not Submitted | T44: Pending Tillman QC Form | U44: Pending Tillman QC Form | V44: 6200 | W44: 6081 | X44: =SUM(V44-W44) -> 119 | Y44: =IFERROR($W44/$V44, 0) -> 0.98080645 | Z44: 46245 | AA44: 46304 | AB44: 0 | AC44: 0 | AD44: 0 | AE44: 7/24 NTP Package Recived
A45: D-HTG218 | B45: Fort Myers | C45: 46233 | D45: Gulfstream | E45: 46219 | F45: Joshua Wheatcroft | G45: FM112751 | H45: 48 | I45: Completed on Track | J45: Received | L45: N/A | M45: Yes | N45: 50669 | O45: Yes | P45: Completed | Q45: 46220 | R45: No | S45: Not Submitted | T45: Pending Tillman QC Form | U45: Pending Tillman QC Form | V45: 3850 | W45: 3834 | X45: =SUM(V45-W45) -> 16 | Y45: =IFERROR($W45/$V45, 0) -> 0.99584416 | Z45: 46226 | AA45: 46262 | AB45: 0 | AC45: 0 | AD45: 0 | AE45: 5/29 NTP Received | AF45: Waiting on Bore logs from Lopez
A46: D-HTG225 | B46: Fort Myers | C46: 46203 | D46: Lopez Underground | E46: 46156 | F46: Joshua Wheatcroft | H46: 69 | I46: Completed on Track | J46: Received | L46: N/A | M46: Yes | N46: 72896 | O46: Yes | P46: Completed | Q46: 46157 | R46: No | S46: Not Submitted | T46: Pending Tillman QC Form | U46: Pending Tillman QC Form | V46: 6189 | W46: 6050 | X46: =SUM(V46-W46) -> 139 | Y46: =IFERROR($W46/$V46, 0) -> 0.9775408 | Z46: 46169 | AA46: 46219 | AB46: 1 | AC46: 1 | AD46: 1 | AE46: 5/8 NTP Package Received | AF46: Not Started
A47: D-HTG228 | B47: Fort Myers | C47: 46203 | D47: Lopez Underground | E47: 46169 | F47: Joshua Wheatcroft | H47: 60 | I47: Completed on Track | J47: Received | L47: N/A | M47: Yes | N47: 70151.5 | O47: Yes | P47: Completed | Q47: 46170 | R47: No | S47: Not Submitted | T47: Pending Tillman QC Form | U47: Pending Tillman QC Form | V47: 5673 | W47: 5183 | X47: =SUM(V47-W47) -> 490 | Y47: =IFERROR($W47/$V47, 0) -> 0.91362595 | Z47: 46197 | AA47: 46219 | AB47: 1 | AC47: 1 | AD47: 1 | AE47: 5/8 NTP Package Received | AF47: Missing Bore logs Lopez
A48: D-HTG229 | B48: Fort Myers | C48: 46203 | D48: Lopez Underground | E48: 46169 | F48: Joshua Wheatcroft | H48: 70 | I48: Completed on Track | J48: Received | L48: N/A | M48: Yes | N48: 65362 | O48: Yes | P48: Completed | Q48: 46170 | R48: No | S48: Not Submitted | T48: Pending Tillman QC Form | U48: Pending Tillman QC Form | V48: 5460 | W48: 5325 | X48: =SUM(V48-W48) -> 135 | Y48: =IFERROR($W48/$V48, 0) -> 0.97527473 | Z48: 46189 | AA48: 46262 | AB48: 1 | AC48: 1 | AD48: 1 | AE48: 5/8 NTP Package Received | AF48: Pending Bore logs from Lopez & asbuilt
A49: D-HTG230 | B49: Fort Myers | C49: 46233 | D49: Restoring Pro | E49: 46219 | F49: Joshua | G49: FM112752 | H49: 79 | I49: Completed on Track | J49: Received | L49: N/A | M49: Yes | N49: 89293.95 | O49: Yes | P49: Completed | Q49: 46220 | R49: No | S49: Not Submitted | T49: Pending Tillman QC Form | U49: Pending Tillman QC Form | V49: 7494 | W49: 7415 | X49: =SUM(V49-W49) -> 79 | Y49: =IFERROR($W49/$V49, 0) -> 0.98945823 | Z49: 46231 | AA49: 46304 | AB49: 1 | AC49: 1 | AD49: 1 | AE49: 4/14 NTP Received
A50: D-HTG233 | B50: Fort Myers | C50: 46203 | D50: Lopez Underground | E50: 46156 | F50: Joshua Wheatcroft | H50: 71 | I50: Completed on Track | J50: Received | L50: N/A | M50: Yes | N50: 91537.75 | O50: Yes | P50: Completed | Q50: 46157 | R50: No | S50: Not Submitted | T50: Pending Tillman QC Form | U50: Pending Tillman QC Form | V50: 7255 | W50: 7248 | X50: =SUM(V50-W50) -> 7 | Y50: =IFERROR($W50/$V50, 0) -> 0.99903515 | Z50: 46174 | AA50: 46262 | AB50: 1 | AC50: 1 | AD50: 1 | AE50: 4/14 NTP Received | AF50: Walked out. Need to update asbuilt
A51: D-HTG235 | B51: Fort Myers | C51: 46203 | D51: Lopez Underground | E51: 46171 | F51: Joshua Wheatcroft | H51: 71 | I51: Completed on Track | J51: Received | L51: N/A | M51: Yes | N51: 68762 | O51: Yes | P51: Completed | Q51: 46174 | R51: No | S51: Not Submitted | T51: Pending Tillman QC Form | U51: Pending Tillman QC Form | V51: 5624 | W51: 5577 | X51: =SUM(V51-W51) -> 47 | Y51: =IFERROR($W51/$V51, 0) -> 0.99164296 | Z51: 46190 | AA51: 46213 | AB51: 1 | AC51: 1 | AD51: 1 | AE51: 4/14 NTP Received | AF51: Missing Bore logs Lopez
A52: D-HTG237 | B52: Fort Myers | C52: 46195 | D52: Lopez Underground | E52: 46171 | F52: Joshua Wheatcroft | H52: 56 | I52: Completed on Track | J52: Received | L52: N/A | M52: Yes | N52: 55504 | O52: Yes | P52: Completed | Q52: 46174 | R52: No | S52: Not Submitted | T52: Pending Tillman QC Form | U52: Pending Tillman QC Form | V52: 4652 | W52: 4625 | X52: =SUM(V52-W52) -> 27 | Y52: =IFERROR($W52/$V52, 0) -> 0.99419604 | Z52: 46189 | AA52: 46196 | AB52: 1 | AC52: 1 | AD52: 1 | AE52: 5/8 NTP Package Received | AF52: Not Started
A53: D-HTG238 | B53: Fort Myers | C53: 46203 | D53: Lopez Underground | E53: 46171 | F53: Joshua Wheatcroft | H53: 74 | I53: Completed on Track | J53: Received | L53: N/A | M53: Yes | N53: 70534.5 | O53: Yes | P53: Completed | Q53: 46174 | R53: No | S53: Not Submitted | T53: Pending Tillman QC Form | U53: Pending Tillman QC Form | V53: 5756 | W53: 5626 | X53: =SUM(V53-W53) -> 130 | Y53: =IFERROR($W53/$V53, 0) -> 0.97741487 | Z53: 46191 | AA53: 46262 | AB53: 1 | AC53: 1 | AD53: 1 | AE53: 5/8 NTP Package Received | AF53: Pending asbuilt
A54: D-HTG239 | B54: Fort Myers | C54: 46187 | D54: Lopez Underground | E54: 46171 | F54: Joshua Wheatcroft | H54: 85 | I54: Completed on Track | J54: Received | L54: N/A | M54: Yes | N54: 64590 | O54: Yes | P54: Completed | Q54: 46174 | R54: Yes | S54: 46190 | T54: Pending Tillman QC Form | U54: Pending Tillman QC Form | V54: 5218 | W54: 5194 | X54: =SUM(V54-W54) -> 24 | Y54: =IFERROR($W54/$V54, 0) -> 0.99540054 | Z54: 46177 | AA54: 46185 | AB54: 1 | AC54: 1 | AD54: 1 | AE54: 4/30 NTP Received | AF54: Missing Bore logs Lopez
A55: D-HTG305 | B55: Fort Myers | C55: 46203 | D55: Lightspeed In-House | E55: 46251 | F55: Joshua Wheatcroft | G55: FM113030 | H55: 56 | I55: Completed on Track | J55: Received | L55: N/A | M55: Yes | N55: 50042 | O55: Yes | P55: Completed | Q55: 46255 | R55: No | S55: Not Submitted | T55: Pending Tillman QC Form | U55: Pending Tillman QC Form | V55: 4159 | W55: 4159 | X55: =SUM(V55-W55) -> 0 | Y55: =IFERROR($W55/$V55, 0) -> 1 | Z55: 46262 | AA55: 46282 | AB55: 1 | AC55: 1 | AD55: 1 | AE55: 4/30 NTP Received. | AF55: just completed
A56: D-HTG241 | B56: Fort Myers | C56: 46195 | D56: Lightspeed In-House | E56: 46161 | F56: Joshua Wheatcroft | H56: 28 | I56: Completed on Track | J56: Received | L56: N/A | M56: Yes | N56: 27694 | O56: Yes | P56: Completed | Q56: 46162 | R56: No | S56: Not Submitted | T56: Pending Tillman QC Form | U56: Pending Tillman QC Form | V56: 2238 | W56: 2269 | X56: =SUM(V56-W56) -> -31 | Y56: =IFERROR($W56/$V56, 0) -> 1.0138517 | Z56: 46181 | AA56: 46195 | AB56: 1 | AC56: 1 | AD56: 1 | AE56: 5/8 NTP Package Received | AF56: Not Started
A57: FB-HTG204 | B57: Fort Myers | C57: 46209 | D57: Alpha Omega | E57: 46183 | F57: Joshua Wheatcroft | H57: 0 | I57: Completed on Track | J57: Received | L57: N/A | M57: Yes | N57: 35456.55 | O57: Yes | P57: Completed | Q57: 46185 | R57: No | S57: Not Submitted | T57: Pending Tillman QC Form | U57: Pending Tillman QC Form | V57: 2635 | W57: 2631 | X57: =SUM(V57-W57) -> 4 | Y57: =IFERROR($W57/$V57, 0) -> 0.99848197 | Z57: 46198 | AA57: 46224 | AB57: 0 | AC57: 0 | AD57: 0 | AE57: 5/22 NTP Package Received--Pending Fiber Details Splicing Document | AF57: Not Started
A58: FB-HTG238 | B58: Fort Myers | C58: 46233 | D58: Lopez Underground | E58: 46213 | F58: Joshua Wheatcroft | G58: FM112420 | H58: 0 | I58: Completed on Track | J58: Received | L58: N/A | M58: Yes | N58: 72557.35 | O58: Yes | P58: Completed | Q58: 46213 | R58: No | S58: Not Submitted | T58: Pending Tillman QC Form | U58: Pending Tillman QC Form | V58: 5666 | W58: 5757 | X58: =SUM(V58-W58) -> -91 | Y58: =IFERROR($W58/$V58, 0) -> 1.0160607 | Z58: 46230 | AA58: 46281 | AB58: 0 | AC58: 0 | AD58: 0 | AE58: 6/15 NTP Package Received | AF58: Just completed. Need to pull fiber
A59: FB-HTG279 | B59: Fort Myers | C59: 46295 | D59: Lightspeed In-House | E59: 46231 | F59: Joshua Wheatcroft | G59: FM112884 | H59: 0 | I59: Completed on Track | J59: Received | L59: N/A | M59: Yes | N59: 17689.15 | O59: Yes | P59: Completed | Q59: 46232 | R59: No | S59: Not Submitted | T59: Pending Tillman QC Form | U59: Pending Tillman QC Form | V59: 949 | W59: 952 | X59: =SUM(V59-W59) -> -3 | Y59: =IFERROR($W59/$V59, 0) -> 1.0031612 | Z59: 46253 | AA59: 46273 | AB59: 0 | AC59: 0 | AD59: 0 | AE59: 7/24 NTP Package Recived | AF59: Pending Phase 2. pulling fiber today
A60: FB-HTG289 | B60: Fort Myers | C60: 46229 | D60: HAS Global | E60: 46184 | F60: Joshua Wheatcroft | H60: 0 | I60: Completed on Track | J60: Received | L60: N/A | M60: Yes | N60: 31327.7 | O60: Yes | P60: Completed | Q60: 46189 | R60: No | S60: Not Submitted | T60: Pending Tillman QC Form | U60: Pending Tillman QC Form | V60: 2342 | W60: 2421 | X60: =SUM(V60-W60) -> -79 | Y60: =IFERROR($W60/$V60, 0) -> 1.0337319 | Z60: 46212 | AA60: 46225 | AB60: 0 | AC60: 0 | AD60: 0 | AE60: 6/11 NTP Package Received. | AF60: Not Started
A61: FB-HTG290 | B61: Fort Myers | C61: 46221 | D61: HAS Global | E61: 46184 | F61: Joshua Wheatcroft | H61: 0 | I61: Completed on Track | J61: Received | L61: N/A | M61: Yes | N61: 27837.25 | O61: Yes | P61: Completed | Q61: 46189 | R61: No | S61: Not Submitted | T61: Pending Tillman QC Form | U61: Pending Tillman QC Form | V61: 2367 | W61: 2367 | X61: =SUM(V61-W61) -> 0 | Y61: =IFERROR($W61/$V61, 0) -> 1 | Z61: 46198 | AA61: 46211 | AB61: 0 | AC61: 0 | AD61: 0 | AE61: 6/1 NTP Package Received. 8-6-26 tillman okd bill for tchr47 x 6 for the trip charge becuase they already had someone splicing it. | AF61: Not Started
A62: FB-HTG292 | B62: Fort Myers | C62: 46234 | D62: Gulfstream | E62: 46212 | F62: Joshua Wheatcroft | G62: FM112413 | H62: 0 | I62: Completed on Track | J62: Received | L62: N/A | M62: Yes | N62: 21849.3 | O62: Yes | P62: Completed | Q62: 46218 | R62: No | S62: Not Submitted | T62: Pending Tillman QC Form | U62: Pending Tillman QC Form | V62: 1618 | W62: 1646 | X62: =SUM(V62-W62) -> -28 | Y62: =IFERROR($W62/$V62, 0) -> 1.0173053 | Z62: 46224 | AA62: 46239 | AB62: 0 | AC62: 0 | AD62: 0 | AE62: 7/6 NTP Packafe Received | AF62: Not Started
A63: Colonial Pointe | B63: Fort Myers | C63: 46221 | D63: APT Communications | E63: 46196 | F63: Joshua Wheatcroft | G63: FM112152 | H63: 72 | I63: Completed on Track | J63: Not Required | L63: N/A | M63: Yes | N63: 60744.4 | O63: Yes | P63: Completed | Q63: 46197 | R63: No | S63: Not Submitted | T63: Pending Tillman QC Form | U63: Pending Tillman QC Form | V63: 5950 | W63: 5332 | X63: =SUM(V63-W63) -> 618 | Y63: =IFERROR($W63/$V63, 0) -> 0.89613445 | Z63: 46216 | AA63: 46227 | AB63: 0 | AC63: 0 | AD63: 0 | AE63: 6/5 NTP Package Received. | AF63: Not started
A64: BHC-FSW-04-E | B64: Kissimmee | C64: 46326 | D64: BICOM | E64: 46247 | F64: Miguel | H64: 0 | I64: Completed on Track | J64: Received | L64: 46251 | M64: Yes | N64: 68022.75 | O64: Yes | P64: Completed | Q64: 46251 | R64: No | S64: Not Submitted | T64: Pending Tillman QC Form | U64: Pending Tillman QC Form | V64: 4564 | W64: 4419 | X64: =SUM(V64-W64) -> 145 | Y64: =IFERROR($W64/$V64, 0) -> 0.96822962 | Z64: 46260 | AA64: 46301 | AB64: 0 | AC64: 0 | AD64: 0 | AE64: 8/4 PO Received/.Locates called 8/17/Locates not clear (Sewer, Water) 8-24/CX started 8/25 Drill broke down/ Cx continuing 8-26/crossing US1 ON HOLD, DOT doing work.
A65: FB-HSW419 | B65: Kissimmee | C65: 46318 | D65: BICOM | E65: 46266 | F65: Miguel | H65: 0 | I65: Completed on Track | J65: Received | L65: N/A | M65: Yes | N65: 9232.4 | O65: Yes | P65: Completed | Q65: 46268 | R65: No | S65: Not Submitted | T65: Pending Tillman QC Form | U65: Pending Tillman QC Form | V65: 7261 | W65: 7434 | X65: =SUM(V65-W65) -> -173 | Y65: =IFERROR($W65/$V65, 0) -> 1.0238259 | Z65: 46266 | AA65: 46301 | AB65: 0 | AC65: 0 | AD65: 0 | AE65: 6/10 NTP Package Received With Permit. Partial Build with BHC-FSW-04-E
A66: D-HBR252 | B66: Miami | C66: 46171 | D66: Yosep AER | E66: 46029 | F66: Efrian | H66: 53 | I66: Completed on Track | J66: Received | L66: 46029 | M66: Yes | N66: 51528.05 | O66: Yes | P66: Completed | Q66: 46024 | R66: Yes | S66: 46192 | T66: 46199 | U66: 46220 | V66: 4005 | W66: 4047 | X66: =SUM(V66-W66) -> -42 | Y66: =IFERROR($W66/$V66, 0) -> 1.0104869 | Z66: 46112 | AA66: 46175 | AB66: 1 | AC66: 1 | AD66: 1 | AE66: 12/24 NTP Package Received. Assigned to Yosep 1/7/26 | AF66: COP is ready
A67: D-HBR256 | B67: Miami | C67: 46326 | D67: Yosep AER | E67: 46029 | F67: Efrian | H67: 73 | I67: Completed on Track | J67: Received | L67: 46092 | M67: Yes | N67: 99925.7 | O67: Yes | P67: Completed | Q67: 46182 | R67: Yes | S67: 46212 | T67: Pending Tillman QC Form | U67: Pending Tillman QC Form | V67: 7660 | W67: 7703 | X67: =SUM(V67-W67) -> -43 | Y67: =IFERROR($W67/$V67, 0) -> 1.0056136 | Z67: 46184 | AA67: 46209 | AB67: 1 | AC67: 1 | AD67: 1 | AE67: 12/24 NTP Package Received. Assigned to Yosep 1/7/26 | AF67: COP is ready
A68: D-HBR257 | B68: Miami | C68: 46387 | D68: Yosep AER | E68: 46029 | F68: Jose | H68: 87 | I68: Completed on Track | J68: Received | L68: 46198 | M68: Yes | N68: 108458.4 | O68: Yes | P68: Completed | Q68: 46190 | R68: Yes | S68: 46261 | T68: Pending Tillman QC Form | U68: Pending Tillman QC Form | V68: 8596 | W68: 8403 | X68: =SUM(V68-W68) -> 193 | Y68: =IFERROR($W68/$V68, 0) -> 0.9775477 | Z68: 46203 | AA68: 46232 | AB68: 1 | AC68: 1 | AD68: 1 | AE68: 12/24 NTP Package Received. Assigned to Yosep 1/7/26 | AF68: Not Started
A69: D-HBR258 | B69: Miami | C69: 46326 | D69: Yosep AER | E69: 46029 | F69: Jose | H69: 70 | I69: Completed on Track | J69: Received | L69: N/A | M69: Yes | N69: 70105.25 | O69: Yes | P69: Completed | Q69: 46213 | R69: Yes | S69: Not Submitted | T69: Pending Tillman QC Form | U69: Pending Tillman QC Form | V69: 5648 | W69: 5650 | X69: =SUM(V69-W69) -> -2 | Y69: =IFERROR($W69/$V69, 0) -> 1.0003541 | Z69: 46226 | AA69: 46262 | AB69: 1 | AC69: 1 | AD69: 1 | AE69: 12/24 NTP Package Received. Assigned to Yosep 1/7/26 | AF69: Not Started
A70: D-HBR259 | B70: Miami | C70: 46387 | D70: Yosep AER | E70: 46029 | F70: Jose | H70: 77 | I70: Completed on Track | J70: Received | L70: N/A | M70: Yes | N70: 78047.35 | O70: Yes | P70: Completed | Q70: 46241 | R70: Yes | S70: 46296 | T70: Failed QC 10/5/2026 | U70: Pending Tillman QC Form | V70: 6238 | W70: 6300 | X70: =SUM(V70-W70) -> -62 | Y70: =IFERROR($W70/$V70, 0) -> 1.0099391 | Z70: 46248 | AA70: 46295 | AB70: 1 | AC70: 1 | AD70: 1 | AE70: 12/24 NTP Package Received. Assigned to Yosep 1/7/26
A71: D-HBR260 | B71: Miami | C71: 46387 | D71: Yosep AER | E71: 46029 | F71: Jose | H71: 52 | I71: Completed on Track | J71: Received | L71: N/A | M71: Yes | N71: 91411.65 | O71: Yes | P71: Completed | Q71: 46260 | R71: Yes | S71: 46296 | T71: Failed QC 10/5/2026 | U71: Pending Tillman QC Form | V71: 5926 | W71: 5982 | X71: =SUM(V71-W71) -> -56 | Y71: =IFERROR($W71/$V71, 0) -> 1.0094499 | Z71: 46262 | AA71: 46275 | AB71: 0 | AC71: 0 | AD71: 0 | AE71: 12/24 NTP Package Received. | AF71: Not started
A72: FB-HBR252 | B72: Miami | C72: 46173 | D72: Yosep AER | E72: 46029 | F72: Jose | H72: 0 | I72: Completed on Track | J72: Received | L72: N/A | M72: Yes | N72: 50239.7 | O72: Yes | P72: Completed | Q72: 46024 | R72: Yes | S72: 46283 | T72: Failed QC 9/25/2026 | U72: 46288 | V72: 3682 | W72: 3730 | X72: =SUM(V72-W72) -> -48 | Y72: =IFERROR($W72/$V72, 0) -> 1.0130364 | Z72: 46155 | AA72: 46247 | AB72: 0.5 | AC72: 0.5 | AD72: 0 | AE72: 12/24 NTP Package Received. 5/5 PO Received. Phase 1 Failed QC Report Uploaded Into SiteTracker. | AF72: QC failed
A73: D-HPP303 | B73: Pinellas | C73: 46262 | D73: R&F Underground Construction Inc | E73: 46171 | F73: Joshua Pacheco | H73: 35 | I73: Completed on Track | J73: Received | L73: 46183 | M73: Yes | N73: 98498 | O73: Yes | P73: Completed | Q73: 46183 | R73: Yes | S73: 46290 | T73: 46302 | U73: 46302 | V73: 7699 | W73: 7300 | X73: =SUM(V73-W73) -> 399 | Y73: =IFERROR($W73/$V73, 0) -> 0.94817509 | Z73: 46195 | AA73: 46262 | AB73: 1 | AC73: 1 | AD73: 1 | AE73: 5/29 NTP Package Received--PO Received 6/1 | AF73: Actualized. Will submit 10/2
A74: D-HPP305 | B74: Pinellas | C74: 46262 | D74: HDD Underground / R&F Underground Construction Inc | E74: 46178 | F74: Matthew Nunes | H74: 87 | I74: Completed on Track | J74: Received | L74: 46178 | M74: Yes | N74: 77365.5 | O74: Yes | P74: Completed | Q74: 46178 | R74: Yes | S74: 46290 | T74: 46302 | U74: 46302 | V74: 6321 | W74: 6271 | X74: =SUM(V74-W74) -> 50 | Y74: =IFERROR($W74/$V74, 0) -> 0.99208986 | Z74: 46191 | AA74: 46238 | AB74: 1 | AC74: 1 | AD74: 1 | AE74: 6/24 Job reassgned to R&F after HDD was removed from the project -- 6/4 NTP Package Received | AF74: Actualized. Will submit 10/2
A75: D-HPP310 | B75: Pinellas | C75: 46262 | D75: Legant Livings | E75: 46181 | F75: Joshua Pacheco | H75: 58 | I75: Completed on Track | J75: Received | L75: 46181 | M75: Yes | N75: 78994.5 | O75: Yes | P75: Completed | Q75: 46178 | R75: Yes | S75: 46290 | T75: 46302 | U75: Pending Tillman QC Form | V75: 6258 | W75: 5944 | X75: =SUM(V75-W75) -> 314 | Y75: =IFERROR($W75/$V75, 0) -> 0.94982422 | Z75: 46195 | AA75: 46226 | AB75: 1 | AC75: 0 | AD75: 0 | AE75: 5/29 NTP Package Received--PO Received 6/1 | AF75: Actualized. Will submit 10/2
A76: D-HPP311 | B76: Pinellas | C76: 46262 | D76: Legant Livings | E76: 46181 | F76: Joshua Pacheco | H76: 85 | I76: Completed on Track | J76: Received | L76: 46181 | M76: Yes | N76: 62709 | O76: Yes | P76: Completed | Q76: 46178 | R76: Yes | S76: 46290 | T76: Failed QC 10/6/2026 | U76: Pending Tillman QC Form | V76: 5055 | W76: 5140 | X76: =SUM(V76-W76) -> -85 | Y76: =IFERROR($W76/$V76, 0) -> 1.016815 | Z76: 46188 | AA76: 46254 | AB76: 1 | AC76: 0 | AD76: 0 | AE76: 5/29 NTP Package Received--PO Received 6/1 | AF76: Actualized. Will submit 10/2
A77: D-HPP314 | B77: Pinellas | C77: 46262 | D77: Power Connect | E77: 46197 | F77: Matthew Nunes | G77: MAN112114 | H77: 69 | I77: Completed on Track | J77: Received | L77: 46198 | M77: Yes | N77: 99986.2 | O77: Yes | P77: Completed | Q77: 46198 | R77: Yes | S77: 46290 | T77: Failed QC 10/5/2026 | U77: Pending Tillman QC Form | V77: 8137 | W77: 8054 | X77: =SUM(V77-W77) -> 83 | Y77: =IFERROR($W77/$V77, 0) -> 0.98979968 | Z77: 46237 | AA77: 46246 | AB77: 0 | AC77: 0 | AD77: 0 | AE77: 6/18 NTP Package Received...6-29-26 permit called in | AF77: Actualized. Will submit 10/2
A78: D-HPP854 | B78: Pinellas | C78: 46322 | D78: Brothers | E78: 46261 | F78: Anthony Adum | H78: 90 | I78: Completed on Track | J78: Received | L78: 46267 | M78: Yes | N78: 78625.9 | O78: Yes | P78: Completed | Q78: 46286 | R78: No | S78: Not Submitted | T78: Pending Tillman QC Form | U78: Pending Tillman QC Form | V78: 6218 | W78: 5826 | X78: =SUM(V78-W78) -> 392 | Y78: =IFERROR($W78/$V78, 0) -> 0.93695722 | Z78: 46282 | AA78: 46304 | AB78: 0 | AC78: 0 | AD78: 0 | AE78: 8/24 NTP Package and PO Received.
A79: D-HPP858 | B79: Pinellas | C79: 46322 | D79: Brothers | E79: 46261 | F79: Anthony Adum | H79: 68 | I79: Completed on Track | J79: Received | L79: 46267 | M79: Yes | N79: 73595.5 | O79: Yes | P79: Completed | Q79: 46267 | R79: No | S79: Not Submitted | T79: Pending Tillman QC Form | U79: Pending Tillman QC Form | V79: 5646 | W79: 5626 | X79: =SUM(V79-W79) -> 20 | Y79: =IFERROR($W79/$V79, 0) -> 0.99645767 | Z79: 46286 | AA79: 46293 | AB79: 0 | AC79: 0 | AD79: 0 | AE79: 8/24 NTP Package and PO Received.
A80: FB-HPP314 | B80: Pinellas | C80: 46262 | D80: Power Connect | E80: 46181 | F80: Joshua Pacheco | H80: 0 | I80: Completed on Track | J80: Received | L80: 46181 | M80: Yes | N80: 419 | O80: Yes | P80: Completed | Q80: 46178 | R80: Yes | S80: 46290 | T80: 46301 | U80: 46301 | V80: 72 | W80: 58 | X80: =SUM(V80-W80) -> 14 | Y80: =IFERROR($W80/$V80, 0) -> 0.80555556 | Z80: 46239 | AA80: 46239 | AB80: 1 | AC80: 0 | AD80: 0 | AE80: 5/29 NTP Package Received--PO Received 6/1 | AF80: Actualized. Will submit 10/2
A81: FB-HPP375 | B81: Pinellas | C81: 46295 | D81: Power Connect | E81: 46286 | F81: Johnnie Williams | H81: 0 | I81: Completed on Track | J81: Received | L81: N/A | M81: Yes | N81: 24396.5 | O81: Yes | P81: Completed | Q81: 46286 | R81: No | S81: Not Submitted | T81: Pending Tillman QC Form | U81: Pending Tillman QC Form | V81: 2286 | W81: 1957 | X81: =SUM(V81-W81) -> 329 | Y81: =IFERROR($W81/$V81, 0) -> 0.85608049 | Z81: 46289 | AA81: 46293 | AB81: 0 | AC81: 0 | AD81: 0 | AE81: 9/18 NTP Package and PO Received.
A82: FB-HPP879 | B82: Pinellas | C82: 46322 | D82: Brothers | E82: 46261 | F82: Anthony Adum | H82: 0 | I82: Completed on Track | J82: Received | L82: N/A | M82: Yes | N82: 73440.1 | O82: Yes | P82: Completed | Q82: 46272 | R82: No | S82: Not Submitted | T82: Pending Tillman QC Form | U82: Pending Tillman QC Form | V82: 5871 | W82: 5903 | X82: =SUM(V82-W82) -> -32 | Y82: =IFERROR($W82/$V82, 0) -> 1.0054505 | Z82: 46293 | AA82: 46296 | AB82: 0 | AC82: 0 | AD82: 0 | AE82: 8/26 NTP Package and PO Received.
A83: D-HLC506 | B83: Pinellas | C83: 46290 | D83: Brothers | E83: 46223 | F83: Anthony Adum | H83: 83 | I83: Completed on Track | J83: Received | L83: 46232 | M83: Yes | N83: 63582 | O83: Yes | P83: Completed | Q83: 46232 | R83: No | S83: Not Submitted | T83: Pending Tillman QC Form | U83: 46302 | V83: 5259 | W83: 5241 | X83: =SUM(V83-W83) -> 18 | Y83: =IFERROR($W83/$V83, 0) -> 0.9965773 | Z83: 46258 | AA83: 46267 | AB83: 1 | AC83: 1 | AD83: 1 | AE83: 7/20 NTP and PO Received. | AF83: QC passed today. Working on this one
A84: D-HLC507 | B84: Pinellas | C84: 46290 | D84: ASM Utilities | E84: 46223 | F84: Danny Combs | H84: 63 | I84: Completed -Missed TSD | J84: Received | L84: 46224 | M84: Yes | N84: 78078 | O84: Yes | P84: Completed | Q84: 46230 | R84: No | S84: Not Submitted | T84: Pending Tillman QC Form | U84: Pending Tillman QC Form | V84: 6335 | W84: 6762 | X84: =SUM(V84-W84) -> -427 | Y84: =IFERROR($W84/$V84, 0) -> 1.0674033 | Z84: 46276 | AA84: 46297 | AB84: 1 | AC84: 1 | AD84: 0 | AE84: 7/13 NTP Package Received. 7/17 PO Received And Approved.
A85: D-HLC511 | B85: Pinellas | C85: 46290 | D85: Lightspeed In-House | E85: 46223 | F85: Treyvon Tillman | H85: 93 | I85: Completed on Track | J85: Received | L85: 46224 | M85: Yes | N85: 72479.5 | O85: Yes | P85: Completed | Q85: 46227 | R85: No | S85: Not Submitted | T85: Pending Tillman QC Form | U85: Pending Tillman QC Form | V85: 5861 | W85: 5935 | X85: =SUM(V85-W85) -> -74 | Y85: =IFERROR($W85/$V85, 0) -> 1.0126258 | Z85: 46258 | AA85: 46293 | AB85: 1 | AC85: 1 | AD85: 1 | AE85: 7/13 NTP Package Received. 7/17 PO Received And Approved.
A86: D-HLC512 | B86: Pinellas | C86: 46290 | D86: Brothers | E86: 46223 | F86: Anthony Adum | G86: PPM113028 | H86: 67 | I86: Completed on Track | J86: Received | L86: 46226 | M86: Yes | N86: 86106.8 | O86: Yes | P86: Completed | Q86: 46226 | R86: No | S86: Not Submitted | T86: Pending Tillman QC Form | U86: Pending Tillman QC Form | V86: 7115 | W86: 7040 | X86: =SUM(V86-W86) -> 75 | Y86: =IFERROR($W86/$V86, 0) -> 0.98945889 | Z86: 46247 | AA86: 46290 | AB86: 1 | AC86: 1 | AD86: 1 | AE86: 7/14 NTP Package Received
A87: D-HLC513 | B87: Pinellas | C87: 46290 | D87: Lightspeed In-House | E87: 46219 | F87: Matthew Nunes | G87: PPM112719 | H87: 91 | I87: Completed on Track | J87: Received | L87: N/A | M87: Yes | N87: 79458 | O87: Yes | P87: Completed | Q87: 46220 | R87: No | S87: Not Submitted | T87: Pending Tillman QC Form | U87: Pending Tillman QC Form | V87: 6519 | W87: 6118 | X87: =SUM(V87-W87) -> 401 | Y87: =IFERROR($W87/$V87, 0) -> 0.9384875 | Z87: 46247 | AA87: 46273 | AB87: 0 | AC87: 0 | AD87: 0 | AE87: 7/13 NTP Package Received. 7/17 PO Received And Approved., Actual VERIFED FOOTAGE wheeled out 6118, SOW incorrect
A88: D-HLC517 | B88: Pinellas | C88: 46290 | D88: ASM Utilities | E88: 46219 | F88: Matthew Nunes | G88: PPM112721 | H88: 83 | I88: Completed on Track | J88: Received | L88: 46272 | M88: Yes | N88: 79947 | O88: Yes | P88: Completed | Q88: 46230 | R88: No | S88: Not Submitted | T88: Pending Tillman QC Form | U88: Pending Tillman QC Form | V88: 6058 | W88: 6169 | X88: =SUM(V88-W88) -> -111 | Y88: =IFERROR($W88/$V88, 0) -> 1.0183229 | Z88: 46251 | AA88: 46290 | AB88: 1 | AC88: 1 | AD88: 1 | AE88: 7/14 NTP Package Received
A89: D-HLC518 | B89: Pinellas | C89: 46290 | D89: ASM Utilities | E89: 46219 | F89: Matthew Nunes | G89: PPM112722 | H89: 93 | I89: Completed on Track | J89: Received | L89: N/A | M89: Yes | N89: 74446.5 | O89: Yes | P89: Completed | Q89: 46230 | R89: No | S89: Not Submitted | T89: Pending Tillman QC Form | U89: Pending Tillman QC Form | V89: 5775 | W89: 5444 | X89: =SUM(V89-W89) -> 331 | Y89: =IFERROR($W89/$V89, 0) -> 0.94268398 | Z89: 46245 | AA89: 46296 | AB89: 1 | AC89: 1 | AD89: 1 | AE89: 7/14 NTP Package Received
A90: D-HLC519 | B90: Pinellas | C90: 46290 | D90: Brothers | E90: 46245 | F90: Anthony Adum | G90: PPM113024 | H90: 44 | I90: Completed on Track | J90: Received | L90: 46251 | M90: Yes | N90: 84001.5 | O90: Yes | P90: Completed | Q90: 46251 | R90: No | S90: Not Submitted | T90: Pending Tillman QC Form | U90: Pending Tillman QC Form | V90: 6969 | W90: 6980 | X90: =SUM(V90-W90) -> -11 | Y90: =IFERROR($W90/$V90, 0) -> 1.0015784 | Z90: 46265 | AA90: 46275 | AB90: 1 | AC90: 1 | AD90: 1 | AE90: 7/31 NTP Package Received. | AF90: Gig list sent to contractor.
A91: D-HLC539 | B91: Pinellas | C91: 46322 | D91: Sosa Line | E91: 46283 | F91: Johnnie Williams | H91: 64 | I91: Completed on Track | J91: Received | L91: N/A | M91: Yes | N91: 88399.4 | O91: Yes | P91: Completed | Q91: 46287 | R91: No | S91: Not Submitted | T91: Pending Tillman QC Form | U91: Pending Tillman QC Form | V91: 6946 | W91: 6979 | X91: =SUM(V91-W91) -> -33 | Y91: =IFERROR($W91/$V91, 0) -> 1.0047509 | Z91: 46294 | AA91: 46300 | AB91: 0 | AC91: 0 | AD91: 0 | AE91: 8/25 NTP Package and PO Received.
A92: FB-HLC512 | B92: Pinellas | C92: 46290 | D92: Brothers | E92: 46223 | F92: Anthony Adum | G92: PPM112758 | H92: 0 | I92: Completed on Track | J92: Received | L92: 46225 | M92: Yes | N92: 71505.7 | O92: Yes | P92: Completed | Q92: 46225 | R92: No | S92: Not Submitted | T92: Pending Tillman QC Form | U92: Pending Tillman QC Form | V92: 5642 | W92: 5699 | X92: =SUM(V92-W92) -> -57 | Y92: =IFERROR($W92/$V92, 0) -> 1.0101028 | Z92: 46241 | AA92: 46274 | AB92: 0 | AC92: 0 | AD92: 0 | AE92: 7/13 NTP Package Received | AF92: Passed QC. Working on COP
A93: FB-HLC519 | B93: Pinellas | C93: 46290 | D93: Power Connect | E93: 46219 | F93: Matthew Nunes | G93: PPM112720 | H93: 0 | I93: Completed on Track | J93: Received | L93: N/A | M93: Yes | N93: 25127.05 | O93: Yes | P93: Completed | Q93: 46220 | R93: No | S93: Not Submitted | T93: Pending Tillman QC Form | U93: Pending Tillman QC Form | V93: 2013 | W93: 2039 | X93: =SUM(V93-W93) -> -26 | Y93: =IFERROR($W93/$V93, 0) -> 1.012916 | Z93: 46273 | AA93: 46274 | AB93: 0 | AC93: 0 | AD93: 0 | AE93: 7/14 NTP Package Received | AF93: Actualized. Will submit 10/2
A94: D-HSF308 | B94: Port Charlotte | C94: 46234 | D94: HD Cable | E94: 46210 | F94: Joshua Wheatcroft | H94: 68 | I94: Completed on Track | J94: Received | L94: N/A | M94: Yes | N94: 62074 | O94: Yes | P94: Completed | Q94: 46211 | R94: No | S94: Not Submitted | T94: 8/28 Failed QC | U94: 8/28 Failed QC | V94: 5495 | W94: 5365 | X94: =SUM(V94-W94) -> 130 | Y94: =IFERROR($W94/$V94, 0) -> 0.97634213 | Z94: 46223 | AA94: 46234 | AB94: 0 | AC94: 0 | AD94: 0 | AE94: 6/17 NTP Package Received. | AF94: working on change orders
A95: D-HSF320 | B95: Port Charlotte | C95: 46172 | D95: GN Systems | E95: 46142 | F95: Joshua Wheatcroft | H95: 79 | I95: Completed on Track | J95: Received | L95: N/A | M95: Yes | N95: 73533 | O95: Yes | P95: Completed | Q95: 46147 | R95: Yes | S95: 46190 | T95: 46244 | U95: 46244 | V95: 5974 | W95: 5911 | X95: =SUM(V95-W95) -> 63 | Y95: =IFERROR($W95/$V95, 0) -> 0.9894543 | Z95: 46174 | AA95: 46176 | AB95: 0 | AC95: 0 | AD95: 0 | AE95: 4/29 NTP Package Received. | AF95: Pending bore logs from lopez
A96: D-HSF322 | B96: Port Charlotte | C96: 46172 | D96: Lopez Underground | E96: 46210 | F96: Joshua Wheatcroft | H96: 89 | I96: Completed on Track | J96: Received | L96: N/A | M96: Yes | N96: 81150 | O96: Yes | P96: Completed | Q96: 46148 | R96: No | S96: Not Submitted | T96: Pending Tillman QC Form | U96: Pending Tillman QC Form | V96: 6825 | W96: 6741 | X96: =SUM(V96-W96) -> 84 | Y96: =IFERROR($W96/$V96, 0) -> 0.98769231 | Z96: 46247 | AA96: 46258 | AB96: 0 | AC96: 0 | AD96: 0 | AE96: 4/21 NTP Received. | AF96: Pending bore logs from lopez
A97: D-HSF402 | B97: Port Charlotte | C97: 46295 | D97: GN Systems | E97: 46254 | F97: Brenton Copelin | G97: FM113092 | H97: 78 | I97: Completed on Track | J97: Received | L97: N/A | M97: Yes | N97: 72242 | O97: Yes | P97: Completed | Q97: 46274 | R97: No | S97: Not Submitted | T97: Pending Tillman QC Form | U97: Pending Tillman QC Form | V97: 5890 | W97: 5834 | X97: =SUM(V97-W97) -> 56 | Y97: =IFERROR($W97/$V97, 0) -> 0.99049236 | Z97: 46289 | AA97: 46302 | AB97: 0 | AC97: 0 | AD97: 0 | AE97: 7/24 PO Received.
A98: D-HSF419 | B98: Port Charlotte | C98: 46295 | D98: GN Systems | E98: 46254 | F98: Brenton Copelin | G98: FM113094 | H98: 49 | I98: Completed on Track | J98: Received | L98: N/A | M98: Yes | N98: 62657 | O98: Yes | P98: Completed | Q98: 46274 | R98: No | S98: Not Submitted | T98: Pending Tillman QC Form | U98: Pending Tillman QC Form | V98: 5185 | W98: 4940 | X98: =SUM(V98-W98) -> 245 | Y98: =IFERROR($W98/$V98, 0) -> 0.95274831 | Z98: 46286 | AA98: 46287 | AB98: 0 | AC98: 0 | AD98: 0 | AE98: 7/31 NTP Package Received. | AF98: Just started. Not ready for QC
A99: FB-HSF304 | B99: Port Charlotte | C99: 46172 | D99: Lightspeed In-House | E99: 46140 | F99: Joshua Wheatcroft | H99: 0 | I99: Completed on Track | J99: Received | L99: N/A | M99: Yes | N99: 33518.7 | O99: Yes | P99: Completed | Q99: 46140 | R99: No | S99: Not Submitted | T99: Pending Tillman QC Form | U99: Pending Tillman QC Form | V99: 3693 | W99: 3896 | X99: =SUM(V99-W99) -> -203 | Y99: =IFERROR($W99/$V99, 0) -> 1.0549689 | Z99: 46146 | AA99: 46262 | AB99: 0 | AC99: 0 | AD99: 0 | AE99: 4/21 NTP Received. Failed Gig List Received From Tillman on 8/28. | AF99: change orders needed
A100: FB-HNP133 | B100: St Petersburg | C100: 45991 | D100: Lightspeed In-House | E100: 45779 | F100: Johnnie Williams | G100: PPM92370 | H100: 0 | I100: Completed on Track | J100: Received | L100: 45742 | M100: Yes | N100: 23800.25 | O100: Yes | P100: Completed | Q100: 45743 | R100: Yes | S100: 46134 | T100: 46196 | U100: Pending Tillman QC Form | V100: 1697 | W100: 1815 | X100: =SUM(V100-W100) -> -118 | Y100: =IFERROR($W100/$V100, 0) -> 1.0695345 | Z100: 45791 | AA100: 45968 | AB100: 1 | AC100: 0 | AD100: 0 | AE100: 4.22 JW // Requested PH1 QC | AF100: Missing Photos
...

Sheet Invoiced-Paid Out-Pending
A1: NTP Number | B1: AREA | C1: SOW TSD Date | D1: Vendor Assignment | E1: Date Assigned | F1: Assigned Supervisor | G1: Penguin ID | H1: HHP | I1: On Track or In Jeopardy | J1: Permit Status | K1: Door Tag Date | L1: SOW Received | M1: SOW Estimated Cost | N1: Invoice Amount Paid | O1: Phase 2 Invoice | P1: Total Invoice | Q1: NTP Received | R1: Constuction Status | S1: Locate Date | T1: Footage UG | U1: Actual Redline Completed Footage UG | V1: UG Percentage Complete | W1: Construction Start Date | X1: Fiber Placement Percentage Complete | Y1: Splicing Percentage Complete | Z1: Construction Total Percent Complete | AA1: QC Received From Tillman | AB1: Phase 2 QC Received From Tillman | AC1: Comments
A2: BHT-FLX-01 | B2: Bradenton | C2: 46172 | D2: Baseline | E2: 45897 | F2: Cody | H2: 0 | I2: Completed on Track | J2: Received | K2: 45891 | L2: Yes | M2: 184994.5 | N2: 159271.5 | O2: 39954.2 | P2: 199225.7 | Q2: Yes | R2: Completed | S2: 45891 | T2: 14790 | U2: 14871 | V2: 1.01 | W2: 45910 | X2: 1 | Y2: 1 | Z2: 1 | AA2: 46064 | AB2: 46064 | AC2: 8/20 Project Received.
A3: BHT-FLX-02 | B3: Bradenton | C3: 46172 | D3: GN Systems | E3: 46077 | F3: Cody | G3: MAN108635 | H3: 0 | I3: Completed on Track | J3: Received | K3: N/A | L3: Yes | M3: 12404.9 | N3: 11793.85 | O3: 8457.75 | P3: 20251.6 | Q3: Yes | R3: Completed | S3: 46077 | T3: 1111 | U3: 1163 | V3: 1.05 | W3: 46097 | X3: 1 | Y3: 1 | Z3: 1 | AA3: 46104 | AB3: 46104 | AC3: 2/12 Print Attached To Permit, Pending Fiber Splicing Documention.
A4: BHT-FOE-03 | B4: Bradenton | C4: 45960 | D4: North Path | E4: 45852 | F4: Joshua | G4: MAN97574 | H4: 0 | I4: Completed on Track | J4: Received | K4: 45852 | L4: Yes | M4: 42837.2 | N4: 36701.2 | P4: 36701.2 | Q4: Yes | R4: Completed | S4: 45852 | T4: 3432 | U4: 3519 | V4: 1.03 | W4: 45866 | X4: 1 | Y4: 1 | Z4: 1 | AA4: 46148 | AB4: Pending Tillman QC Form | AC4: 5/7 Phase 2 Failed Gig List Received From Tillman.
A5: BHU-FAL-01-E | B5: Bradenton | C5: 45960 | D5: HAS Global / Lightspeed | E5: 45909 | F5: Betsy | G5: MAN101752 | H5: 0 | I5: Completed on Track | J5: Received | K5: 45905 | L5: Yes | M5: 98170.1 | N5: 98170.1 | P5: 98170.1 | Q5: Yes | R5: Completed | S5: 45908 | T5: 9086 | U5: 8945 | V5: 0.98 | W5: 45922 | X5: 1 | Y5: 1 | Z5: 1 | AA5: 46195 | AB5: 46226 | AC5: 8/28 Permit Received With NTP Package. Assigned to HAS Global. 9.24 new design recieved and whitelined. Pending locates/ 1/13 CX Construction Complete...144F Placed. Phase 1 and 2 Failed Gig List Uploaded On 2/12/2026.
A6: BHU-FAL-01-W | B6: Bradenton | C6: 46172 | D6: Lightspeed In-House | E6: 45905 | F6: Betsy | H6: 0 | I6: Completed on Track | J6: Received | K6: 45943 | L6: Yes | M6: 2167.3 | N6: 7455 | O6: 64855.05 | P6: 72310.05 | Q6: Yes | R6: Completed | S6: 45908 | T6: 158 | U6: 395 | V6: =IFERROR($W6/$V6, 0) -> 2.5 | W6: 10/1/3/2025 | X6: 1 | Y6: 1 | Z6: 1 | AA6: 46136 | AB6: 46136 | AC6: 8/22 Project Received With Permit. 9-18-25 on hold per tillman needs redesign. 9/22 Package 10 Permit Received. 9.24 new design recieved and whitelined. Pending locates.
A7: BHU-FAL-01-W-2 | B7: Bradenton | C7: 46172 | D7: Lightspeed In-House | E7: 45905 | F7: Betsy | H7: 0 | I7: Completed on Track | J7: Received | K7: 45943 | L7: Yes | M7: 2167.3 | N7: 1930.3 | O7: 1737.5 | P7: 3667.8 | Q7: Yes | R7: Completed | S7: 45908 | T7: 279 | U7: 279 | V7: =IFERROR($W7/$V7, 0) -> 1 | W7: 10/1/3/2025 | X7: 1 | Y7: 1 | Z7: 1 | AA7: 46133 | AB7: 46133 | AC7: 8/22 Project Received With Permit. 9-18-25 on hold per tillman needs redesign. 9/22 Package 10 Permit Received. 9.24 new design recieved and whitelined. Pending locates.
A8: BHUD-FLX-04-E | B8: Bradenton | C8: 46172 | D8: GN Systems | E8: 46114 | F8: Cody | G8: MAN104351 | H8: 0 | I8: Completed on Track | J8: Received | K8: N/A | L8: Yes | M8: 82825 | N8: 73316 | P8: 73316 | Q8: Yes | R8: Completed | S8: 45965 | T8: 6210 | U8: 6217 | V8: 1 | W8: 46128 | X8: 1 | Y8: 1 | Z8: 1 | AA8: 46198 | AB8: 46224 | AC8: 9/29 Package 10 Permit.
A9: BHUD-FOE-02-W | B9: Bradenton | C9: 45868 | D9: Power Connect | E9: 45716 | F9: Joshua | G9: MAN92070 | H9: 0 | I9: Completed on Track | J9: Received | K9: 45716 | L9: Yes | M9: 64932.55 | N9: 69110.8 | P9: 69110.8 | Q9: Yes | R9: Completed | S9: 45721 | T9: 5151 | U9: 5207 | V9: 1.01 | W9: 45748 | X9: 1 | Y9: 1 | Z9: 1 | AA9: Legacy Project | AB9: Legacy Project
A10: BHZD-FLX-04-W | B10: Bradenton | C10: 46172 | D10: GN Systems | E10: 46114 | F10: Cody | G10: MAN104071 | H10: 0 | I10: Completed on Track | J10: Received | K10: N/A | L10: Yes | M10: 34736.85 | N10: 30641.35 | P10: 30641.35 | Q10: Yes | R10: Completed | S10: 45965 | T10: 2601 | U10: 2890 | V10: =IFERROR($W10/$V10, 0) -> 1.1111111 | W10: 45973 | X10: 1 | Y10: 1 | Z10: 1 | AA10: 46195 | AB10: 46177 | AC10: 10/1 ntp received
A11: BHZD-FOE-03-W | B11: Bradenton | C11: 45991 | D11: Raven | E11: 45707 | F11: Joshua | G11: PPM89496 | H11: 0 | I11: Completed on Track | J11: Received | K11: 45708 | L11: Yes | M11: 87944.4 | N11: 99159.12 | P11: 99159.12 | Q11: Yes | R11: Completed | S11: 45709 | T11: 7008 | U11: 7258 | V11: 1.04 | W11: 45747 | X11: 1 | Y11: 1 | Z11: 1 | AA11: 46072 | AB11: 46072 | AC11: Needs soft dig to finish. Locates expired and re-called
A12: D-HLR203 | B12: Bradenton | C12: 45991 | D12: North Path | E12: 45950 | F12: Joshua | H12: 82 | I12: Completed on Track | J12: Received | K12: 45902 | L12: Yes | M12: 87830 | N12: 72935 | O12: 12266.1 | P12: 85201.1 | Q12: Yes | R12: Completed | S12: 45898 | T12: 7022 | U12: 7002 | V12: 1 | W12: 45958 | X12: 1 | Y12: 1 | Z12: 1 | AA12: 46134 | AB12: 46134 | AC12: 8/27 Permit Received With NTP Package.
A13: D-HLR204 | B13: Bradenton | C13: 46099 | D13: Lightspeed In-House | E13: 45959 | F13: Betsy | G13: MAN103593 | H13: 69 | I13: Completed on Track | J13: Received | K13: 45925 | L13: Yes | M13: 51632 | N13: 39035 | P13: 39035 | Q13: Yes | R13: Completed | S13: 45932 | T13: 3997 | U13: 3937 | V13: =IFERROR($W13/$V13, 0) -> 0.98498874 | W13: 45960 | X13: 1 | Y13: 1 | Z13: 1 | AA13: 46139 | AB13: 46139 | AC13: 4-28 JW // COP Submitted - 9/15 Pending Permit. 9/22 Package 10 Permit Received. was gold gate but due to damages we dismissed them./ 2/3 CX Construction Continues--FDH Placed.
A14: D-HLR205 | B14: Bradenton | C14: 45989 | D14: North Path | E14: 45964 | F14: Joshua | G14: MAN104002 | H14: 74 | I14: Completed on Track | J14: Received | K14: 45932 | L14: Yes | M14: 47064 | N14: 43955 | P14: 43955 | Q14: Yes | R14: Completed | S14: 45932 | T14: 4716 | U14: 4731 | V14: =IFERROR($W14/$V14, 0) -> 1.0031807 | W14: 45971 | X14: 1 | Y14: 1 | Z14: 1 | AA14: 46140 | AB14: 46140 | AC14: 9/15 Pending Permit. 9/22 Package 10 Permit Received.
A15: D-HLR207 | B15: Bradenton | C15: 45960 | D15: North Path | E15: 45930 | F15: Joshua | H15: 80 | I15: Completed on Track | J15: Received | K15: 45902 | L15: Yes | M15: 90173 | N15: 73132 | P15: 73132 | Q15: Yes | R15: Completed | S15: 45898 | T15: 7009 | U15: 6948 | V15: 0.99 | W15: 45944 | X15: 1 | Y15: 1 | Z15: 1 | AA15: 46134 | AB15: 46134 | AC15: 8/27 Permit Received With NTP Package.
A16: D-HLR208 | B16: Bradenton | C16: 45999 | D16: GN Systems | E16: 45964 | F16: Cody | G16: MAN104067 | H16: 81 | I16: Completed on Track | J16: Received | K16: N/A | L16: Yes | M16: 68962 | N16: 53757 | O16: 11950.2 | P16: 65707.2 | Q16: Yes | R16: Completed | S16: 45932 | T16: 5333 | U16: 5339 | V16: 1 | W16: 46044 | X16: 1 | Y16: 1 | Z16: 1 | AA16: 46128 | AB16: 46128 | AC16: 9/15 Pending Permit. 9/22 Package 10 Permit Received./ 1/22 CX Construction Started/
A17: D-HLR210 | B17: Bradenton | C17: 45960 | D17: GN Systems | E17: 45950 | F17: Cody | H17: 80 | I17: Completed on Track | J17: Received | K17: 45905 | L17: Yes | M17: 66674.3 | N17: 50364.3 | O17: 19125.8 | P17: 69490.1 | Q17: Yes | R17: Completed | S17: 45922 | T17: 5285 | U17: 5305 | V17: 1 | W17: 45954 | X17: 1 | Y17: 1 | Z17: 1 | AA17: 45982 | AB17: 45982 | AC17: 8/28 Permit Received With NTP Package.
A18: D-HLR211 | B18: Bradenton | C18: 45960 | D18: GN Systems | E18: 45937 | F18: Cody | H18: 82 | I18: Completed on Track | J18: Received | K18: 45903 | L18: Yes | M18: 93666.75 | N18: 78401.25 | O18: 15459.55 | P18: 93860.8 | Q18: Yes | R18: Completed | S18: 45897 | T18: 7883 | U18: 7909 | V18: 1 | W18: 45945 | X18: 1 | Y18: 1 | Z18: 1 | AA18: 46079 | AB18: 46079 | AC18: 8/27 Permit Received With NTP Package.
A19: D-HLR212 | B19: Bradenton | C19: 46099 | D19: North Path | E19: 45975 | F19: Joshua | G19: MAN104535 | H19: 48 | I19: Completed on Track | J19: Received | K19: N/A | L19: Yes | M19: 39064 | N19: 30327 | P19: 30327 | Q19: Yes | R19: Completed | S19: 45932 | T19: 2982 | U19: 3061 | V19: 1.02 | W19: 46104 | X19: 1 | Y19: 1 | Z19: 1 | AA19: 46140 | AB19: 46140 | AC19: 4-28 JW // HAS BOTH PASSING QAQC FORMS - COP WIP 9/15 Pending Permit. 10/2 permit added to site tracker on 9/25 downloaded and put in sharepoint folder
A20: D-HOE102 | B20: Bradenton | C20: 45807 | D20: MTX | E20: 45706 | F20: Joshua | G20: MAN89819 | H20: 56 | I20: Completed on Track | J20: Received | K20: 45701 | L20: Yes | M20: 55089 | N20: 57509 | P20: 57509 | Q20: Yes | R20: Completed | S20: 45709 | T20: 4836 | U20: 5095 | V20: =IFERROR(Table4[[#This Row],[Actual Redline Completed Footage UG]]/Table4[[#This Row],[Footage UG]], 0) -> 1.0535567 | W20: 45741 | X20: 1 | Y20: 1 | Z20: 1 | AA20: 45926 | AB20: 45926 | AC20: 4-29-25 Was MTX need to reassign.
A21: D-HOE206 | B21: Bradenton | C21: 45991 | D21: Power Connect - In-House | E21: 45716 | F21: Betsy | G21: PPM92353 | H21: 31 | I21: Completed on Track | J21: Received | K21: 45716 | L21: Yes | M21: 28777 | N21: 28496.8 | P21: 28496.8 | Q21: Yes | R21: Completed | S21: 45716 | T21: 2315 | U21: 2279 | V21: 0.98 | W21: 45862 | X21: 1 | Y21: 1 | Z21: 1 | AA21: 45993 | AB21: 45993
A22: D-HOE302 | B22: Bradenton | C22: 45991 | D22: North Path | E22: 45880 | F22: Joshua | G22: MAN98158 | H22: 57 | I22: Completed on Track | J22: Received | K22: 45863 | L22: Yes | M22: 49223.7 | N22: 37040.5 | O22: 10534.7 | P22: 47575.2 | Q22: Yes | R22: Completed | S22: 45863 | T22: 3649 | U22: 3557 | V22: 0.97 | W22: 45916 | X22: 1 | Y22: 1 | Z22: 1 | AA22: 46055 | AB22: Pending Tillman QC Form | AC22: 10.10.25 changed total drill footage to 3394 as per walked out footages
A23: D-HOE306 | B23: Bradenton | C23: 45991 | D23: North Path | E23: 45880 | F23: Joshua | G23: MAN99374 | H23: 75 | I23: Completed on Track | J23: Received | K23: 45879 | L23: Yes | M23: 68151.75 | N23: 54018.75 | P23: 54018.75 | Q23: Yes | R23: Completed | S23: 45881 | T23: 5362 | U23: 5236 | V23: 0.98 | W23: 45926 | X23: 1 | Y23: 1 | Z23: 1 | AA23: 46147 | AB23: 46147 | AC23: 5/5 QC Forms Received From Tillman For Phase 1 and 2.
A24: D-HOE501 | B24: Bradenton | C24: 46107 | D24: North Path | E24: 45980 | F24: Cody | G24: MAN104528 | H24: 82 | I24: Completed on Track | J24: Received | K24: N/A | L24: Yes | M24: 56294 | N24: 41907 | O24: 19111.55 | P24: 61018.55 | Q24: Yes | R24: Completed | S24: 45981 | T24: 4146 | U24: 4184 | V24: 1.01 | W24: 46084 | X24: 1 | Y24: 1 | Z24: 1 | AA24: 46125 | AB24: 46125 | AC24: 12/18 CX Construction.
A25: D-HOE502 | B25: Bradenton | C25: 46107 | D25: North Path | E25: 46009 | F25: Cody | G25: MAN104531 | H25: 54 | I25: Completed on Track | J25: Received | K25: 46077 | L25: Yes | M25: 58240 | N25: 47101 | P25: 47101 | Q25: Yes | R25: Completed | S25: 46077 | T25: 3599 | U25: 3613 | V25: 1 | W25: 46085 | X25: 1 | Y25: 1 | Z25: 1 | AA25: 46125 | AB25: 46125 | AC25: 10/17 Permit Received With NTP Package./ 3/4 CX Construction Started
A26: FB-HAL101 | B26: Bradenton | C26: 46172 | D26: North Path | E26: 46142 | F26: Cody | G26: MAN108654 | H26: 0 | I26: Completed on Track | J26: Received | K26: N/A | L26: Yes | M26: 36998.55 | N26: 31640.05 | P26: 31640.05 | Q26: Yes | R26: Completed | S26: 46143 | T26: 2944 | U26: 2988 | V26: =IFERROR($W26/$V26, 0) -> 1.0149457 | W26: 46155 | X26: 1 | Y26: 1 | Z26: 1 | AA26: 46176 | AB26: 46176
A27: FB-HAL113 | B27: Bradenton | C27: 46172 | D27: North Path | E27: 46101 | F27: Cody | G27: MAN108657 | H27: 0 | I27: Completed on Track | J27: Received | K27: N/A | L27: Yes | M27: 49932.8 | N27: 43666.8 | O27: 11479.55 | P27: 55146.35 | Q27: Yes | R27: Completed | S27: 46077 | T27: 4048 | U27: 4028 | V27: =IFERROR($W27/$V27, 0) -> 0.99505929 | W27: 46111 | X27: 1 | Y27: 1 | Z27: 1 | AA27: 46150 | AB27: 46150
A28: FB-HAL177 | B28: Bradenton | C28: 46172 | D28: North Path | E28: 46101 | F28: Cody | G28: MAN108659 | H28: 0 | I28: Completed on Track | J28: Received | K28: N/A | L28: Yes | M28: 18270.8 | N28: 15994.8 | P28: 15994.8 | Q28: Yes | R28: Completed | S28: 46077 | T28: 1388 | U28: 1360 | V28: =IFERROR($W28/$V28, 0) -> 0.97982709 | W28: 46118 | X28: 1 | Y28: 1 | Z28: 1 | AA28: 46150 | AB28: 46150 | AC28: 11/28 FDOT Permit Received.
A29: FB-HAL175 | B29: Bradenton | C29: 46172 | D29: GN Systems | E29: 46055 | F29: Cody | G29: MAN104100 | H29: 0 | I29: Completed on Track | J29: Received | K29: N/A | L29: Yes | M29: 11518.95 | N29: 10003.35 | P29: 10003.35 | Q29: Yes | R29: Completed | S29: 46056 | T29: 881 | U29: 817 | V29: 0.93 | W29: 46063 | X29: 1 | Y29: 1 | Z29: 1 | AA29: 46072 | AB29: 46072 | AC29: 9/16 Pending Permit. 1/30 Permit Received./ 2/10 CX Construction Started/ 2/12 CX Complete--96F Placed, Pending Splicing.
A30: FB-HAL176 | B30: Bradenton | C30: 46112 | D30: North Path | E30: 46125 | F30: Cody | G30: MAN104756 | H30: 20 | I30: Completed on Track | J30: Received | K30: N/A | L30: Yes | M30: 1733.25 | N30: 1381.75 | P30: 1381.75 | Q30: Yes | R30: Completed | S30: 46128 | T30: 145 | U30: 145 | V30: 1 | W30: 46156 | X30: 1 | Y30: 1 | Z30: 1 | AA30: 6/3 Failed QC | AB30: 46176 | AC30: 11/5 Permit Package 11 Received./
